Workbook

Sheet Table 1
B2: Table 1. Summary Statistics for LEHD Samples
E4: Full sample | F4: Industry stayers | G4: Industry switchers | H4: Event study sample
E5: -1 | F5: -2 | G5: -3 | H5: -4
B6: Mean quarterly earnings | D6: ='disclosed1-1'!A7 -> lne | E6: =VALUE('disclosed1-1'!B7) -> 15510 | F6: =VALUE('disclosed1-1'!C7) -> 16050 | G6: =VALUE('disclosed1-1'!D7) -> 14630 | H6: =VALUE('disclosed1-1'!E7) -> 16350
B7: (standard deviation) | E7: =VALUE('disclosed1-1'!B8) -> -18020 | F7: =VALUE('disclosed1-1'!C8) -> -19710 | G7: =VALUE('disclosed1-1'!D8) -> -14860 | H7: =VALUE('disclosed1-1'!E8) -> -45670
B8: Mean age | D8: ='disclosed1-1'!A9 -> age | E8: =VALUE('disclosed1-1'!B9) -> 42.43 | F8: =VALUE('disclosed1-1'!C9) -> 44.04 | G8: =VALUE('disclosed1-1'!D9) -> 39.85 | H8: =VALUE('disclosed1-1'!E9)*40 +40 -> 40.04928
E9: =VALUE('disclosed1-1'!B10) -> -10.78 | F9: =VALUE('disclosed1-1'!C10) -> -10.71 | G9: =VALUE('disclosed1-1'!D10) -> -10.39 | H9: =VALUE('disclosed1-1'!E10)*40 -> -10.524
B10: Fraction female | D10: ='disclosed1-1'!A11 -> Gender | E10: =VALUE('disclosed1-1'!B11) -> 0.4734 | F10: =VALUE('disclosed1-1'!C11) -> 0.4839 | G10: =VALUE('disclosed1-1'!D11) -> 0.4565 | H10: =VALUE('disclosed1-1'!E11) -> 0.4629
E11: =VALUE('disclosed1-1'!B12) -> -0.4993 | F11: =VALUE('disclosed1-1'!C12) -> -0.4997 | G11: =VALUE('disclosed1-1'!D12) -> -0.4981 | H11: =VALUE('disclosed1-1'!E12) -> -0.4986
B12: Fraction foreign born | D12: ='disclosed1-1'!A13 -> forborn | E12: =VALUE('disclosed1-1'!B13) -> 0.1607 | F12: =VALUE('disclosed1-1'!C13) -> 0.1632 | G12: =VALUE('disclosed1-1'!D13) -> 0.1566 | H12: =VALUE('disclosed1-1'!E13) -> 0.143
E13: =VALUE('disclosed1-1'!B14) -> -0.3672 | F13: =VALUE('disclosed1-1'!C14) -> -0.3695 | G13: =VALUE('disclosed1-1'!D14) -> -0.3634 | H13: =VALUE('disclosed1-1'!E14) -> -0.3501
B14: Hispanic | D14: ='disclosed1-1'!A15 -> hisp | E14: =VALUE('disclosed1-1'!B15) -> 0.1334 | F14: =VALUE('disclosed1-1'!C15) -> 0.1295 | G14: =VALUE('disclosed1-1'!D15) -> 0.1396 | H14: =VALUE('disclosed1-1'!E15) -> 0.1228
E15: =VALUE('disclosed1-1'!B16) -> -0.34 | F15: =VALUE('disclosed1-1'!C16) -> -0.3358 | G15: =VALUE('disclosed1-1'!D16) -> -0.3466 | H15: =VALUE('disclosed1-1'!E16) -> -0.3282
B16: Number of CZs in which observed:
C17: 1 | D17: ='disclosed1-1'!A17 -> czcnt1 | E17: =VALUE('disclosed1-1'!B17) -> 0.786 | F17: =VALUE('disclosed1-1'!C17) -> 0.824 | G17: =VALUE('disclosed1-1'!D17) -> 0.7248 | H17: =VALUE('disclosed1-1'!E17) -> 0.9993
E18: =VALUE('disclosed1-1'!B18) -> -0.4101 | F18: =VALUE('disclosed1-1'!C18) -> -0.3808 | G18: =VALUE('disclosed1-1'!D18) -> -0.4466 | H18: =VALUE('disclosed1-1'!E18) -> -0.02634
C19: 2 | D19: ='disclosed1-1'!A19 -> czcnt2 | E19: =VALUE('disclosed1-1'!B19) -> 0.1734 | F19: =VALUE('disclosed1-1'!C19) -> 0.1434 | G19: =VALUE('disclosed1-1'!D19) -> 0.2218 | H19: =VALUE('disclosed1-1'!E19) -> 0.0006942
E20: =VALUE('disclosed1-1'!B20) -> -0.3786 | F20: =VALUE('disclosed1-1'!C20) -> -0.3504 | G20: =VALUE('disclosed1-1'!D20) -> -0.4154 | H20: =VALUE('disclosed1-1'!E20) -> -0.02634
C21: 3+ | D21: ='disclosed1-1'!A21 -> czcnt3 | E21: =VALUE('disclosed1-1'!B21) -> 0.04057 | F21: =VALUE('disclosed1-1'!C21) -> 0.03259 | G21: =VALUE('disclosed1-1'!D21) -> 0.05341 | H21: =VALUE('disclosed1-1'!E21) -> 0
E22: =VALUE('disclosed1-1'!B22) -> -0.1973 | F22: =VALUE('disclosed1-1'!C22) -> -0.1776 | G22: =VALUE('disclosed1-1'!D22) -> -0.2248 | H22: =VALUE('disclosed1-1'!E22) -> 0
B23: Number of industry switches (within CZs):
C24: 0 | D24: ='disclosed1-1'!A23 -> naics4dswitch0 | E24: =VALUE('disclosed1-1'!B23) -> 0.6166 | F24: 1 | G24: =VALUE('disclosed1-1'!D23) -> 0 | H24: =VALUE('disclosed1-1'!E23) -> 0
E25: =VALUE('disclosed1-1'!B24) -> -0.4862 | F25: =VALUE('disclosed1-1'!C24) -> 0 | G25: =VALUE('disclosed1-1'!D24) -> 0 | H25: =VALUE('disclosed1-1'!E24) -> 0
C26: 1 | D26: ='disclosed1-1'!A25 -> naics4dswitch1 | E26: =VALUE('disclosed1-1'!B25) -> 0.2607 | F26: =VALUE('disclosed1-1'!C25) -> 0 | G26: =VALUE('disclosed1-1'!D25) -> 0.68 | H26: 1
E27: =VALUE('disclosed1-1'!B26) -> -0.439 | F27: =VALUE('disclosed1-1'!C26) -> 0 | G27: =VALUE('disclosed1-1'!D26) -> -0.4665 | H27: =VALUE('disclosed1-1'!E26) -> 0
C28: 2+ | D28: ='disclosed1-1'!A27 -> naics4dswitch2 | E28: =VALUE('disclosed1-1'!B27) -> 0.1227 | F28: =VALUE('disclosed1-1'!C27) -> 0 | G28: =VALUE('disclosed1-1'!D27) -> 0.32 | H28: =VALUE('disclosed1-1'!E27) -> 0
E29: =VALUE('disclosed1-1'!B28) -> -0.3281 | F29: =VALUE('disclosed1-1'!C28) -> 0 | G29: =VALUE('disclosed1-1'!D28) -> -0.4665 | H29: =VALUE('disclosed1-1'!E28) -> 0
B30: Mean number of quarters observed | D30: ='disclosed1-1'!A29 -> qobserved | E30: =VALUE('disclosed1-1'!B29) -> 25.85 | F30: =VALUE('disclosed1-1'!C29) -> 27.19 | G30: =VALUE('disclosed1-1'!D29) -> 23.7 | H30: =VALUE('disclosed1-1'!E29) -> 10.01
B31: (standard deviation) | E31: =VALUE('disclosed1-1'!B30) -> -7.683 | F31: =VALUE('disclosed1-1'!C30) -> -7.757 | G31: =VALUE('disclosed1-1'!D30) -> -7.045 | H31: =VALUE('disclosed1-1'!E30) -> -0.2634
B32: Number of person-quarter obs. (millions) | D32: ='disclosed1-1'!A31 -> Observations | E32: =VALUE('disclosed1-1'!B31)/1000000 -> 2505 | F32: =VALUE('disclosed1-1'!C31)/1000000 -> 1544 | G32: =VALUE('disclosed1-1'!D31)/1000000 -> 960.4 | H32: =VALUE('disclosed1-1'!E31)/1000000 -> 87.39
B33: Number of unique people (millions) | D33: ='disclosed1-1'!A32 -> Unique PIKs | E33: =VALUE('disclosed1-1'!B32)/1000000 -> 111.7 | F33: =VALUE('disclosed1-1'!C32)/1000000 -> 65.67 | G33: =VALUE('disclosed1-1'!D32)/1000000 -> 46.05 | H33: =VALUE('disclosed1-1'!E32)/1000000 -> 8.736
B35: Notes: See text for discussion of sample derivation. "Industry switchers" in column 3 are people observed in more than one industry within a single CZ. "Industry stayers" in column 2 may be observed in multiple CZ's, potentially in different industries in each, but are observed in only one industry per CZ. Event study sample is comprised of workers who switch industries exactly once within a CZ, and are observed for at least five continuous quarters within the CZ before and after the switch.

Sheet table2
B2: Table 2: Mean Wages, Estimated Wage Premiums, and Estimated Worker Skills for 2-digit Industries
D3: Based on Data from LEHD | I3: Based on Data from ACS
D4: Percent of | E4: Mean | F4: Mean | G4: Mean | J4: Mean | K4: Mean
D5: Workforce | E5: Log | F5: Worker | G5: Industry | J5: Worker | K5: Industry
E6: Earnings | F6: Skill | G6: Premium | J6: Skill | K6: Premium
F7: (Mean | I7: Mean Log | J7: (Mean
B8: NAICS | C8: Industry Description | F8: Zero) | I8: Wage | J8: Zero)
D9: (1) | E9: (2) | F9: (3) | G9: (4) | I9: (5) | J9: (5) | K9: (6)
B10: ='t2'!A2 -> 11 | C10: Agriculture, Forestry, Fishing | D10: ='t2'!D2 -> 0.0057974318 | E10: ='t2'!E2 -> 9.119638 | F10: ='t2'!F2 -> -0.23639491 | G10: ='t2'!G2 -> 0.16001994 | I10: =+#REF! -> #REF! | J10: ='t2'!L2 -> -0.19985279 | K10: ='t2'!K2 -> 0.087610438
B11: ='t2'!A3 -> 21 | C11: Mining, Quarrying, Oil and Gas | D11: ='t2'!D3 -> 0.0069294511 | E11: ='t2'!E3 -> 9.9076929 | F11: ='t2'!F3 -> 0.078292206 | G11: ='t2'!G3 -> 0.62160186 | I11: =+#REF! -> #REF! | J11: ='t2'!L3 -> -0.020007471 | K11: ='t2'!K3 -> 0.6229651
B12: ='t2'!A4 -> 22 | C12: Utilities | D12: ='t2'!D4 -> 0.008941575 | E12: ='t2'!E4 -> 9.8835471 | F12: ='t2'!F4 -> 0.1957944 | G12: ='t2'!G4 -> 0.48822169 | I12: =+#REF! -> #REF! | J12: ='t2'!L4 -> 0.1092599 | K12: ='t2'!K4 -> 0.60447341
B13: ='t2'!A5 -> 23 | C13: Construction | D13: ='t2'!D5 -> 0.051243287 | E13: ='t2'!E5 -> 9.4804554 | F13: ='t2'!F5 -> 0.018735725 | G13: ='t2'!G5 -> 0.25197944 | I13: =+#REF! -> #REF! | J13: ='t2'!L5 -> -0.058517601 | K13: ='t2'!K5 -> 0.35374469
B14: ='t2'!A6 -> 31 | C14: Manufacturing | D14: ='t2'!D6 -> 0.12045356 | E14: ='t2'!E6 -> 9.4966835 | F14: ='t2'!F6 -> -0.054122381 | G14: ='t2'!G6 -> 0.35077908 | I14: =+#REF! -> #REF! | J14: ='t2'!L6 -> 0.016122887 | K14: ='t2'!K6 -> 0.37315267
B15: ='t2'!A7 -> 42 | C15: Wholesale Trade | D15: ='t2'!D7 -> 0.05215393 | E15: ='t2'!E7 -> 9.5765202 | F15: ='t2'!F7 -> 0.080336347 | G15: ='t2'!G7 -> 0.29539186 | I15: =+#REF! -> #REF! | J15: ='t2'!L7 -> 0.032295261 | K15: ='t2'!K7 -> 0.34781817
B16: ='t2'!A8 -> 44 | C16: Retail Trade | D16: ='t2'!D8 -> 0.086937323 | E16: ='t2'!E8 -> 9.1359558 | F16: ='t2'!F8 -> -0.15786937 | G16: ='t2'!G8 -> 0.10734527 | I16: =+#REF! -> #REF! | J16: ='t2'!L8 -> -0.14028744 | K16: ='t2'!K8 -> 0.13417928
B17: ='t2'!A9 -> 48 | C17: Transportation and Warehousing | D17: ='t2'!D9 -> 0.040178798 | E17: ='t2'!E9 -> 9.4009981 | F17: ='t2'!F9 -> -0.045566775 | G17: ='t2'!G9 -> 0.24470794 | I17: =+#REF! -> #REF! | J17: ='t2'!L9 -> -0.014589984 | K17: ='t2'!K9 -> 0.30663061
B18: ='t2'!A10 -> 51 | C18: Information | D18: ='t2'!D10 -> 0.026018279 | E18: ='t2'!E10 -> 9.7745929 | F18: ='t2'!F10 -> 0.1897753 | G18: ='t2'!G10 -> 0.38970665 | I18: =+#REF! -> #REF! | J18: ='t2'!L10 -> 0.11969135 | K18: ='t2'!K10 -> 0.43130851
B19: ='t2'!A11 -> 52 | C19: Finance and Insurance | D19: ='t2'!D11 -> 0.056744289 | E19: ='t2'!E11 -> 9.6926854 | F19: ='t2'!F11 -> 0.17488569 | G19: ='t2'!G11 -> 0.31782429 | I19: =+#REF! -> #REF! | J19: ='t2'!L11 -> 0.11905921 | K19: ='t2'!K11 -> 0.5190739
B20: ='t2'!A12 -> 53 | C20: Real Estate and Rental and Leasing | D20: ='t2'!D12 -> 0.015188341 | E20: ='t2'!E12 -> 9.3916469 | F20: ='t2'!F12 -> -0.027557533 | G20: ='t2'!G12 -> 0.22311722 | I20: =+#REF! -> #REF! | J20: ='t2'!L12 -> 0.050885566 | K20: ='t2'!K12 -> 0.29658061
B21: ='t2'!A13 -> 54 | C21: Professional, Scientific, Tech. | D21: ='t2'!D13 -> 0.075251035 | E21: ='t2'!E13 -> 9.7950068 | F21: ='t2'!F13 -> 0.27015549 | G21: ='t2'!G13 -> 0.32803653 | I21: =+#REF! -> #REF! | J21: ='t2'!L13 -> 0.2577993 | K21: ='t2'!K13 -> 0.47749209
... B29: ='t2'!A21 -> 92 | C29: Public Administration | D29: ='t2'!D21 -> 0.056624118 | E29: ='t2'!E21 -> 9.4710006 | F29: ='t2'!F21 -> -0.010014789 | G29: ='t2'!G21 -> 0.2789326 | I29: =+#REF! -> #REF! | J29: ='t2'!L21 -> 0.12519775 | K29: ='t2'!K21 -> 0.42675492
B30: Weighted std. dev. across sectors | D30: -- | E30: ='t2'!E22 -> 0.22078065 | F30: ='t2'!F22 -> 0.13721281 | G30: ='t2'!G22 -> 0.10443362 | H30: -- | I30: 0.25 | J30: ='t2'!L22 -> 0.13770522 | K30: ='t2'!K22 -> 0.14892778
B32: Notes: See text for descriptions of samples used in LEHD (columns 1-4) and ACS (columns 5-6). Entry in column 3 is average of estimated person effects from AKM models fit by CZ, normalized to have mean zero across all workers. Entry in column 4 is average wage premium, based on person-quarter weighted average of establishment premiums from AKM models fit by CZ, and normalized to have mean 0 in restaurants and eating places (NAICS 7225). Entry in column 5 is mean of estimated wage index (Xθ) from cross sectional regression model, normalized to have mean zero across all workers. Entry in column 6 is mean of estimated industry effects for industries in the 2-digit sector from cross sectional regression model, normalized to have mean of 0.04 in accommodation and food services.

Sheet table3
F2: Table 3: Mean Wages, Estimated Wage Premiums, and Estimated Worker Skills for 3-digit manufacturing Industries
H3: Based on Data from LEHD | M3: Based on Data from ACS
H4: Percent of | I4: Mean | J4: Mean | K4: Mean | M4: Mean | N4: Mean
H5: Workforce | I5: Log | J5: Worker | K5: Industry | M5: Worker | N5: Industry
I6: Earnings | J6: Skill | K6: Premium | M6: Skill | N6: Premium
J7: (Mean | M7: (Mean
F8: NAICS | G8: Industry Description | J8: Zero) | M8: Zero)
H9: (1) | I9: (2) | J9: (3) | K9: (4) | M9: (5) | N9: (6)
F10: 311-2 | G10: Food and kindred products | H10: ='t3'!C2/SUM('t2'!$C$2:$C$21) -> 0.015261001 | I10: ='t3'!E2 -> 9.2838179 | J10: ='t3'!F2 -> -0.24407361 | K10: ='t3'!G2 -> 0.32482625 | M10: ='t3'!L2 -> -0.12964387 | N10: ='t3'!K2 -> 0.27415311
F11: 313-4 | G11: Textile mill products | H11: ='t3'!C3/SUM('t2'!$C$2:$C$21) -> 0.0020740046 | I11: ='t3'!E3 -> 9.1369249 | J11: ='t3'!F3 -> -0.29171222 | K11: ='t3'!G3 -> 0.22304441 | M11: ='t3'!L3 -> -0.1362257 | N11: ='t3'!K3 -> 0.22885813
F12: 315-6 | G12: Apparel and leather | H12: ='t3'!C4/SUM('t2'!$C$2:$C$21) -> 0.0011845181 | I12: ='t3'!E4 -> 9.0988959 | J12: ='t3'!F4 -> -0.22897443 | K12: ='t3'!G4 -> 0.1466246 | M12: ='t3'!L4 -> -0.12995601 | N12: ='t3'!K4 -> 0.14716405
F13: 321 | G13: Wood Products | H13: ='t3'!C5/SUM('t2'!$C$2:$C$21) -> 0.0031790758 | I13: ='t3'!E5 -> 9.2031955 | J13: ='t3'!F5 -> -0.22424467 | K13: ='t3'!G5 -> 0.2177352 | M13: ='t3'!L5 -> -0.10726997 | N13: ='t3'!K5 -> 0.21257707
F14: 322 | G14: Paper | H14: ='t3'!C6/SUM('t2'!$C$2:$C$21) -> 0.0040529923 | I14: ='t3'!E6 -> 9.5325463 | J14: ='t3'!F6 -> -0.095454685 | K14: ='t3'!G6 -> 0.42831864 | M14: ='t3'!L6 -> -0.0038604476 | N14: ='t3'!K6 -> 0.43684211
F15: 323 | G15: Printing and Related | H15: ='t3'!C7/SUM('t2'!$C$2:$C$21) -> 0.0042198708 | I15: ='t3'!E7 -> 9.282 | J15: ='t3'!F7 -> -0.12726025 | K15: ='t3'!G7 -> 0.2163 | M15: ='t3'!L7 -> -0.0018905663 | N15: ='t3'!K7 -> 0.26059794
F16: 324 | G16: Petroleum and Coal | H16: ='t3'!C8/SUM('t2'!$C$2:$C$21) -> 0.0013050859 | I16: ='t3'!E8 -> 10.05 | J16: ='t3'!F8 -> 0.21973975 | K16: ='t3'!G8 -> 0.6214 | M16: ='t3'!L8 -> 0.10419235 | N16: ='t3'!K8 -> 0.69355416
F17: 325 | G17: Chemicals | H17: ='t3'!C9/SUM('t2'!$C$2:$C$21) -> 0.0085846625 | I17: ='t3'!E9 -> 9.7771006 | J17: ='t3'!F9 -> 0.10552467 | K17: ='t3'!G9 -> 0.46533688 | M17: ='t3'!L9 -> 0.14170207 | N17: ='t3'!K9 -> 0.51985294
F18: 326 | G18: Plastics and Rubber | H18: ='t3'!C10/SUM('t2'!$C$2:$C$21) -> 0.0066935056 | I18: ='t3'!E10 -> 9.3204719 | J18: ='t3'!F10 -> -0.19119857 | K18: ='t3'!G10 -> 0.30308083 | M18: ='t3'!L10 -> -0.06159072 | N18: ='t3'!K10 -> 0.30486643
F19: 327 | G19: Nonmetallic Minerals | H19: ='t3'!C11/SUM('t2'!$C$2:$C$21) -> 0.0037898991 | I19: ='t3'!E11 -> 9.4204772 | J19: ='t3'!F11 -> -0.12425814 | K19: ='t3'!G11 -> 0.33743568 | M19: ='t3'!L11 -> -0.032979824 | N19: ='t3'!K11 -> 0.33702356
F20: 331 | G20: Primary Metals | H20: ='t3'!C12/SUM('t2'!$C$2:$C$21) -> 0.0041212608 | I20: ='t3'!E12 -> 9.565383 | J20: ='t3'!F12 -> -0.11686336 | K20: ='t3'!G12 -> 0.48025375 | M20: ='t3'!L12 -> -0.024083862 | N20: ='t3'!K12 -> 0.42135847
F21: 332 | G21: Fabricated Metals | H21: ='t3'!C13/SUM('t2'!$C$2:$C$21) -> 0.013563072 | I21: ='t3'!E13 -> 9.3863793 | J21: ='t3'!F13 -> -0.0951076 | K21: ='t3'!G13 -> 0.2831072 | M21: ='t3'!L13 -> -0.030013798 | N21: ='t3'!K13 -> 0.32188016
F22: 333 | G22: Machinery | H22: ='t3'!C14/SUM('t2'!$C$2:$C$21) -> 0.011335364 | I22: ='t3'!E14 -> 9.5432986 | J22: ='t3'!F14 -> -0.0010662206 | K22: ='t3'!G14 -> 0.34283593 | M22: ='t3'!L14 -> 0.040200993 | N22: ='t3'!K14 -> 0.39938101
F23: 334 | G23: Computer and Electronic | H23: ='t3'!C15/SUM('t2'!$C$2:$C$21) -> 0.01162281 | I23: ='t3'!E15 -> 9.8615 | J23: ='t3'!F15 -> 0.26058221 | K23: ='t3'!G15 -> 0.42112437 | M23: ='t3'!L15 -> 0.25900835 | N23: ='t3'!K15 -> 0.50987136
F24: 335 | G24: Electrical Equipment | H24: ='t3'!C16/SUM('t2'!$C$2:$C$21) -> 0.0039978984 | I24: ='t3'!E16 -> 9.4776484 | J24: ='t3'!F16 -> -0.063004307 | K24: ='t3'!G16 -> 0.34009203 | M24: ='t3'!L16 -> 0.042388741 | N24: ='t3'!K16 -> 0.37804139
... F27: 339 | G27: Miscellaneous | H27: ='t3'!C19/SUM('t2'!$C$2:$C$21) -> 0.0055992137 | I27: ='t3'!E19 -> 9.4247356 | J27: ='t3'!F19 -> -0.054513298 | K27: ='t3'!G19 -> 0.28289634 | M27: ='t3'!L19 -> 0.020442761 | N27: ='t3'!K19 -> 0.31435332
F28: Weighted std. dev. across sectors | H28: -- | I28: ='t3'!E20 -> 0.21787692 | J28: ='t3'!F20 -> 0.15339325 | K28: ='t3'!G20 -> 0.087248246 | M28: ='t3'!L20 -> 0.10943842 | N28: ='t3'!K20 -> 0.10914908
F30: Notes: See notes to Table 2.

Sheet Table4
B2: Table 4. Relationships Between Worker Skills and Industry Wage Premiums
E4: Based on LEHD | I4: Based on Linked LEHD and ACS
B5: Explanatory Variable:
E6: -1 | F6: -2 | G6: -3 | I6: -4 | J6: -5 | K6: -6 | L6: -7 | M6: -8
B8: Mean earnings in industry | E8: =VALUE('t4'!B5) -> 0.6185 | F8: =VALUE('t4'!C5) -> 0.3722
E9: =VALUE('t4'!B6) -> -0.0194 | F9: =VALUE('t4'!C6) -> -0.0183
B11: Industry premium | G11: =VALUE('t4'!D8) -> 0.9012 | I11: =VALUE('t4'!E8) -> 0.9005 | K11: =VALUE('t4'!G8) -> 0.3299 | L11: =VALUE('t4'!H8) -> 0.6587 | M11: =VALUE('t4'!I8) -> 0.2418
G12: =VALUE('t4'!D9) -> -0.1226 | I12: =VALUE('t4'!E9) -> -0.1227 | K12: =VALUE('t4'!G9) -> -0.0997 | L12: =VALUE('t4'!H9) -> -0.1538 | M12: =VALUE('t4'!I9) -> -0.0827
B14: Skill index | J14: =VALUE('t4'!F11) -> 1.041 | K14: =VALUE('t4'!G11) -> 0.9017
J15: =VALUE('t4'!F12) -> -0.0698 | K15: =VALUE('t4'!G12) -> -0.0838
B16: Constant
B18: Num. observations | E18: =VALUE('t4'!B17) -> 311 | F18: =VALUE('t4'!C17) -> 311 | G18: =VALUE('t4'!D17) -> 311 | I18: =VALUE('t4'!E17) -> 310 | J18: =VALUE('t4'!F17) -> 310 | K18: =VALUE('t4'!G17) -> 310 | L18: =VALUE('t4'!H17) -> 310 | M18: =VALUE('t4'!I17) -> 310
B19: R-squared | E19: =VALUE('t4'!B18) -> 0.867 | F19: =VALUE('t4'!C18) -> 0.717 | G19: =VALUE('t4'!D18) -> 0.356 | I19: =VALUE('t4'!E18) -> 0.355 | J19: =VALUE('t4'!F18) -> 0.712 | K19: =VALUE('t4'!G18) -> 0.747 | L19: =VALUE('t4'!H18) -> 0.267 | M19: =VALUE('t4'!I18) -> 0.089
B21: Note: Each column is a separate regression model, estimated across 4-digit industries, with dependent variable in column heading. In columns 4-8 the sample excludes one industry (Central Banking) that cannot be linked to ACS. Skill index is constructed from ACS data and merged to 4-digit industry data from LEHD. All models are fit by weighted OLS, using the number of person-quarter observations in the industry in our LEHD sample as a weight. Robust standard errors in parentheses.

Sheet Table5
B3: Table 5. Worker Experience and the Industry Hierarchy Effect
C5: Young workers | F5: Older workers
C6: -1 | D6: -2 | F6: -3 | G6: -4
B7: Number of quarters in industry/10 | C7: =VALUE(SUBSTITUTE('disclosed1-12'!B6,"*",""))*10 -> 0.0119 | D7: =VALUE(SUBSTITUTE('disclosed1-12'!C6,"*",""))*10 -> 0.0101 | F7: =VALUE(SUBSTITUTE('disclosed1-12'!D6,"*",""))*10 -> 0.00702 | G7: =VALUE(SUBSTITUTE('disclosed1-12'!E6,"*",""))*10 -> 0.00587
C8: =VALUE(SUBSTITUTE('disclosed1-12'!B7,"*",""))*10 -> -0.00191 | D8: =VALUE(SUBSTITUTE('disclosed1-12'!C7,"*",""))*10 -> -0.000884 | F8: =VALUE(SUBSTITUTE('disclosed1-12'!D7,"*",""))*10 -> -0.00118 | G8: =VALUE(SUBSTITUTE('disclosed1-12'!E7,"*",""))*10 -> -0.000579
B9: Number of quarters in industry/10, squared | C9: =VALUE(SUBSTITUTE('disclosed1-12'!B9,"*",""))*100 -> -0.00328 | D9: =VALUE(SUBSTITUTE('disclosed1-12'!C9,"*",""))*100 -> -0.00293 | F9: =VALUE(SUBSTITUTE('disclosed1-12'!D9,"*",""))*100 -> -0.00161 | G9: =VALUE(SUBSTITUTE('disclosed1-12'!E9,"*",""))*100 -> -0.0016
C10: =VALUE(SUBSTITUTE('disclosed1-12'!B10,"*",""))*100 -> -0.000568 | D10: =VALUE(SUBSTITUTE('disclosed1-12'!C10,"*",""))*100 -> -0.000265 | F10: =VALUE(SUBSTITUTE('disclosed1-12'!D10,"*",""))*100 -> -0.000294 | G10: =VALUE(SUBSTITUTE('disclosed1-12'!E10,"*",""))*100 -> -0.000162
B11: Fixed effects for worker, CZ, industry, time | C11: N | D11: Y | F11: N | G11: Y
B12: Person-quarter observations (millions) | C12: =VALUE('disclosed1-12'!B18)/1000000 -> 89.76 | D12: =C12 -> 89.76 | F12: =VALUE('disclosed1-12'!D18)/1000000 -> 421.8 | G12: =F12 -> 421.8
B13: Adjusted R-squared | C13: =VALUE(SUBSTITUTE('disclosed1-12'!B12,"*","")) -> 0.000368 | D13: =VALUE(SUBSTITUTE('disclosed1-12'!C12,"*","")) -> 0.734 | F13: =VALUE(SUBSTITUTE('disclosed1-12'!D12,"*","")) -> 0.000173 | G13: =VALUE(SUBSTITUTE('disclosed1-12'!E12,"*","")) -> 0.837
B14: Experience (in quarters) at which slope=0 | C14: =-10*C7/(2*C9) -> 18.140244 | D14: =-10*D7/(2*D9) -> 17.235495 | F14: =-10*F7/(2*F9) -> 21.801242 | G14: =-10*G7/(2*G9) -> 18.34375
B15: Cumulative effect of 5 years of experience | C15: =2*C7+4*C9 -> 0.01068 | D15: =2*D7+4*D9 -> 0.00848 | F15: =2*F7+4*F9 -> 0.0076 | G15: =2*G7+4*G9 -> 0.00534
B17: Notes: Each column is a separate regression. Dependent variable in all columns is the hierarchy effect for a given worker in a given quarter (the difference between the workplace pay premium and the industry average pay premium). Young workers in columns 1-2 are those who were not yet 27 at the beginning of 2010; older workers are all others in our main sample. Industry experience is the cumulative number of quarters from 2010-Q1 to date that the worker has been observed in their current industry (including previous spells). Standard errors are clustered at the industry level.

Sheet Table6
B2: Table 6. Comparisons of Industry Effects from Alternative Models
D4: Preferred model | F4: Cross-sectional models (fit to ACS) | J4: Industry Mover models (fit to LEHD)
D5: -1 | F5: -2 | G5: -3 | H5: -4 | J5: -5 | K5: -6 | L5: -7
B6: Alternative model controls for:
C7: Person fixed effects | J7: X | K7: X | L7: X
C8: Year effects and age/experience | F8: X | G8: X | H8: X | J8: X | K8: X | L8: X
C9: Education, gender, and race/ethicity | F9: X | G9: X | H9: X
C10: Field of study and immigration | G10: X | H10: X
C11: CZ fixed effects | H11: X | K11: X
C12: Industry-by-CZ fixed effects | L12: X
B14: Standard deviation of industry effects | D14: =VALUE('disclosed1-5'!B12) -> 0.122 | F14: =VALUE('t6'!B14) -> 0.1887 | G14: =VALUE('t6'!C14) -> 0.1737 | H14: =VALUE('t6'!D14) -> 0.1692 | J14: =VALUE('disclosed1-5'!E11) -> 0.0788 | K14: =VALUE('disclosed1-5'!F11) -> 0.0787 | L14: =VALUE('disclosed1-5'!G11) -> 0.0824
B16: Regression of alternative model estimates on preferred model estimates (N=311) | D16: 1 | F16: =VALUE('t6'!B5) -> 1.239 | G16: =VALUE('t6'!C5) -> 1.1686 | H16: =VALUE('t6'!D5) -> 1.1659 | J16: =VALUE(SUBSTITUTE('disclosed1-5'!E6,"*","")) -> 0.621 | K16: =VALUE(SUBSTITUTE('disclosed1-5'!F6,"*","")) -> 0.618 | L16: =VALUE(SUBSTITUTE('disclosed1-5'!G6,"*","")) -> 0.658
F17: =VALUE('t6'!B6) -> -0.0728 | G17: =VALUE('t6'!C6) -> -0.0639 | H17: =VALUE('t6'!D6) -> -0.0571 | J17: =VALUE(SUBSTITUTE('disclosed1-5'!E7,"*","")) -> -0.0194 | K17: =VALUE(SUBSTITUTE('disclosed1-5'!F7,"*","")) -> -0.02 | L17: =VALUE(SUBSTITUTE('disclosed1-5'!G7,"*","")) -> -0.0147
B18: R2 (adjusted) | F18: =VALUE('t6'!B13) -> 0.644 | G18: =VALUE('t6'!C13) -> 0.676 | H18: =VALUE('t6'!D13) -> 0.709 | J18: =VALUE('disclosed1-5'!E10) -> 0.929 | K18: =VALUE('disclosed1-5'!F10) -> 0.924 | L18: =VALUE('disclosed1-5'!G10) -> 0.954
B20: Note: Preferred model is "ground-up" model, based on averages of firm effects from AKM specification. Regressions are of industry effects from alternative model on industry effects from preferred model, and are weighted by the number of person-quarter observations in the industry. Alternative models in columns 2-4 are fit to ACS, and include 222 NAICS codes (some combining 4 digit codes). These are then merged to 310 4-digit NAICS codes. Alternative models in columns 5-7 are fit to LEHD with person effects and 311 4-digit NAICS dummies, as well as year and age effects. Robust standard errors in parentheses.

Sheet Table7
B2: Table 7. Summaries of CZ-specific β Coefficients
D5: -1 | E5: -2 | F5: -3
B6: Mean | D6: =VALUE('disclosed1-9a'!B57) -> 0.88 | E6: =VALUE('disclosed1-9a'!B65) -> 0.863 | F6: =VALUE('disclosed1-9a'!B61) -> 0.7988
B7: Standard deviation | D7: =VALUE('disclosed1-9a'!B58) -> 0.0818 | E7: =VALUE('disclosed1-9a'!B66) -> 0.097 | F7: =VALUE('disclosed1-9a'!B62) -> 0.1341
B8: Sampling-error adjusted SD | D8: =SQRT(D7^2-'disclosed2-1'!B8) -> 0.07628591 | E8: =SQRT(E7^2-'disclosed2-1'!B9) -> 0.094200849 | F8: =SQRT(F7^2-'disclosed2-1'!B10) -> 0.11485996
B10: Regressions of β in column heading on β indicated in row:
B11: Models for
C12: Coefficient | E12: =VALUE(SUBSTITUTE('disclosed1-9a'!K57,"*","")) -> 0.355 | F12: =VALUE(SUBSTITUTE('disclosed1-9a'!H57,"*","")) -> 0.6166
C13: (Standard error) | E13: =VALUE('disclosed1-9a'!K58) -> -0.2067 | F13: =VALUE('disclosed1-9a'!H58) -> -0.2044
C14: R2 (within-region) | E14: ='T7-8calcs'!D78 -> 0.13827983 | F14: ='T7-8calcs'!E78 -> 0.25599107
B15: Models for
C16: Coefficient | D16: =VALUE(SUBSTITUTE('disclosed1-9a'!E65,"*","")) -> 0.4279 | F16: =VALUE(SUBSTITUTE('disclosed1-9a'!H65,"*","")) -> 1.144
C17: (Standard error) | D17: =VALUE('disclosed1-9a'!E66) -> -0.2222 | F17: =VALUE('disclosed1-9a'!H66) -> -0.1355
C18: R2 (within-region) | D18: =E14 -> 0.13827983 | F18: ='T7-8calcs'!E83 -> 0.74142834
B19: Models for
C20: Coefficient | D20: =VALUE(SUBSTITUTE('disclosed1-9a'!E61,"*","")) -> 0.4214 | E20: =VALUE(SUBSTITUTE('disclosed1-9a'!K61,"*","")) -> 0.6491
C21: (Standard error) | D21: =VALUE('disclosed1-9a'!E62) -> -0.09287 | E21: =VALUE('disclosed1-9a'!K62) -> -0.06223
C22: R2 (within-region) | D22: =F14 -> 0.25599107 | E22: =F18 -> 0.74142834
B24: Note: β coefficients are slopes of a CZ's estimated industry effects or industry average person effects with respect to the national industry effect or industry average person effect -- see text. Summary statistics are weighted by the number of person-quarter observations in each CZ. Regressions relate one of the β coefficients for a CZ to another β coefficient for the same CZ, and control for indicators for four regions and for each of approximately 10 composite CZ's. N≈60. Reported R-squared statistics indicate the share of the within-CZ variation in the β explained, among the 50 non-composite CZs. Regressions are weighted by the number of person-quarter observations in the CZ; and standard errors are heteroskedasticity-robust.

Sheet Table8
B3: Table 8. Bivariate Relationships Between Beta Coefficients and CZ Characteristics
G5: Dependent Variable:
E6: Mean | G6: theta(psi, psi) | M6: theta(alpha, psi) | S6: theta(alpha, alpha)
E7: [Std Dev.] | G7: Coefficient | H7: Adj R2 | I7: Actual R2 | J7: Incremental R2 | K7: R2 | N7: Adj R2 | O7: Actual R2 | P7: Incremental R2 | Q7: R2 | S7: Coefficient | T7: Adj R2 | U7: Actual R2 | W7: R2
E8: -1 | G8: -2 | H8: -3 | K8: -3 | M8: -4 | N8: -5 | S8: -4 | T8: -7 | W8: -5
B15: ln(city size) | D15: ='disclosed1-9a'!A45 -> lnN_c | E15: =VALUE('disclosed1-9a'!B45) -> 17.91 | G15: =VALUE(SUBSTITUTE('disclosed1-9a'!E45,"*","")) -> 0.02925 | H15: =VALUE('disclosed1-9a'!E47) -> 0.1073 | I15: =1-(((59-12-1)/(59-1))*(1-H15)) -> 0.29199655 | J15: =I15-'T7-8calcs'!C$73 -> 0.030619929 | K15: =J15/(1-'T7-8calcs'!C73) -> 0.041455402 | M15: =VALUE(SUBSTITUTE('disclosed1-9a'!H45,"*","")) -> 0.08542 | N15: =VALUE('disclosed1-9a'!H47) -> 0.6304 | O15: =1-(((59-12-1)/(59-1))*(1-N15)) -> 0.70686897 | P15: =O15-#REF! -> #REF! | Q15: =P15/(1-#REF!) -> #REF! | S15: =VALUE(SUBSTITUTE('disclosed1-9a'!K45,"*","")) -> 0.08752 | T15: =VALUE('disclosed1-9a'!K47) -> 0.7293 | U15: =1-(((59-12-1)/(59-1))*(1-T15)) -> 0.7853069 | V15: =U15-'T7-8calcs'!D$73 -> 0.21705358 | W15: =V15/(1-'T7-8calcs'!D$73) -> 0.50273364
E16: =VALUE('disclosed1-9a'!B46) -> 0.8355 | G16: =VALUE('disclosed1-9a'!E46) -> -0.02691 | M16: =VALUE('disclosed1-9a'!H46) -> -0.03135 | S16: =VALUE('disclosed1-9a'!K46) -> -0.01958
B17: Mean pay premium in CZ | D17: ='disclosed1-9a'!A17 -> psi_c | E17: =VALUE('disclosed1-9a'!B17) -> 0.2356 | G17: =VALUE(SUBSTITUTE('disclosed1-9a'!E17,"*","")) -> 1.861 | H17: =VALUE('disclosed1-9a'!E19) -> 0.7407 | I17: =1-(((59-12-1)/(59-1))*(1-H17)) -> 0.79434828 | J17: =I17-'T7-8calcs'!C$73 -> 0.53297165 | K17: =J17/(1-'T7-8calcs'!C73) -> 0.72157431 | M17: =VALUE(SUBSTITUTE('disclosed1-9a'!H17,"*","")) -> 1.401 | N17: =VALUE('disclosed1-9a'!H19) -> 0.6326 | O17: =1-(((59-12-1)/(59-1))*(1-N17)) -> 0.70861379 | P17: =O17-#REF! -> #REF! | Q17: =P17/(1-#REF!) -> #REF! | S17: =VALUE(SUBSTITUTE('disclosed1-9a'!K17,"*","")) -> 0.8843 | T17: =VALUE('disclosed1-9a'!K19) -> 0.5558 | U17: =1-(((59-12-1)/(59-1))*(1-T17)) -> 0.64770345 | V17: =U17-'T7-8calcs'!D$73 -> 0.079450132 | W17: =V17/(1-'T7-8calcs'!D$73) -> 0.18402025
E18: =VALUE('disclosed1-9a'!B18) -> 0.04349 | G18: =VALUE('disclosed1-9a'!E18) -> -0.2175 | M18: =VALUE('disclosed1-9a'!H18) -> -0.3538 | S18: =VALUE('disclosed1-9a'!K18) -> -0.355
B19: Share of firms with psis in Q1 and Q5 | D19: ='disclosed1-9a'!A33 -> s_psi_q1q5 | E19: =VALUE('disclosed1-9a'!B33) -> 0.3006 | G19: =VALUE(SUBSTITUTE('disclosed1-9a'!E33,"*","")) -> 0.8656 | H19: =VALUE('disclosed1-9a'!E35) -> 0.6955 | M19: =VALUE(SUBSTITUTE('disclosed1-9a'!H33,"*","")) -> 0.7861 | N19: =VALUE('disclosed1-9a'!H35) -> 0.6838 | S19: =VALUE(SUBSTITUTE('disclosed1-9a'!K33,"*","")) -> 0.5768 | T19: =VALUE('disclosed1-9a'!K35) -> 0.6467
E20: =VALUE('disclosed1-9a'!B34) -> 0.09014 | G20: =VALUE('disclosed1-9a'!E34) -> -0.1145 | M20: =VALUE('disclosed1-9a'!H34) -> -0.1539 | S20: =VALUE('disclosed1-9a'!K34) -> -0.1095
B21: Average person effect in CZ | D21: ='disclosed1-9a'!A5 -> alpha_c | E21: =VALUE('disclosed1-9a'!B5) -> 9.456 | G21: =VALUE(SUBSTITUTE('disclosed1-9a'!E5,"*","")) -> 0.199 | H21: =VALUE('disclosed1-9a'!E7) -> 0.1101 | I21: =1-(((59-12-1)/(59-1))*(1-H21)) -> 0.29421724 | J21: =I21-'T7-8calcs'!C$73 -> 0.032840619 | K21: =J21/(1-'T7-8calcs'!C73) -> 0.044461927 | M21: =VALUE(SUBSTITUTE('disclosed1-9a'!H5,"*","")) -> 0.7971 | N21: =VALUE('disclosed1-9a'!H7) -> 0.771 | O21: =1-(((59-12-1)/(59-1))*(1-N21)) -> 0.81837931 | P21: =O21-#REF! -> #REF! | Q21: =P21/(1-#REF!) -> #REF! | S21: =VALUE(SUBSTITUTE('disclosed1-9a'!K5,"*","")) -> 0.662 | T21: =VALUE('disclosed1-9a'!K7) -> 0.8177 | U21: =1-(((59-12-1)/(59-1))*(1-T21)) -> 0.85541724 | V21: =U21-'T7-8calcs'!D$73 -> 0.28716393 | W21: =V21/(1-'T7-8calcs'!D$73) -> 0.66512132
E22: =VALUE('disclosed1-9a'!B6) -> 0.1319 | G22: =VALUE('disclosed1-9a'!E6) -> -0.2203 | M22: =VALUE('disclosed1-9a'!H6) -> -0.1414 | S22: =VALUE('disclosed1-9a'!K6) -> -0.07046
B23: Share of workers with alphas in Q1 and Q5 | D23: ='disclosed1-9a'!A13 -> s_alpha_q1q5 | E23: =VALUE('disclosed1-9a'!B13) -> 0.3994 | G23: =VALUE(SUBSTITUTE('disclosed1-9a'!E13,"*","")) -> 0.5773 | H23: =VALUE('disclosed1-9a'!E15) -> 0.09661 | M23: =VALUE(SUBSTITUTE('disclosed1-9a'!H13,"*","")) -> 1.988 | N23: =VALUE('disclosed1-9a'!H15) -> 0.638 | S23: =VALUE(SUBSTITUTE('disclosed1-9a'!K13,"*","")) -> 1.967 | T23: =VALUE('disclosed1-9a'!K15) -> 0.7245
E24: =VALUE('disclosed1-9a'!B14) -> 0.03059 | G24: =VALUE('disclosed1-9a'!E14) -> -0.6396 | M24: =VALUE('disclosed1-9a'!H14) -> -0.3943 | S24: =VALUE('disclosed1-9a'!K14) -> -0.2481
B25: Expected average pay premiums and expected average worker skills, given industry composition:
C26: Expected mean pay premium in CZ | D26: ='disclosed1-9a'!A29 -> Epsi_c | E26: =VALUE('disclosed1-9a'!B29) -> 0.2356 | G26: =VALUE(SUBSTITUTE('disclosed1-9a'!E29,"*","")) -> 3.975 | H26: =VALUE('disclosed1-9a'!E31) -> 0.3325 | I26: =1-(((59-12-1)/(59-1))*(1-H26)) -> 0.47060345 | J26: =I26-'T7-8calcs'!C$73 -> 0.20922683 | K26: =J26/(1-'T7-8calcs'!C73) -> 0.28326591 | M26: =VALUE(SUBSTITUTE('disclosed1-9a'!H29,"*","")) -> 5.241 | N26: =VALUE('disclosed1-9a'!H31) -> 0.664 | O26: =1-(((59-12-1)/(59-1))*(1-N26)) -> 0.73351724 | P26: =O26-#REF! -> #REF! | Q26: =P26/(1-#REF!) -> #REF! | S26: =VALUE(SUBSTITUTE('disclosed1-9a'!K29,"*","")) -> 2.615 | T26: =VALUE('disclosed1-9a'!K31) -> 0.5299 | U26: =1-(((59-12-1)/(59-1))*(1-T26)) -> 0.62716207 | V26: =U26-'T7-8calcs'!D$73 -> 0.058908753 | W26: =V26/(1-'T7-8calcs'!D$73) -> 0.13644286
E27: =VALUE('disclosed1-9a'!B30) -> 0.0111 | G27: =VALUE('disclosed1-9a'!E30) -> -1.015 | M27: =VALUE('disclosed1-9a'!H30) -> -1.057 | S27: =VALUE('disclosed1-9a'!K30) -> -0.8646
C28: Expected share of firms with psis in Q1 and Q5 | D28: ='disclosed1-9a'!A53 -> Es_psi_q1q5 | E28: =VALUE('disclosed1-9a'!B53) -> 0.3006 | G28: =VALUE(SUBSTITUTE('disclosed1-9a'!E53,"*","")) -> 2.077 | H28: =VALUE('disclosed1-9a'!E55) -> 0.3229 | M28: =VALUE(SUBSTITUTE('disclosed1-9a'!H53,"*","")) -> 3.297 | N28: =VALUE('disclosed1-9a'!H55) -> 0.7335 | S28: =VALUE(SUBSTITUTE('disclosed1-9a'!K53,"*","")) -> 1.851 | T28: =VALUE('disclosed1-9a'!K55) -> 0.5938
E29: =VALUE('disclosed1-9a'!B54) -> 0.02114 | G29: =VALUE('disclosed1-9a'!E54) -> -0.5314 | M29: =VALUE('disclosed1-9a'!H54) -> -0.5127 | S29: =VALUE('disclosed1-9a'!K54) -> -0.4174
C30: Expected mean person effect in CZ | D30: ='disclosed1-9a'!A21 -> Ealpha_c | E30: =VALUE('disclosed1-9a'!B21) -> 9.456 | G30: =VALUE(SUBSTITUTE('disclosed1-9a'!E21,"*","")) -> 1.354 | H30: =VALUE('disclosed1-9a'!E23) -> 0.1886 | I30: =1-(((59-12-1)/(59-1))*(1-H30)) -> 0.35647586 | J30: =I30-'T7-8calcs'!C$73 -> 0.09509924 | K30: =J30/(1-'T7-8calcs'!C73) -> 0.128752 | M30: =VALUE(SUBSTITUTE('disclosed1-9a'!H21,"*","")) -> 3.393 | N30: =VALUE('disclosed1-9a'!H23) -> 0.7832 | O30: =1-(((59-12-1)/(59-1))*(1-N30)) -> 0.82805517 | P30: =O30-#REF! -> #REF! | Q30: =P30/(1-#REF!) -> #REF! | S30: =VALUE(SUBSTITUTE('disclosed1-9a'!K21,"*","")) -> 2.36 | T30: =VALUE('disclosed1-9a'!K23) -> 0.7184 | U30: =1-(((59-12-1)/(59-1))*(1-T30)) -> 0.77666207 | V30: =U30-'T7-8calcs'!D$73 -> 0.20840875 | W30: =V30/(1-'T7-8calcs'!D$73) -> 0.48271072
E31: =VALUE('disclosed1-9a'!B22) -> 0.03052 | G31: =VALUE('disclosed1-9a'!E22) -> -0.4808 | M31: =VALUE('disclosed1-9a'!H22) -> -0.4288 | S31: =VALUE('disclosed1-9a'!K22) -> -0.385
C32: Expected share of workers with alphas in Q1 and Q5 | D32: ='disclosed1-9a'!A25 -> Es_alpha_q1q5 | E32: =VALUE('disclosed1-9a'!B25) -> 0.3872 | G32: =VALUE(SUBSTITUTE('disclosed1-9a'!E25,"*","")) -> 1.957 | H32: =VALUE('disclosed1-9a'!E27) -> 0.08608 | M32: =VALUE(SUBSTITUTE('disclosed1-9a'!H25,"*","")) -> 8.593 | N32: =VALUE('disclosed1-9a'!H27) -> 0.6553 | S32: =VALUE(SUBSTITUTE('disclosed1-9a'!K25,"*","")) -> 7.019 | T32: =VALUE('disclosed1-9a'!K27) -> 0.6582
E33: =VALUE('disclosed1-9a'!B26) -> 0.009524 | G33: =VALUE('disclosed1-9a'!E26) -> -2.127 | M33: =VALUE('disclosed1-9a'!H26) -> -2.749 | S33: =VALUE('disclosed1-9a'!K26) -> -1.658
B34: Institutional features:
C35: Union coverage | D35: ='disclosed1-9a'!A41 -> coverage | E35: =VALUE('disclosed1-9a'!B41) -> 0.1303 | G35: =VALUE(SUBSTITUTE('disclosed1-9a'!E41,"*","")) -> 0.4496 | H35: =VALUE('disclosed1-9a'!E43) -> 0.08972 | I35: =1-(((59-12-1)/(59-1))*(1-H35)) -> 0.27805379 | J35: =I35-'T7-8calcs'!C$73 -> 0.016677171 | K35: =J35/(1-'T7-8calcs'!C73) -> 0.02257872 | M35: =VALUE(SUBSTITUTE('disclosed1-9a'!H41,"*","")) -> 0.1463 | N35: =VALUE('disclosed1-9a'!H43) -> 0.4906 | O35: =1-(((59-12-1)/(59-1))*(1-N35)) -> 0.5959931 | P35: =O35-#REF! -> #REF! | Q35: =P35/(1-#REF!) -> #REF! | S35: =VALUE(SUBSTITUTE('disclosed1-9a'!K41,"*","")) -> 0.6131 | T35: =VALUE('disclosed1-9a'!K43) -> 0.4823 | U35: =1-(((59-12-1)/(59-1))*(1-T35)) -> 0.58941034 | V35: =U35-'T7-8calcs'!D$73 -> 0.021157029 | W35: =V35/(1-'T7-8calcs'!D$73) -> 0.049003338
E36: =VALUE('disclosed1-9a'!B42) -> 0.06013 | G36: =VALUE('disclosed1-9a'!E42) -> -0.5278 | M36: =VALUE('disclosed1-9a'!H42) -> -0.4202 | S36: =VALUE('disclosed1-9a'!K42) -> -0.3628
C37: ln(minimum wage) | D37: ='disclosed1-9a'!A49 -> lnmw | E37: =VALUE('disclosed1-9a'!B49) -> 2.089 | G37: =VALUE(SUBSTITUTE('disclosed1-9a'!E49,"*","")) -> 0.2417 | H37: =VALUE('disclosed1-9a'!E51) -> 0.1249 | I37: =1-(((59-12-1)/(59-1))*(1-H37)) -> 0.30595517 | J37: =I37-'T7-8calcs'!C$73 -> 0.04457855 | K37: =J37/(1-'T7-8calcs'!C73) -> 0.060353559 | M37: =VALUE(SUBSTITUTE('disclosed1-9a'!H49,"*","")) -> 0.4666 | N37: =VALUE('disclosed1-9a'!H51) -> 0.5755 | O37: =1-(((59-12-1)/(59-1))*(1-N37)) -> 0.66332759 | P37: =O37-#REF! -> #REF! | Q37: =P37/(1-#REF!) -> #REF! | S37: =VALUE(SUBSTITUTE('disclosed1-9a'!K49,"*","")) -> 0.4191 | T37: =VALUE('disclosed1-9a'!K51) -> 0.5794 | U37: =1-(((59-12-1)/(59-1))*(1-T37)) -> 0.66642069 | V37: =U37-'T7-8calcs'!D$73 -> 0.098167374 | W37: =V37/(1-'T7-8calcs'!D$73) -> 0.22737262
E38: =VALUE('disclosed1-9a'!B50) -> 0.1112 | G38: =VALUE('disclosed1-9a'!E50) -> -0.1438 | M38: =VALUE('disclosed1-9a'!H50) -> -0.1342 | S38: =VALUE('disclosed1-9a'!K50) -> -0.09526
B40: Note: Each coefficient is from a regression of the column variable on the row variable, with additional controls for four regions and for each of approximately 10 composite CZs. N≈60. Regressions are weighted by the number of person-quarter observations in the CZ, and standard errors are heteroskedasticity-robust.

Sheet tab A-1
B2: Table A1: Summary of AKM Estimation Results
C4: Variance / covariance | D4: Std. Dev. | E4: Correlation | F4: Variance share
C5: (1) | D5: (2) | E5: (3) | F5: (4)
B6: Panel A: Average of CZ-level variances/covariances computed from CZ-level AKM models
B7: Log quarterly earnings | C7: =VALUE('disclosed2-4'!C4) -> 0.406 | D7: =SQRT(C7) -> 0.63718129 | F7: =+C7/D$7^2 -> 1
B9: Estimated person, establishment effects and covariates
B10: Person effects | C10: ='disclosed2-4'!C5 -> 0.274 | D10: =SQRT(C10) -> 0.52345009 | F10: =+C10/D$7^2 -> 0.67487685
B11: Establishment effects | C11: ='disclosed2-4'!C6 -> 0.04398 | D11: =SQRT(C11) -> 0.20971409 | F11: =+C11/D$7^2 -> 0.10832512
B12: Covariate index | C12: ='disclosed2-4'!C7 -> 0.01874 | D12: =SQRT(C12) -> 0.13689412 | F12: =+C12/D$7^2 -> 0.046157635
B13: Residual | C13: ='disclosed2-4'!C8 -> 0.04916 | D13: =SQRT(C13) -> 0.22172054 | F13: =+C13/D$7^2 -> 0.12108374
B14: Covariances
B15: (person effects, establishment effects) | C15: ='disclosed2-4'!C9/2 -> 0.01444 | E15: =C15/(D10*D11) -> 0.13154196 | F15: =2*C15/D$7^2 -> 0.071133005
B16: (person effects, covariate index) | C16: ='disclosed2-4'!C10/2 -> -0.00503 | E16: =C16/(D10*D12) -> -0.07019528 | F16: =2*C16/D$7^2 -> -0.024778325
B17: (establishment effects, covariate index) | C17: ='disclosed2-4'!C12/2 -> 0.0006565 | E17: =C17/(D11*D12) -> 0.022867691 | F17: =2*C17/D$7^2 -> 0.0032339901
B19: Panel B: Variances/covariances from national AKM model (Card, Rothstein, and Yi 2023)
B20: Log quarterly earnings | C20: =D20^2 -> 0.42588676 | D20: =VALUE('L3disclosure7-2'!B7) -> 0.6526 | F20: 1
B22: Estimated person, establishment effects and covariates
B23: Person effects | C23: =F23*C$20 -> 0.27444143 | D23: =SQRT(C23) -> 0.52387158 | F23: =VALUE('L3disclosure7-2'!B8) -> 0.6444
B24: Establishment effects | C24: =F24*C$20 -> 0.049658396 | D24: =SQRT(C24) -> 0.22284164 | F24: =VALUE('L3disclosure7-2'!B9) -> 0.1166
B25: Covariate index | C25: =F25*C$20 -> 0.018138517 | D25: =SQRT(C25) -> 0.13467931 | F25: =VALUE('L3disclosure7-2'!B10) -> 0.04259
B26: Residual | C26: =F26*C$20 -> 0.053874675 | D26: =SQRT(C26) -> 0.23210919 | F26: =VALUE('L3disclosure7-2'!B11) -> 0.1265
B27: Covariances
B28: (person effects, establishment effects) | C28: =F28*C$20/2 -> 0.021294338 | E28: =C28/(D23*D24) -> 0.18240761 | F28: =VALUE('L3disclosure7-2'!B12) -> 0.1
B29: (person effects, covariate index) | C29: =F29*C$20/2 -> -0.0070484259 | E29: =C29/(D23*D25) -> -0.099900213 | F29: =VALUE('L3disclosure7-2'!B13) -> -0.0331
B30: (establishment effects, covariate index) | C30: =F30*C$20/2 -> 0.00061434165 | E30: =C30/(F24*F25) -> 0.1237097 | F30: =VALUE('L3disclosure7-2'!B15) -> 0.002885
B32: Note: Table presents summaries of estimated AKM models. Panel A summarizes results from the primary models used in this paper, fit separately to each of approximately 60 CZs or regional aggregates. Panel B summarizes results from an alternative model that is fit to the entire U.S., as in Card, Rothstein, and Yi (2023). Total sample size is approximately 2.505 billion person-quarters.

Sheet tabA-2
B2: Appendix Table A-2. Industry Wage Premiums, Mean Worker Effects, and Average Pay, 4-Digit Industries
B4: NAICS | C4: Industry | D4: Mean log earnings | E4: Mean worker effect (normalized to mean 0) | F4: Industry premium | G4: Percent of workforce
D5: (1) | E5: (2) | F5: (3) | G5: (4)
C6: Across-industry mean | D6: =apptab2!A2 -> 9.4336428 | E6: =apptab2!B2 -> 9.4562602 | F6: =apptab2!C2 -> 0.23558897
C7: Across-industry SD | D7: =apptab2!A3 -> 0.27829195 | E7: =apptab2!B3 -> 0.18484385 | F7: =apptab2!C3 -> 0.12233035
B9: =apptab2!E4 -> 1111 | C9: Oilseed and Grain Farming | D9: =apptab2!A4 -> 9.216 | E9: =apptab2!B4 -> -0.14526024 | F9: =apptab2!C4 -> 0.1524 | G9: =apptab2!F4 -> 0.00030141935
B10: =apptab2!E5 -> 1112 | C10: Vegetable and Melon Farming | D10: =apptab2!A5 -> 9.12 | E10: =apptab2!B5 -> -0.21326025 | F10: =apptab2!C5 -> 0.1545 | G10: =apptab2!F5 -> 0.0004247817
B11: =apptab2!E6 -> 1113 | C11: Fruit and Tree Nut Farming | D11: =apptab2!A6 -> 9.013 | E11: =apptab2!B6 -> -0.27026024 | F11: =apptab2!C6 -> 0.1043 | G11: =apptab2!F6 -> 0.00060882716
B12: =apptab2!E7 -> 1114 | C12: Greenhouse, Nursery, and Floriculture | D12: =apptab2!A7 -> 9.032 | E12: =apptab2!B7 -> -0.26326025 | F12: =apptab2!C7 -> 0.1021 | G12: =apptab2!F7 -> 0.00080964033
B13: =apptab2!E8 -> 1119 | C13: Other Crop Farming | D13: =apptab2!A8 -> 9.113 | E13: =apptab2!B8 -> -0.21526025 | F13: =apptab2!C8 -> 0.1306 | G13: =apptab2!F8 -> 0.00033735012
B14: =apptab2!E9 -> 1121 | C14: Cattle Ranching and Farming | D14: =apptab2!A9 -> 9.108 | E14: =apptab2!B9 -> -0.27126026 | F14: =apptab2!C9 -> 0.1771 | G14: =apptab2!F9 -> 0.00079646567
B15: =apptab2!E10 -> 1122 | C15: Hog and Pig Farming | D15: =apptab2!A10 -> 9.159 | E15: =apptab2!B10 -> -0.32026026 | F15: =apptab2!C10 -> 0.2593 | G15: =apptab2!F10 -> 0.00022516624
B16: =apptab2!E11 -> 1123 | C16: Poultry and Egg Production | D16: =apptab2!A11 -> 9.143 | E16: =apptab2!B11 -> -0.30726025 | F16: =apptab2!C11 -> 0.2355 | G16: =apptab2!F11 -> 0.00029423318
B17: =apptab2!E12 -> 1124 | C17: Sheep and Goat Farming | D17: =apptab2!A12 -> 9.019 | E17: =apptab2!B12 -> -0.25426024 | F17: =apptab2!C12 -> 0.08397 | G17: =apptab2!F12 -> 6.9865409e-06
B18: =apptab2!E13 -> 1125 | C18: Aquaculture | D18: =apptab2!A13 -> 9.185 | E18: =apptab2!B13 -> -0.15226024 | F18: =apptab2!C13 -> 0.1408 | G18: =apptab2!F13 -> 4.3116939e-05
B19: =apptab2!E14 -> 1129 | C19: Other Animal Production | D19: =apptab2!A14 -> 9.15 | E19: =apptab2!B14 -> -0.22926025 | F19: =apptab2!C14 -> 0.1739 | G19: =apptab2!F14 -> 0.0001161762
B20: =apptab2!E15 -> 1131 | C20: Timber Tract Operations | D20: =apptab2!A15 -> 9.555 | E20: =apptab2!B15 -> 0.075739756 | F20: =apptab2!C15 -> 0.2839 | G20: =apptab2!F15 -> 2.9343473e-05
... B47: =apptab2!E42 -> 3112 | C47: Grain and Oilseed Milling | D47: =apptab2!A42 -> 9.582 | E47: =apptab2!B42 -> -0.073260248 | F47: =apptab2!C42 -> 0.4492 | G47: =apptab2!F42 -> 0.00066591718
B48: Appendix Table A-2 (continued)
B50: NAICS | C50: Industry | D50: Mean log earnings | E50: Mean worker effect (normalized to mean 0) | F50: Industry premium | G50: Percent of workforce
D51: (1) | E51: (2) | F51: (3) | G51: (4)
B52: =apptab2!E43 -> 3113 | C52: Sugar and Confectionery Product Manuf. | D52: =apptab2!A43 -> 9.395 | E52: =apptab2!B43 -> -0.14926025 | F52: =apptab2!C43 -> 0.3478 | G52: =apptab2!F43 -> 0.00059445482
B53: =apptab2!E44 -> 3114 | C53: Fruit & Veg. Prsrvng. & Spec. Food Manuf. | D53: =apptab2!A44 -> 9.278 | E53: =apptab2!B44 -> -0.24226025 | F53: =apptab2!C44 -> 0.3256 | G53: =apptab2!F44 -> 0.0015741675
B54: =apptab2!E45 -> 3115 | C54: Dairy Product Manufacturing | D54: =apptab2!A45 -> 9.457 | E54: =apptab2!B45 -> -0.15926024 | F54: =apptab2!C45 -> 0.4117 | G54: =apptab2!F45 -> 0.0014168705
B55: =apptab2!E46 -> 3116 | C55: Animal Slaughtering and Processing | D55: =apptab2!A46 -> 9.069 | E55: =apptab2!B46 -> -0.43426025 | F55: =apptab2!C46 -> 0.2927 | G55: =apptab2!F46 -> 0.0044234786
B56: =apptab2!E47 -> 3117 | C56: Seafood Product Preparation and Pkging. | D56: =apptab2!A47 -> 9.226 | E56: =apptab2!B47 -> -0.23126024 | F56: =apptab2!C47 -> 0.281 | G56: =apptab2!F47 -> 0.00024113548
B57: =apptab2!E48 -> 3118 | C57: Bakeries and Tortilla Manufacturing | D57: =apptab2!A48 -> 9.217 | E57: =apptab2!B48 -> -0.25826025 | F57: =apptab2!C48 -> 0.2816 | G57: =apptab2!F48 -> 0.0021394785
B58: =apptab2!E49 -> 3119 | C58: Other Food Manufacturing | D58: =apptab2!A49 -> 9.373 | E58: =apptab2!B49 -> -0.15726025 | F58: =apptab2!C49 -> 0.3261 | G58: =apptab2!F49 -> 0.0017178906
B59: =apptab2!E50 -> 3121 | C59: Beverage Manufacturing | D59: =apptab2!A50 -> 9.452 | E59: =apptab2!B50 -> -0.061260246 | F59: =apptab2!C50 -> 0.3102 | G59: =apptab2!F50 -> 0.0018264814
B60: =apptab2!E51 -> 3122 | C60: Tobacco Manufacturing | D60: =apptab2!A51 -> 9.702 | E60: =apptab2!B51 -> -0.034260247 | F60: =apptab2!C51 -> 0.533 | G60: =apptab2!F51 -> 0.00013454082
B61: =apptab2!E52 -> 3131 | C61: Fiber, Yarn, and Thread Mills | D61: =apptab2!A52 -> 9.057 | E61: =apptab2!B52 -> -0.39926025 | F61: =apptab2!C52 -> 0.2405 | G61: =apptab2!F52 -> 0.00026748472
B62: =apptab2!E53 -> 3132 | C62: Fabric Mills | D62: =apptab2!A53 -> 9.194 | E62: =apptab2!B53 -> -0.28226024 | F62: =apptab2!C53 -> 0.2699 | G62: =apptab2!F53 -> 0.00052738405
B63: =apptab2!E54 -> 3133 | C63: Textile & Fabric Finishing & Coating Mills | D63: =apptab2!A54 -> 9.219 | E63: =apptab2!B54 -> -0.20826025 | F63: =apptab2!C54 -> 0.2325 | G63: =apptab2!F54 -> 0.00028584935
... B93: =apptab2!E84 -> 3311 | C93: Iron and Steel Mills & Ferroalloy Manuf. | D93: =apptab2!A84 -> 9.822 | E93: =apptab2!B84 -> -0.040260248 | F93: =apptab2!C84 -> 0.661 | G93: =apptab2!F84 -> 0.00098610041
B94: Appendix Table A-2 (continued)
B96: NAICS | C96: Industry | D96: Mean log earnings | E96: Mean worker effect (normalized to mean 0) | F96: Industry premium | G96: Percent of workforce
D97: (1) | E97: (2) | F97: (3) | G97: (4)
B98: =apptab2!E85 -> 3312 | C98: Steel Product Manuf. from Purchased Steel | D98: =apptab2!A85 -> 9.526 | E98: =apptab2!B85 -> -0.11126025 | F98: =apptab2!C85 -> 0.4318 | G98: =apptab2!F85 -> 0.00060323795
B99: =apptab2!E86 -> 3313 | C99: Alumina and Aluminum | D99: =apptab2!A86 -> 9.546 | E99: =apptab2!B86 -> -0.15226024 | F99: =apptab2!C86 -> 0.4911 | G99: =apptab2!F86 -> 0.00063078484
B100: =apptab2!E87 -> 3314 | C100: Nonferrous Metal (except Aluminum) | D100: =apptab2!A87 -> 9.559 | E100: =apptab2!B87 -> -0.083260246 | F100: =apptab2!C87 -> 0.4412 | G100: =apptab2!F87 -> 0.00065913022
B101: =apptab2!E88 -> 3315 | C101: Foundries | D101: =apptab2!A88 -> 9.394 | E101: =apptab2!B88 -> -0.18026024 | F101: =apptab2!C88 -> 0.3755 | G101: =apptab2!F88 -> 0.0012420074
B102: =apptab2!E89 -> 3321 | C102: Forging and Stamping | D102: =apptab2!A89 -> 9.392 | E102: =apptab2!B89 -> -0.11026025 | F102: =apptab2!C89 -> 0.3064 | G102: =apptab2!F89 -> 0.0009864996
B103: =apptab2!E90 -> 3322 | C103: Cutlery and Handtool Manufacturing | D103: =apptab2!A90 -> 9.394 | E103: =apptab2!B90 -> -0.094260246 | F103: =apptab2!C90 -> 0.3006 | G103: =apptab2!F90 -> 0.00038765321
B104: =apptab2!E91 -> 3323 | C104: Architectural and Structural Metals Manuf. | D104: =apptab2!A91 -> 9.349 | E104: =apptab2!B91 -> -0.11226024 | F104: =apptab2!C91 -> 0.2578 | G104: =apptab2!F91 -> 0.0033343767
B105: =apptab2!E92 -> 3324 | C105: Boiler, Tank, & Shipping Container Manuf. | D105: =apptab2!A92 -> 9.508 | E105: =apptab2!B92 -> -0.077260248 | F105: =apptab2!C92 -> 0.3833 | G105: =apptab2!F92 -> 0.00093260343
B106: =apptab2!E93 -> 3325 | C106: Hardware Manufacturing | D106: =apptab2!A93 -> 9.358 | E106: =apptab2!B93 -> -0.11726025 | F106: =apptab2!C93 -> 0.2742 | G106: =apptab2!F93 -> 0.00024153471
B107: =apptab2!E94 -> 3326 | C107: Spring and Wire Product Manufacturing | D107: =apptab2!A94 -> 9.296 | E107: =apptab2!B94 -> -0.15326025 | F107: =apptab2!C94 -> 0.2507 | G107: =apptab2!F94 -> 0.00041400245
B108: =apptab2!E95 -> 3327 | C108: Mach. Shops, Turned Prod., & Screw Manuf. | D108: =apptab2!A95 -> 9.383 | E108: =apptab2!B95 -> -0.055260248 | F108: =apptab2!C95 -> 0.2456 | G108: =apptab2!F95 -> 0.0033531405
B109: =apptab2!E96 -> 3328 | C109: Coating, Engraving, Heat Treating,etc. | D109: =apptab2!A96 -> 9.275 | E109: =apptab2!B96 -> -0.17526025 | F109: =apptab2!C96 -> 0.2541 | G109: =apptab2!F96 -> 0.0012128635
... B139: =apptab2!E126 -> 3399 | C139: Other Miscellaneous Manufacturing | D139: =apptab2!A126 -> 9.311 | E139: =apptab2!B126 -> -0.10726025 | F139: =apptab2!C126 -> 0.2196 | G139: =apptab2!F126 -> 0.0025227403
B140: Appendix Table A-2 (continued)
B142: NAICS | C142: Industry | D142: Mean log earnings | E142: Mean worker effect (normalized to mean 0) | F142: Industry premium | G142: Percent of workforce
D143: (1) | E143: (2) | F143: (3) | G143: (4)
B144: =apptab2!E127 -> 4231 | C144: Motor Vehicle & Parts Wholesalers | D144: =apptab2!A127 -> 9.39 | E144: =apptab2!B127 -> -0.034260247 | F144: =apptab2!C127 -> 0.2233 | G144: =apptab2!F127 -> 0.0028465164
B145: =apptab2!E128 -> 4232 | C145: Furniture & Home Furnishing Wholesalers | D145: =apptab2!A128 -> 9.423 | E145: =apptab2!B128 -> 0.0087397536 | F145: =apptab2!C128 -> 0.2172 | G145: =apptab2!F128 -> 0.00090585498
B146: =apptab2!E129 -> 4233 | C146: Lumber and Other Const. Materials Whlsl. | D146: =apptab2!A129 -> 9.424 | E146: =apptab2!B129 -> -0.023260247 | F146: =apptab2!C129 -> 0.2383 | G146: =apptab2!F129 -> 0.0018787807
B147: =apptab2!E130 -> 4234 | C147: Prof. & Comm. Equip. & Supplies Whlsl. | D147: =apptab2!A130 -> 9.788 | E147: =apptab2!B130 -> 0.23873976 | F147: =apptab2!C130 -> 0.3498 | G147: =apptab2!F130 -> 0.0062838946
B148: =apptab2!E131 -> 4235 | C148: Metal & Mineral (exc. Petroleum) Whlsl. | D148: =apptab2!A131 -> 9.491 | E148: =apptab2!B131 -> -0.014260246 | F148: =apptab2!C131 -> 0.3035 | G148: =apptab2!F131 -> 0.0012220459
B149: =apptab2!E132 -> 4236 | C149: Appliances & Electrical Wholesalers | D149: =apptab2!A132 -> 9.667 | E149: =apptab2!B132 -> 0.16673975 | F149: =apptab2!C132 -> 0.3027 | G149: =apptab2!F132 -> 0.0032026304
B150: =apptab2!E133 -> 4237 | C150: Hardware , Plumbing, & Heating Whlsl. | D150: =apptab2!A133 -> 9.477 | E150: =apptab2!B133 -> 0.038739752 | F150: =apptab2!C133 -> 0.2355 | G150: =apptab2!F133 -> 0.0022939809
B151: =apptab2!E134 -> 4238 | C151: Mach., Equip. & Supplies Wholesalers | D151: =apptab2!A134 -> 9.547 | E151: =apptab2!B134 -> 0.064739756 | F151: =apptab2!C134 -> 0.2793 | G151: =apptab2!F134 -> 0.0062679253
B152: =apptab2!E135 -> 4239 | C152: Misc. Durable Goods Wholesalers | D152: =apptab2!A135 -> 9.352 | E152: =apptab2!B135 -> -0.058260247 | F152: =apptab2!C135 -> 0.2158 | G152: =apptab2!F135 -> 0.0024197386
B153: =apptab2!E136 -> 4241 | C153: Paper & Paper Product Wholesalers | D153: =apptab2!A136 -> 9.482 | E153: =apptab2!B136 -> 0.032739755 | F153: =apptab2!C136 -> 0.2583 | G153: =apptab2!F136 -> 0.0010547681
B154: =apptab2!E137 -> 4242 | C154: Drugs and Druggists' Sundries Wholesalers | D154: =apptab2!A137 -> 9.888 | E154: =apptab2!B137 -> 0.25373974 | F154: =apptab2!C137 -> 0.4211 | G154: =apptab2!F137 -> 0.0019498438
B155: =apptab2!E138 -> 4243 | C155: Apparel, Piece Goods, and Notions Whlsl. | D155: =apptab2!A138 -> 9.447 | E155: =apptab2!B138 -> 0.057739753 | F155: =apptab2!C138 -> 0.214 | G155: =apptab2!F138 -> 0.0011889096
... B185: =apptab2!E168 -> 4533 | C185: Used Merchandise Stores | D185: =apptab2!A168 -> 8.892 | E185: =apptab2!B168 -> -0.32526025 | F185: =apptab2!C168 -> 0.02459 | G185: =apptab2!F168 -> 0.00064595562
B186: Appendix Table A-2 (continued)
B188: NAICS | C188: Industry | D188: Mean log earnings | E188: Mean worker effect (normalized to mean 0) | F188: Industry premium | G188: Percent of workforce
D189: (1) | E189: (2) | F189: (3) | G189: (4)
B190: =apptab2!E169 -> 4539 | C190: Other Miscellaneous Store Retailers | D190: =apptab2!A169 -> 9.117 | E190: =apptab2!B169 -> -0.15526025 | F190: =apptab2!C169 -> 0.08517 | G190: =apptab2!F169 -> 0.0015226668
B191: =apptab2!E170 -> 4541 | C191: Electronic Shopping and Mail-Order Houses | D191: =apptab2!A170 -> 9.454 | E191: =apptab2!B170 -> 0.015739754 | F191: =apptab2!C170 -> 0.2424 | G191: =apptab2!F170 -> 0.002565857
B192: =apptab2!E171 -> 4542 | C192: Vending Machine Operators | D192: =apptab2!A171 -> 9.096 | E192: =apptab2!B171 -> -0.23826024 | F192: =apptab2!C171 -> 0.1349 | G192: =apptab2!F171 -> 0.00027427165
B193: =apptab2!E172 -> 4543 | C193: Direct Selling Establishments | D193: =apptab2!A172 -> 9.359 | E193: =apptab2!B172 -> -0.067260243 | F193: =apptab2!C172 -> 0.2292 | G193: =apptab2!F172 -> 0.0010871058
B194: =apptab2!E173 -> 4811 | C194: Scheduled Air Transportation | D194: =apptab2!A173 -> 9.627 | E194: =apptab2!B173 -> 0.24973975 | F194: =apptab2!C173 -> 0.1883 | G194: =apptab2!F173 -> 0.0042438246
B195: =apptab2!E174 -> 4812 | C195: Nonscheduled Air Transportation | D195: =apptab2!A174 -> 9.745 | E195: =apptab2!B174 -> 0.24673976 | F195: =apptab2!C174 -> 0.2926 | G195: =apptab2!F174 -> 0.00037288168
B196: =apptab2!E175 -> 4821 | C196: Rail Transportation | D196: =apptab2!A175 -> 9.485 | E196: =apptab2!B175 -> -0.010260247 | F196: =apptab2!C175 -> 0.3382 | G196: =apptab2!F175 -> 1.0779235e-05
B197: =apptab2!E176 -> 4831 | C197: Ocean & Great Lakes Water Transp. | D197: =apptab2!A176 -> 9.746 | E197: =apptab2!B176 -> 0.18173975 | F197: =apptab2!C176 -> 0.3775 | G197: =apptab2!F176 -> 0.00040362246
B198: =apptab2!E177 -> 4832 | C198: Inland Water Transportation | D198: =apptab2!A177 -> 9.706 | E198: =apptab2!B177 -> 0.073739752 | F198: =apptab2!C177 -> 0.4288 | G198: =apptab2!F177 -> 0.00025670548
B199: =apptab2!E178 -> 4841 | C199: General Freight Trucking | D199: =apptab2!A178 -> 9.375 | E199: =apptab2!B178 -> -0.11926024 | F199: =apptab2!C178 -> 0.2863 | G199: =apptab2!F178 -> 0.0083359415
B200: =apptab2!E179 -> 4842 | C200: Specialized Freight Trucking | D200: =apptab2!A179 -> 9.367 | E200: =apptab2!B179 -> -0.12626025 | F200: =apptab2!C179 -> 0.2854 | G200: =apptab2!F179 -> 0.0034250021
B201: =apptab2!E180 -> 4851 | C201: Urban Transit Systems | D201: =apptab2!A180 -> 9.602 | E201: =apptab2!B180 -> 0.025739754 | F201: =apptab2!C180 -> 0.395 | G201: =apptab2!F180 -> 0.0025319224
... B231: =apptab2!E210 -> 5174 | C231: Satellite Telecommunications | D231: =apptab2!A210 -> 9.873 | E231: =apptab2!B210 -> 0.25973976 | F231: =apptab2!C210 -> 0.4285 | G231: =apptab2!F210 -> 0.00010100543
B232: Appendix Table A-2 (continued)
B234: NAICS | C234: Industry | D234: Mean log earnings | E234: Mean worker effect (normalized to mean 0) | F234: Industry premium | G234: Percent of workforce
D235: (1) | E235: (2) | F235: (3) | G235: (4)
B236: =apptab2!E211 -> 5179 | C236: Other Telecommunications | D236: =apptab2!A211 -> 9.765 | E236: =apptab2!B211 -> 0.15673976 | F236: =apptab2!C211 -> 0.4207 | G236: =apptab2!F211 -> 0.0009038588
B237: =apptab2!E212 -> 5182 | C237: Data Processing, Hosting, and Related Svcs. | D237: =apptab2!A212 -> 9.806 | E237: =apptab2!B212 -> 0.24573976 | F237: =apptab2!C212 -> 0.3514 | G237: =apptab2!F212 -> 0.002800605
B238: =apptab2!E213 -> 5191 | C238: Other Information Services | D238: =apptab2!A213 -> 9.875 | E238: =apptab2!B213 -> 0.28973976 | F238: =apptab2!C213 -> 0.3913 | G238: =apptab2!F213 -> 0.0029028081
B239: =apptab2!E214 -> 5211 | C239: Monetary Authorities-Central Bank | D239: =apptab2!A214 -> 10.03 | E239: =apptab2!B214 -> 0.42573977 | F239: =apptab2!C214 -> 0.4103 | G239: =apptab2!F214 -> 0.00021478624
B240: =apptab2!E215 -> 5221 | C240: Depository Credit Intermediation | D240: =apptab2!A215 -> 9.493 | E240: =apptab2!B215 -> 0.044739753 | F240: =apptab2!C215 -> 0.2557 | G240: =apptab2!F215 -> 0.017111037
B241: =apptab2!E216 -> 5222 | C241: Nondepository Credit Intermediation | D241: =apptab2!A216 -> 9.663 | E241: =apptab2!B216 -> 0.12073975 | F241: =apptab2!C216 -> 0.3315 | G241: =apptab2!F216 -> 0.0057369485
B242: =apptab2!E217 -> 5223 | C242: Activities Related to Credit Intermediation | D242: =apptab2!A217 -> 9.602 | E242: =apptab2!B217 -> 0.089739755 | F242: =apptab2!C217 -> 0.3061 | G242: =apptab2!F217 -> 0.0026664634
B243: =apptab2!E218 -> 5231 | C243: Secur. & Commod. Intermed. & Brokerage | D243: =apptab2!A218 -> 10.27 | E243: =apptab2!B218 -> 0.66373974 | F243: =apptab2!C218 -> 0.4219 | G243: =apptab2!F218 -> 0.0047668172
B244: =apptab2!E219 -> 5232 | C244: Securities and Commodity Exchanges | D244: =apptab2!A219 -> 10.34 | E244: =apptab2!B219 -> 0.64373976 | F244: =apptab2!C219 -> 0.5108 | G244: =apptab2!F219 -> 7.2260795e-05
B245: =apptab2!E220 -> 5239 | C245: Other Financial Investment Activities | D245: =apptab2!A220 -> 10.15 | E245: =apptab2!B220 -> 0.52173978 | F245: =apptab2!C220 -> 0.4254 | G245: =apptab2!F220 -> 0.0040681632
B246: =apptab2!E221 -> 5241 | C246: Insurance Carriers | D246: =apptab2!A221 -> 9.718 | E246: =apptab2!B221 -> 0.14373976 | F246: =apptab2!C221 -> 0.3685 | G246: =apptab2!F221 -> 0.01275942
B247: =apptab2!E222 -> 5242 | C247: Agencies, Brokerages, and Other Insurance | D247: =apptab2!A222 -> 9.553 | E247: =apptab2!B222 -> 0.097739756 | F247: =apptab2!C222 -> 0.2487 | G247: =apptab2!F222 -> 0.0089268032
... B277: =apptab2!E252 -> 5622 | C277: Waste Treatment and Disposal | D277: =apptab2!A252 -> 9.612 | E277: =apptab2!B252 -> 0.0087397536 | F277: =apptab2!C252 -> 0.4029 | G277: =apptab2!F252 -> 0.0012671589
B278: Appendix Table A-2 (continued)
B280: NAICS | C280: Industry | D280: Mean log earnings | E280: Mean worker effect (normalized to mean 0) | F280: Industry premium | G280: Percent of workforce
...

Sheet tab A-3
B3: Intermediate estimates | R3: Table A-3. Testing the Role of Industry Composition Effects
E4: Psi(j,c) on psi(j) | I4: Alpha(j,c) on psi(j) | M4: Alpha(j,c) on alpha(j) | T4: Psi(j,c) on psi(j) | X4: Alpha(j,c) on psi(j) | AB4: Alpha(j,c) on alpha(j)
E7: -1 | F7: -2 | G7: -2 | I7: -3 | K7: -4 | M7: -3 | O7: -4 | T7: -1 | U7: -2 | V7: -2 | X7: -3 | Z7: -4 | AB7: -3 | AD7: -4
B8: Mean firm effect in CZ | R8: Mean pay premium in CZ
C9: Actual | D9: ='disclosed1-9b'!A13 -> psi_c | E9: =VALUE(SUBSTITUTE('disclosed1-9b'!J13,"*","")) -> 1.783 | I9: =VALUE(SUBSTITUTE('disclosed1-9b'!J46,"*","")) -> 0.7555 | M9: =VALUE(SUBSTITUTE('disclosed1-9b'!J77,"*","")) -> 0.6578 | S9: Expected given industry shares | T9: =+E9+E11 -> 2.2343 | X9: =+I9+I11 -> 4.5045 | AB9: =+M9+M11 -> 1.9728
E10: =VALUE(SUBSTITUTE('disclosed1-9b'!J14,"*","")) -> -0.2366 | I10: =VALUE(SUBSTITUTE('disclosed1-9b'!J47,"*","")) -> -0.3991 | M10: =VALUE(SUBSTITUTE('disclosed1-9b'!J78,"*","")) -> -0.4173 | T10: =-1*SQRT((E12)^2 - (E10)^2) -> -0.97778139 | X10: =-1*SQRT((I12)^2 - (I10)^2) -> -1.2844237 | AB10: =-1*SQRT((M12)^2 - (M10)^2) -> -0.86067006
C11: Expected given industry share | D11: =+'disclosed1-9b'!A15 -> Epsi_c | E11: =VALUE(SUBSTITUTE('disclosed1-9b'!J15,"*","")) -> 0.4513 | I11: =VALUE(SUBSTITUTE('disclosed1-9b'!J48,"*","")) -> 3.749 | M11: =VALUE(SUBSTITUTE('disclosed1-9b'!J79,"*","")) -> 1.315 | S11: Actual - expected | T11: =+E9 -> 1.783 | X11: =+I9 -> 0.7555 | AB11: =+M9 -> 0.6578
E12: =VALUE(SUBSTITUTE('disclosed1-9b'!J16,"*","")) -> -1.006 | I12: =VALUE(SUBSTITUTE('disclosed1-9b'!J49,"*","")) -> -1.345 | M12: =VALUE(SUBSTITUTE('disclosed1-9b'!J80,"*","")) -> -0.9565 | T12: =E10 -> -0.2366 | X12: =I10 -> -0.3991 | AB12: =M10 -> -0.4173
B13: Share of firms with psis in Q1 and Q5
C14: Actual | D14: =+'disclosed1-9b'!A17 -> s_psi_q1q5 | F14: =VALUE(SUBSTITUTE('disclosed1-9b'!M17,"*","")) -> 0.8061 | J14: =VALUE(SUBSTITUTE('disclosed1-9b'!M50,"*","")) -> 0.4292 | N14: =VALUE(SUBSTITUTE('disclosed1-9b'!M81,"*","")) -> 0.4369
F15: =VALUE(SUBSTITUTE('disclosed1-9b'!M18,"*","")) -> -0.1235 | J15: =VALUE(SUBSTITUTE('disclosed1-9b'!M51,"*","")) -> -0.1594 | N15: =VALUE(SUBSTITUTE('disclosed1-9b'!M82,"*","")) -> -0.1311
C16: Expected given industry share | D16: =+'disclosed1-9b'!A19 -> Es_psi_q1q5 | F16: =VALUE(SUBSTITUTE('disclosed1-9b'!M19,"*","")) -> 0.4017 | J16: =VALUE(SUBSTITUTE('disclosed1-9b'!M52,"*","")) -> 2.405 | N16: =VALUE(SUBSTITUTE('disclosed1-9b'!M83,"*","")) -> 0.9435
F17: =VALUE(SUBSTITUTE('disclosed1-9b'!M20,"*","")) -> -0.4592 | J17: =VALUE(SUBSTITUTE('disclosed1-9b'!M53,"*","")) -> -0.6118 | N17: =VALUE(SUBSTITUTE('disclosed1-9b'!M84,"*","")) -> -0.4655
B18: Average person effect in CZ | R18: Average person effect in CZ
C19: Actual | D19: =+'disclosed1-9b'!A5 -> alpha_c | G19: =VALUE(SUBSTITUTE('disclosed1-9b'!D5,"*","")) -> -0.2305 | K19: =VALUE(SUBSTITUTE('disclosed1-9b'!D38,"*","")) -> 0.389 | O19: =VALUE(SUBSTITUTE('disclosed1-9b'!D69,"*","")) -> 0.6189 | S19: Expected given industry shares | V19: =+G19+G21 -> 1.9225 | Z19: =+K19+K21 -> 2.435 | AD19: =+O19+O21 -> 0.835
G20: =VALUE(SUBSTITUTE('disclosed1-9b'!D6,"*","")) -> -0.3905 | K20: =VALUE(SUBSTITUTE('disclosed1-9b'!D39,"*","")) -> -0.2155 | O20: =VALUE(SUBSTITUTE('disclosed1-9b'!D70,"*","")) -> -0.1088 | V20: =-1*SQRT((G22)^2 - (G20)^2) -> -1.2347205 | Z20: =-1*SQRT((K22)^2 - (K20)^2) -> -0.72682554 | AD20: =-1*SQRT((O22)^2 - (O20)^2) -> -0.33423765
C21: Expected given industry share | D21: =+'disclosed1-9b'!A7 -> Ealpha_c | G21: =VALUE(SUBSTITUTE('disclosed1-9b'!D7,"*","")) -> 2.153 | K21: =VALUE(SUBSTITUTE('disclosed1-9b'!D40,"*","")) -> 2.046 | O21: =VALUE(SUBSTITUTE('disclosed1-9b'!D71,"*","")) -> 0.2161 | S21: Actual - expected | V21: =+G19 -> -0.2305 | Z21: =+K19 -> 0.389 | AD21: =+O19 -> 0.6189
G22: =VALUE(SUBSTITUTE('disclosed1-9b'!D8,"*","")) -> -1.295 | K22: =VALUE(SUBSTITUTE('disclosed1-9b'!D41,"*","")) -> -0.7581 | O22: =VALUE(SUBSTITUTE('disclosed1-9b'!D72,"*","")) -> -0.3515 | V22: =G20 -> -0.3905 | Z22: =K20 -> -0.2155 | AD22: =O20 -> -0.1088
B23: Share of workers with alphas in Q1 and Q5
C24: Actual | D24: =+'disclosed1-9b'!A9 -> s_alpha_q1q5 | H24: =VALUE(SUBSTITUTE('disclosed1-9b'!G9,"*","")) -> 0.4509 | L24: =VALUE(SUBSTITUTE('disclosed1-9b'!G42,"*","")) -> 1.178 | P24: =VALUE(SUBSTITUTE('disclosed1-9b'!G73,"*","")) -> 1.465
H25: =VALUE(SUBSTITUTE('disclosed1-9b'!G10,"*","")) -> -0.8431 | L25: =VALUE(SUBSTITUTE('disclosed1-9b'!G43,"*","")) -> -0.7429 | P25: =VALUE(SUBSTITUTE('disclosed1-9b'!G74,"*","")) -> -0.3986
C26: Expected given industry share | D26: =+'disclosed1-9b'!A11 -> Es_alpha_q1q5 | H26: =VALUE(SUBSTITUTE('disclosed1-9b'!G11,"*","")) -> 0.917 | L26: =VALUE(SUBSTITUTE('disclosed1-9b'!G44,"*","")) -> 5.875 | P26: =VALUE(SUBSTITUTE('disclosed1-9b'!G75,"*","")) -> 3.639
H27: =VALUE(SUBSTITUTE('disclosed1-9b'!G12,"*","")) -> -2.808 | L27: =VALUE(SUBSTITUTE('disclosed1-9b'!G45,"*","")) -> -3.957 | P27: =VALUE(SUBSTITUTE('disclosed1-9b'!G76,"*","")) -> -1.986
B29: R2 | E29: =1-(1-VALUE('disclosed1-9b'!J29))*(59-14-1)/(59-1) -> 0.80063448 | F29: =1-(1-VALUE('disclosed1-9b'!M29))*(59-14-1)/(59-1) -> 0.769 | G29: =1-(1-VALUE('disclosed1-9b'!D29))*(59-14-1)/(59-1) -> 0.38566897 | H29: =1-(1-VALUE('disclosed1-9b'!G29))*(59-14-1)/(59-1) -> 0.3017731 | I29: =1-(1-VALUE('disclosed1-9b'!J60))*(59-14-1)/(59-1) -> 0.76057931 | J29: =1-(1-VALUE('disclosed1-9b'!M60))*(59-14-1)/(59-1) -> 0.82430345 | K29: =1-(1-VALUE('disclosed1-9b'!D60))*(59-14-1)/(59-1) -> 0.84789655 | L29: =1-(1-VALUE('disclosed1-9b'!G60))*(59-14-1)/(59-1) -> 0.7602 | M29: =1-(1-VALUE('disclosed1-9b'!J93))*(59-14-1)/(59-1) -> 0.66605517 | N29: =1-(1-VALUE('disclosed1-9b'!M93))*(59-14-1)/(59-1) -> 0.7463931 | O29: =1-(1-VALUE('disclosed1-9b'!D93))*(59-14-1)/(59-1) -> 0.85912414 | P29: =1-(1-VALUE('disclosed1-9b'!G93))*(59-14-1)/(59-1) -> 0.81633793 | R29: R-squared | T29: =E29 -> 0.80063448 | U29: =1-(1-VALUE('disclosed1-9b'!T29))*(59-14-1)/(59-1) -> 0.43831724 | V29: =G29 -> 0.38566897 | X29: =I29 -> 0.76057931 | Y29: =1-(1-VALUE('disclosed1-9b'!T60))*(59-14-1)/(59-1) -> 0.52297931 | Z29: =K29 -> 0.84789655 | AB29: =M29 -> 0.66605517 | AC29: =1-(1-VALUE('disclosed1-9b'!T93))*(59-14-1)/(59-1) -> 0.55309655 | AD29: =O29 -> 0.85912414
B30: R2 (adj) | E30: =VALUE(+'disclosed1-9b'!J29) -> 0.7372 | F30: =VALUE(+'disclosed1-9b'!M29) -> 0.6955 | G30: =VALUE(+'disclosed1-9b'!D29) -> 0.1902 | H30: =VALUE(+'disclosed1-9b'!G29) -> 0.07961 | I30: =VALUE(+'disclosed1-9b'!J60) -> 0.6844 | J30: =VALUE(+'disclosed1-9b'!M60) -> 0.7684 | K30: =VALUE(+'disclosed1-9b'!D60) -> 0.7995 | L30: =VALUE(+'disclosed1-9b'!G60) -> 0.6839 | M30: =VALUE(+'disclosed1-9b'!J93) -> 0.5598 | N30: =VALUE(+'disclosed1-9b'!M93) -> 0.6657 | O30: =VALUE(+'disclosed1-9b'!D93) -> 0.8143 | P30: =VALUE(+'disclosed1-9b'!G93) -> 0.7579 | R30: Adjusted R-squared | T30: =E30 -> 0.7372 | U30: =VALUE(+'disclosed1-9b'!T29) -> 0.2596 | V30: =G30 -> 0.1902 | X30: =I30 -> 0.6844 | Y30: =VALUE(+'disclosed1-9b'!T60) -> 0.3712 | Z30: =K30 -> 0.7995 | AB30: =M30 -> 0.5598 | AC30: =VALUE(+'disclosed1-9b'!T93) -> 0.4109 | AD30: =O30 -> 0.8143
B32: Note: N≈60. Each coefficient is from a regression of the column variable on the row variables, with indicators for four regions and for each of approximately 10 composite Czs. | R32: Note: N≈60. Each coefficient is from a regression of the column variable on the row variables, with indicators for four regions and for each of approximately 10 composite CZs. Standard errors are approximated.

Sheet T7-8calcs
A1: This sheet contains intermediate calculations to construct R2 statistics for the non-composite CZs in the samples, based on disclosed Census data
A4: ="Output 9a - Bivariate Regressions, Top59 100%" -> Output 9a - Bivariate Regressions, Top59 100%
A5: ="" | B5: ="(1)" -> (1) | C5: ="(2)" -> (2) | D5: ="(3)" -> (3) | E5: ="(4)" -> (4) | F5: ="(5)" -> (5) | G5: ="(6)" -> (6) | H5: ="(7)" -> (7) | I5: ="(8)" -> (8) | J5: ="(9)" -> (9) | K5: ="(10)" -> (10)
A6: ="" | B6: Mean/SD | C6: Dependent Variable: "b_pjc_pj" | F6: Dependent Variable: "b_ajc_pj" | I6: Dependent Variable: "b_ajc_aj"
A8: Theta - mean | C8: ='disclosed1-9a'!B57 -> 0.880 | D8: =C8 -> 0.880 | E8: =D8 -> 0.880 | F8: ='disclosed1-9a'!B61 -> .7988 | G8: =F8 -> .7988 | H8: =G8 -> .7988 | I8: ='disclosed1-9a'!B65 -> 0.863 | J8: =I8 -> 0.863 | K8: =J8 -> 0.863
A9: theta - SD | C9: ='disclosed1-9a'!B58 -> 0.0818 | D9: =C9 -> 0.0818 | E9: =D9 -> 0.0818 | F9: ='disclosed1-9a'!B62 -> .1341 | G9: =F9 -> .1341 | H9: =G9 -> .1341 | I9: ='disclosed1-9a'!B66 -> 0.0970 | J9: =I9 -> 0.0970 | K9: =J9 -> 0.0970
A11: ="Division-CZ dummies" -> Division-CZ dummies | C11: ="No" -> No | D11: ="Yes" -> Yes | E11: ="Yes" -> Yes | F11: ="No" -> No | G11: ="Yes" -> Yes | H11: ="Yes" -> Yes | I11: ="No" -> No | J11: ="Yes" -> Yes | K11: ="Yes" -> Yes
A12: ="Region dummies" -> Region dummies | C12: ="No" -> No | D12: ="No" -> No | E12: ="Yes" -> Yes | F12: ="No" -> No | G12: ="No" -> No | H12: ="Yes" -> Yes | I12: ="No" -> No | J12: ="No" -> No | K12: ="Yes" -> Yes
A13: ="N" -> N | B13: ='disclosed1-9a'!B72 -> 60 | C13: =B13 -> 60 | F13: =C13 -> 60 | I13: =F13 -> 60
A15: N | B15: 59
A16: k | B16: 12 | C16: 0 | D16: 9 | E16: 12 | F16: 0 | G16: 9 | H16: 12 | I16: 0 | J16: 9 | K16: 12
A17: Membership
A18: Original output
A19: beta | B19: ='disclosed1-9a'!B37 -> .1178 | C19: ='disclosed1-9a'!C37 -> .3291 | D19: ='disclosed1-9a'!D37 -> .6368 | E19: ='disclosed1-9a'!E37 -> .5403 | F19: ='disclosed1-9a'!F37 -> .2339 | G19: ='disclosed1-9a'!G37 -> .1561 | H19: ='disclosed1-9a'!H37 -> .256 | I19: ='disclosed1-9a'!I37 -> .1826 | ... K19: ='disclosed1-9a'!K37 -> .7034*
A20: SE | B20: ='disclosed1-9a'!B38 -> .05989 | C20: ='disclosed1-9a'!C38 -> (.2479) | D20: ='disclosed1-9a'!D38 -> (.4074) | E20: ='disclosed1-9a'!E38 -> (.5216) | F20: ='disclosed1-9a'!F38 -> (.4062) | G20: ='disclosed1-9a'!G38 -> (.3036) | H20: ='disclosed1-9a'!H38 -> (.4258) | I20: ='disclosed1-9a'!I38 -> (.326) | ... K20: ='disclosed1-9a'!K38 -> (.3592)
A21: r2 adj | C21: ='disclosed1-9a'!C39 -> .04148 | D21: ='disclosed1-9a'!D39 -> .1519 | E21: ='disclosed1-9a'!E39 -> .09966 | F21: ='disclosed1-9a'!F39 -> -.00644 | G21: ='disclosed1-9a'!G39 -> .5049 | H21: ='disclosed1-9a'!H39 -> .4926 | I21: ='disclosed1-9a'!I39 -> -.004619 | J21: ='disclosed1-9a'!J39 -> .4934 | K21: ='disclosed1-9a'!K39 -> .4911
A22: RMSE | C22: ='disclosed1-9a'!C40 -> .08012 | D22: ='disclosed1-9a'!D40 -> .07536 | E22: ='disclosed1-9a'!E40 -> .07765 | F22: ='disclosed1-9a'!F40 -> .1345 | G22: ='disclosed1-9a'!G40 -> .09436 | H22: ='disclosed1-9a'!H40 -> .09553 | I22: ='disclosed1-9a'!I40 -> .09725 | J22: ='disclosed1-9a'!J40 -> .06906 | K22: ='disclosed1-9a'!K40 -> .06921
A23: Calculations
A24: R2 of regression of X on controls | C24: 0 | D24: 0.5663 | E24: 0.8495 | F24: =+C24 -> 0 | G24: =+D24 -> 0.5663 | H24: =+E24 -> 0.8495 | I24: =+F24 -> 0 | J24: =+G24 -> 0.5663 | K24: =+H24 -> 0.8495
A25: R2 of regression of theta on X, Z | C25: =1-((($B$15-C$16-1)/($B$15-1))*(1-C21)) -> 0.04148 | D25: =1-((($B$15-D$16-1)/($B$15-1))*(1-D21)) -> 0.28350172 | E25: =1-((($B$15-E$16-1)/($B$15-1))*(1-E21)) -> 0.28593724 | F25: =1-((($B$15-F$16-1)/($B$15-1))*(1-F21)) -> -0.00644 | G25: =1-((($B$15-G$16-1)/($B$15-1))*(1-G21)) -> 0.58172586 | H25: =1-((($B$15-H$16-1)/($B$15-1))*(1-H21)) -> 0.59757931 | I25: =1-((($B$15-I$16-1)/($B$15-1))*(1-I21)) -> -0.004619 | J25: =1-((($B$15-J$16-1)/($B$15-1))*(1-J21)) -> 0.57201034 | K25: =1-((($B$15-K$16-1)/($B$15-1))*(1-K21)) -> 0.59638966
A26: V(xtilde) | C26: =(1-C24)*($B20^2) -> 0.0035868121 | D26: =(1-D24)*($B20^2) -> 0.0015556004 | E26: =(1-E24)*($B20^2) -> 0.00053981522 | F26: =(1-F24)*($B20^2) -> 0.0035868121 | G26: =(1-G24)*($B20^2) -> 0.0015556004 | H26: =(1-H24)*($B20^2) -> 0.00053981522 | I26: =(1-I24)*($B20^2) -> 0.0035868121 | J26: =(1-J24)*($B20^2) -> 0.0015556004 | K26: =(1-K24)*($B20^2) -> 0.00053981522
A27: V(prediction from regression of theta on X, Z) | C27: =C25*(C$9^2) -> 0.00027755264 | D27: =D25*(D$9^2) -> 0.0018969781 | E27: =E25*(E$9^2) -> 0.0019132747 | F27: =F25*(F$9^2) -> -0.0001158093 | G27: =G25*(G$9^2) -> 0.010461066 | H27: =H25*(H$9^2) -> 0.010746155 | I27: =I25*(I$9^2) -> -4.3460171e-05 | J27: =J25*(J$9^2) -> 0.0053820453 | K27: =K25*(K$9^2) -> 0.0056114303
A28: V(prediction from regression of theta on Z) | C28: =C27-C26*(VALUE(SUBSTITUTE(C19,"*",""))^2) -> -0.00011092354 | D28: =D27-D26*(VALUE(SUBSTITUTE(D19,"*",""))^2) -> 0.00126616 | E28: =E27-E26*(VALUE(SUBSTITUTE(E19,"*",""))^2) -> 0.0017556896 | F28: =F27-F26*(VALUE(SUBSTITUTE(F19,"*",""))^2) -> -0.00031204095 | G28: =G27-G26*(VALUE(SUBSTITUTE(G19,"*",""))^2) -> 0.01042316 | H28: =H27-H26*(VALUE(SUBSTITUTE(H19,"*",""))^2) -> 0.010710778 | I28: =I27-I26*(VALUE(SUBSTITUTE(I19,"*",""))^2) -> -0.00016305439 | J28: =J27-J26*(VALUE(SUBSTITUTE(J19,"*",""))^2) -> 0.0051272658 | K28: =K27-K26*(VALUE(SUBSTITUTE(K19,"*",""))^2) -> 0.005344345
A29: r2 of regression of theta on Z | C29: =C28/(C$9^2) -> -0.016577427 | D29: =D28/(D9^2) -> 0.18922651 | E29: =E28/(E9^2) -> 0.26238629 | F29: =F28/(F9^2) -> -0.01735218 | G29: =G28/(G9^2) -> 0.57961798 | H29: =H28/(H9^2) -> 0.59561202 | I29: =I28/(I9^2) -> -0.017329619 | J29: =J28/(J9^2) -> 0.54493207 | K29: =K28/(K9^2) -> 0.56800351
A32: Coveratge
A33: Original output
A34: beta | B34: ='disclosed1-9a'!B41 -> .1303 | C34: ='disclosed1-9a'!C41 -> .3196 | D34: ='disclosed1-9a'!D41 -> .605 | E34: ='disclosed1-9a'!E41 -> .4496 | F34: ='disclosed1-9a'!F41 -> .1881 | G34: ='disclosed1-9a'!G41 -> .1244 | H34: ='disclosed1-9a'!H41 -> .1463 | I34: ='disclosed1-9a'!I41 -> .1492 | ... K34: ='disclosed1-9a'!K41 -> .6131*
A35: SE | B35: ='disclosed1-9a'!B42 -> .06013 | C35: ='disclosed1-9a'!C42 -> (.2477) | D35: ='disclosed1-9a'!D42 -> (.4098) | E35: ='disclosed1-9a'!E42 -> (.5278) | F35: ='disclosed1-9a'!F42 -> (.4043) | G35: ='disclosed1-9a'!G42 -> (.3001) | H35: ='disclosed1-9a'!H42 -> (.4202) | I35: ='disclosed1-9a'!I42 -> (.3256) | ... K35: ='disclosed1-9a'!K42 -> (.3628)
A36: r2 adj | C36: ='disclosed1-9a'!C43 -> .03857 | D36: ='disclosed1-9a'!D43 -> .1397 | E36: ='disclosed1-9a'!E43 -> .08972 | F36: ='disclosed1-9a'!F43 -> -.01031 | G36: ='disclosed1-9a'!G43 -> .5038 | H36: ='disclosed1-9a'!H43 -> .4906 | I36: ='disclosed1-9a'!I43 -> -.008845 | J36: ='disclosed1-9a'!J43 -> .4896 | K36: ='disclosed1-9a'!K43 -> .4823
A37: RMSE | C37: ='disclosed1-9a'!C44 -> .08024 | D37: ='disclosed1-9a'!D44 -> .0759 | E37: ='disclosed1-9a'!E44 -> .07808 | F37: ='disclosed1-9a'!F44 -> .1348 | G37: ='disclosed1-9a'!G44 -> .09447 | H37: ='disclosed1-9a'!H44 -> .09572 | I37: ='disclosed1-9a'!I44 -> .09746 | J37: ='disclosed1-9a'!J44 -> .06932 | K37: ='disclosed1-9a'!K44 -> .06982
A38: Calculations
A39: R2 of regression of X on controls | C39: 0 | D39: 0.5654 | E39: 0.8422 | F39: =+C39 -> 0 | G39: =+D39 -> 0.5654 | H39: =+E39 -> 0.8422 | I39: =+F39 -> 0 | J39: =+G39 -> 0.5654 | K39: =+H39 -> 0.8422
A40: R2 of regression of theta on X, Z | C40: =1-((($B$15-C$16-1)/($B$15-1))*(1-C36)) -> 0.03857 | D40: =1-((($B$15-D$16-1)/($B$15-1))*(1-D36)) -> 0.27319483 | E40: =1-((($B$15-E$16-1)/($B$15-1))*(1-E36)) -> 0.27805379 | F40: =1-((($B$15-F$16-1)/($B$15-1))*(1-F36)) -> -0.01031 | G40: =1-((($B$15-G$16-1)/($B$15-1))*(1-G36)) -> 0.58079655 | H40: =1-((($B$15-H$16-1)/($B$15-1))*(1-H36)) -> 0.5959931 | I40: =1-((($B$15-I$16-1)/($B$15-1))*(1-I36)) -> -0.008845 | J40: =1-((($B$15-J$16-1)/($B$15-1))*(1-J36)) -> 0.5688 | K40: =1-((($B$15-K$16-1)/($B$15-1))*(1-K36)) -> 0.58941034
A41: V(xtilde) | C41: =(1-C39)*($B35^2) -> 0.0036156169 | D41: =(1-D39)*($B35^2) -> 0.0015713471 | E41: =(1-E39)*($B35^2) -> 0.00057054435 | F41: =(1-F39)*($B35^2) -> 0.0036156169 | G41: =(1-G39)*($B35^2) -> 0.0015713471 | H41: =(1-H39)*($B35^2) -> 0.00057054435 | I41: =(1-I39)*($B35^2) -> 0.0036156169 | J41: =(1-J39)*($B35^2) -> 0.0015713471 | K41: =(1-K39)*($B35^2) -> 0.00057054435
A42: V(prediction from regression of theta on X, Z) | C42: =C40*(C$9^2) -> 0.00025808113 | D42: =D40*(D$9^2) -> 0.0018280122 | E42: =E40*(E$9^2) -> 0.0018605247 | F42: =F40*(F$9^2) -> -0.00018540277 | G42: =G40*(G$9^2) -> 0.010444354 | H42: =H40*(H$9^2) -> 0.010717631 | I42: =I40*(I$9^2) -> -8.3222605e-05 | J42: =J40*(J$9^2) -> 0.0053518392 | K42: =K40*(K$9^2) -> 0.0055457619
A43: V(prediction from regression of theta on Z) | C43: =C42-C41*(VALUE(SUBSTITUTE(C34,"*",""))^2) -> -0.00011123302 | D43: =D42-D41*(VALUE(SUBSTITUTE(D34,"*",""))^2) -> 0.0012528598 | E43: =E42-E41*(VALUE(SUBSTITUTE(E34,"*",""))^2) -> 0.0017451947 | F43: =F42-F41*(VALUE(SUBSTITUTE(F34,"*",""))^2) -> -0.00031332912 | G43: =G42-G41*(VALUE(SUBSTITUTE(G34,"*",""))^2) -> 0.010420037 | H43: =H42-H41*(VALUE(SUBSTITUTE(H34,"*",""))^2) -> 0.010705419 | I43: =I42-I41*(VALUE(SUBSTITUTE(I34,"*",""))^2) -> -0.00016370855 | J43: =J42-J41*(VALUE(SUBSTITUTE(J34,"*",""))^2) -> 0.0051210991 | K43: =K42-K41*(VALUE(SUBSTITUTE(K34,"*",""))^2) -> 0.0053312991
A44: r2 of regression of theta on Z | C44: =C43/(C$9^2) -> -0.016623679 | D44: =D43/(D$9^2) -> 0.18723881 | E44: =E43/(E$9^2) -> 0.26081784 | F44: =F43/(F$9^2) -> -0.017423813 | G44: =G43/(G$9^2) -> 0.57944431 | H44: =H43/(H$9^2) -> 0.59531402 | I44: =I43/(I$9^2) -> -0.017399145 | J44: =J43/(J$9^2) -> 0.54427666 | K44: =K43/(K$9^2) -> 0.56661697
A47: Minimum wages
A48: Original output
A49: beta | B49: ='disclosed1-9a'!B49 -> 2.089 | C49: ='disclosed1-9a'!C49 -> .07224 | D49: ='disclosed1-9a'!D49 -> .2625** | E49: ='disclosed1-9a'!E49 -> .2417* | F49: ='disclosed1-9a'!F49 -> .6453*** | G49: ='disclosed1-9a'!G49 -> .3435** | H49: ='disclosed1-9a'!H49 -> .4666*** | I49: ='disclosed1-9a'!I49 -> .4692*** | ... K49: ='disclosed1-9a'!K49 -> .4191***
A50: SE | B50: ='disclosed1-9a'!B50 -> .1112 | C50: ='disclosed1-9a'!C50 -> (.08676) | D50: ='disclosed1-9a'!D50 -> (.1052) | E50: ='disclosed1-9a'!E50 -> (.1438) | F50: ='disclosed1-9a'!F50 -> (.1369) | G50: ='disclosed1-9a'!G50 -> (.1392) | H50: ='disclosed1-9a'!H50 -> (.1342) | I50: ='disclosed1-9a'!I50 -> (.103) | ... K50: ='disclosed1-9a'!K50 -> (.09526)
A51: r2 adj | C51: ='disclosed1-9a'!C51 -> -.007744 | D51: ='disclosed1-9a'!D51 -> .1274 | E51: ='disclosed1-9a'!E51 -> .1249 | F51: ='disclosed1-9a'!F51 -> .2736 | G51: ='disclosed1-9a'!G51 -> .5751 | H51: ='disclosed1-9a'!H51 -> .5755 | I51: ='disclosed1-9a'!I51 -> .2766 | J51: ='disclosed1-9a'!J51 -> .5747 | K51: ='disclosed1-9a'!K51 -> .5794
A52: RMSE | C52: ='disclosed1-9a'!C52 -> .08215 | D52: ='disclosed1-9a'!D52 -> .07644 | E52: ='disclosed1-9a'!E52 -> .07655 | F52: ='disclosed1-9a'!F52 -> .1143 | G52: ='disclosed1-9a'!G52 -> .08743 | H52: ='disclosed1-9a'!H52 -> .08738 | I52: ='disclosed1-9a'!I52 -> .08253 | J52: ='disclosed1-9a'!J52 -> .06328 | K52: ='disclosed1-9a'!K52 -> .06292
A53: Calculations
A54: R2 of regression of X on controls | C54: 0 | D54: 0.2977 | E54: 0.5829 | F54: =+C54 -> 0 | G54: =+D54 -> 0.2977 | H54: =+E54 -> 0.5829 | I54: =+F54 -> 0 | J54: =+G54 -> 0.2977 | K54: =+H54 -> 0.5829
A55: R2 of regression of theta on X, Z | C55: =1-((($B$15-C$16-1)/($B$15-1))*(1-C51)) -> -0.007744 | D55: =1-((($B$15-D$16-1)/($B$15-1))*(1-D51)) -> 0.26280345 | E55: =1-((($B$15-E$16-1)/($B$15-1))*(1-E51)) -> 0.30595517 | F55: =1-((($B$15-F$16-1)/($B$15-1))*(1-F51)) -> 0.2736 | G55: =1-((($B$15-G$16-1)/($B$15-1))*(1-G51)) -> 0.64103276 | H55: =1-((($B$15-H$16-1)/($B$15-1))*(1-H51)) -> 0.66332759 | I55: =1-((($B$15-I$16-1)/($B$15-1))*(1-I51)) -> 0.2766 | J55: =1-((($B$15-J$16-1)/($B$15-1))*(1-J51)) -> 0.64069483 | K55: =1-((($B$15-K$16-1)/($B$15-1))*(1-K51)) -> 0.66642069
A56: V(xtilde) | C56: =(1-C54)*($B50^2) -> 0.01236544 | D56: =(1-D54)*($B50^2) -> 0.0086842485 | E56: =(1-E54)*($B50^2) -> 0.005157625 | F56: =(1-F54)*($B50^2) -> 0.01236544 | G56: =(1-G54)*($B50^2) -> 0.0086842485 | H56: =(1-H54)*($B50^2) -> 0.005157625 | I56: =(1-I54)*($B50^2) -> 0.01236544 | J56: =(1-J54)*($B50^2) -> 0.0086842485 | K56: =(1-K54)*($B50^2) -> 0.005157625
A57: V(prediction from regression of theta on X, Z) | C57: =C55*(C$9^2) -> -5.1816963e-05 | D57: =D55*(D$9^2) -> 0.0017584809 | E57: =E55*(E$9^2) -> 0.0020472195 | F57: =F55*(F$9^2) -> 0.0049200968 | G57: =G55*(G$9^2) -> 0.01152757 | H57: =H55*(H$9^2) -> 0.011928494 | I57: =I55*(I$9^2) -> 0.0026025294 | J57: =J55*(J$9^2) -> 0.0060282976 | K57: =K55*(K$9^2) -> 0.0062703523
A58: V(prediction from regression of theta on Z) | C58: =C57-C56*(VALUE(SUBSTITUTE(C49,"*",""))^2) -> -0.00011634747 | D58: =D57-D56*(VALUE(SUBSTITUTE(D49,"*",""))^2) -> 0.0011600819 | E58: =E57-E56*(VALUE(SUBSTITUTE(E49,"*",""))^2) -> 0.0017459168 | F58: =F57-F56*(VALUE(SUBSTITUTE(F49,"*",""))^2) -> -0.0002290219 | G58: =G57-G56*(VALUE(SUBSTITUTE(G49,"*",""))^2) -> 0.010502896 | H58: =H57-H56*(VALUE(SUBSTITUTE(H49,"*",""))^2) -> 0.010805599 | I58: =I57-I56*(VALUE(SUBSTITUTE(I49,"*",""))^2) -> -0.0001197054 | J58: =J57-J56*(VALUE(SUBSTITUTE(J49,"*",""))^2) -> 0.0051395863 | K58: =K57-K56*(VALUE(SUBSTITUTE(K49,"*",""))^2) -> 0.0053644422
A59: r2 of regression of theta on Z | C59: =C58/(C$9^2) -> -0.017388028 | D59: =D58/(D$9^2) -> 0.17337324 | E59: =E58/(E$9^2) -> 0.26092574 | F59: =F58/(F$9^2) -> -0.012735601 | G59: =G58/(G$9^2) -> 0.58405201 | H59: =H58/(H$9^2) -> 0.60088489 | I59: =I58/(I$9^2) -> -0.012722436 | J59: =J58/(J$9^2) -> 0.5462415 | K59: =K58/(K$9^2) -> 0.57013946
A63: Averages | C63: =(C29+C44+C59)/3 -> -0.016863044 | D63: =(D29+D44+D59)/3 -> 0.18327952 | E63: =(E29+E44+E59)/3 -> 0.26137662 | F63: =(F29+F44+F59)/3 -> -0.015837198 | G63: =(G29+G44+G59)/3 -> 0.5810381 | H63: =(H29+H44+H59)/3 -> 0.59727031 | I63: =(I29+I44+I59)/3 -> -0.015817067 | J63: =(J29+J44+J59)/3 -> 0.54515008 | K63: =(K29+K44+K59)/3 -> 0.56825332
A71: Calculations for R2
A72: R2 for regression of y on the controls (approximate)
C73: =E63 -> 0.26137662 | D73: =K63 -> 0.56825332 | E73: =H63 -> 0.59727031
A74: theta(psi, psi)
B75: Adjusted R2 | D75: =VALUE('disclosed1-9a'!K59) -> 0.5309 | E75: =VALUE('disclosed1-9a'!H59) -> 0.6222
B76: Actual R2 | D76: =1-(((59-12-1)/(59-1))*(1-D75)) -> 0.62795517 | E76: =1-(((59-12-1)/(59-1))*(1-E75)) -> 0.70036552
B77: Incremental R2 | D77: =D76-D$73 -> 0.059701856 | E77: =E76-E$73 -> 0.10309521
B78: Within-region R2 | D78: =D77/(1-D$73) -> 0.13827983 | E78: =E77/(1-E$73) -> 0.25599107
A79: theta(alpha, alpha)
B80: Adj. R2 | C80: =VALUE('disclosed1-9a'!E67) -> 0.2053 | E80: =VALUE('disclosed1-9a'!H67) -> 0.8687
B81: Actual R2 | C81: =1-(((59-12-1)/(59-1))*(1-C80)) -> 0.36972069 | E81: =1-(((59-12-1)/(59-1))*(1-E80)) -> 0.89586552
B82: Incremental R2 | C82: =C81-C$73 -> 0.10834407 | E82: =E81-E$73 -> 0.29859521
B83: Within-region R2 | C83: =C82/(1-C$73) -> 0.14668378 | E83: =E82/(1-E$73) -> 0.74142834
A84: theta(alpha, psi)
B85: Adj. R2 | C85: =VALUE('disclosed1-9a'!E63) -> 0.3065 | D85: =VALUE('disclosed1-9a'!K63) -> 0.8578
B86: Actual R2 | C86: =1-(((59-12-1)/(59-1))*(1-C85)) -> 0.44998276 | D86: =1-(((59-12-1)/(59-1))*(1-D85)) -> 0.88722069
B87: Incremental R2 | C87: =C86-C$73 -> 0.18860614 | D87: =D86-D$73 -> 0.31896737
B88: Within-region R2 | C88: =C87/(1-C$73) -> 0.25534818 | D88: =D87/(1-D$73) -> 0.73878361

Sheet disclosed1-1
A1: Output 1: Descriptive Table
A3: ="" | B3: ="(1)" -> (1) | C3: ="(2)" -> (2) | D3: ="(3)" -> (3) | E3: ="(4)" -> (4)
C4: Sample 1
A5: ="" | B5: Sample 1 | C5: Industry stayers subgroup | D5: Industry movers subgroup | E5: Event study sample
A6: ="" | B6: ="mean/sd" -> mean/sd | C6: ="mean/sd" -> mean/sd | D6: ="mean/sd" -> mean/sd | E6: ="mean/sd" -> mean/sd
A7: lne | B7: 15510 | C7: 16050 | D7: 14630 | E7: 16350
A8: ="" | B8: (18020) | C8: (19710) | D8: (14860) | E8: (45670)
A9: ="age" -> age | B9: 42.43 | C9: 44.04 | D9: 39.85 | E9: .001232
A10: ="" | B10: (10.78) | C10: (10.71) | D10: (10.39) | E10: (.2631)
A11: ="Gender" -> Gender | B11: .4734 | C11: .4839 | D11: .4565 | E11: .4629
A12: ="" | B12: (.4993) | C12: (.4997) | D12: (.4981) | E12: (.4986)
A13: ="forborn" -> forborn | B13: .1607 | C13: .1632 | D13: .1566 | E13: .143
A14: ="" | B14: (.3672) | C14: (.3695) | D14: (.3634) | E14: (.3501)
A15: ="hisp" -> hisp | B15: .1334 | C15: .1295 | D15: .1396 | E15: .1228
A16: ="" | B16: (.34) | C16: (.3358) | D16: (.3466) | E16: (.3282)
A17: ="czcnt1" -> czcnt1 | B17: .786 | C17: .824 | D17: .7248 | E17: .9993
A18: ="" | B18: (.4101) | C18: (.3808) | D18: (.4466) | E18: (.02634)
A19: ="czcnt2" -> czcnt2 | B19: .1734 | C19: .1434 | D19: .2218 | E19: .0006942
A20: ="" | B20: (.3786) | C20: (.3504) | D20: (.4154) | E20: (.02634)
A21: ="czcnt3" -> czcnt3 | B21: .04057 | C21: .03259 | D21: .05341
A22: ="" | B22: (.1973) | C22: (.1776) | D22: (.2248)
A23: ="naics4dswitch0" -> naics4dswitch0 | B23: .6166
A24: ="" | B24: (.4862)
A25: ="naics4dswitch1" -> naics4dswitch1 | B25: .2607 | D25: .68
A26: ="" | B26: (.439) | D26: (.4665)
A27: ="naics4dswitch2" -> naics4dswitch2 | B27: .1227 | D27: .32
A28: ="" | B28: (.3281) | D28: (.4665)
A29: ="qobserved" -> qobserved | B29: 25.85 | C29: 27.19 | D29: 23.7 | E29: 10.01
A30: ="" | B30: (7.683) | C30: (7.757) | D30: (7.045) | E30: (.2634)
A31: ="Observations" -> Observations | B31: 2505000000 | C31: 1544000000 | D31: 960400000 | E31: 87390000
A32: ="Unique PIKs" -> Unique PIKs | B32: 111700000 | C32: 65670000 | D32: 46050000 | E32: 8736000

Sheet disclosed1-5
A1: ="Ouput 5: Regressions coefficients of psi_j on industry effects from alternative specifications" -> Ouput 5: Regressions coefficients of psi_j on industry effects from alternative specifications
A3: ="" | B3: ="(1)" -> (1) | C3: ="(2)" -> (2) | D3: ="(3)" -> (3) | E3: ="(4)" -> (4) | F3: ="(5)" -> (5) | G3: ="(6)" -> (6)
A4: ="" | B4: ="M1" -> M1 | C4: ="M2" -> M2 | D4: ="M4" -> M4 | E4: ="M6" -> M6 | F4: ="M7" -> M7 | G4: ="M8" -> M8
A6: psi_j | B6: ="1.862***" -> 1.862*** | C6: ="1.627***" -> 1.627*** | D6: ="1.609***" -> 1.609*** | E6: ="0.621***" -> 0.621*** | F6: ="0.618***" -> 0.618*** | G6: ="0.658***" -> 0.658***
A7: ="" | B7: ="(0.115)" -> (0.115) | C7: ="(0.127)" -> (0.127) | D7: ="(0.116)" -> (0.116) | E7: ="(0.0194)" -> (0.0194) | F7: ="(0.0200)" -> (0.0200) | G7: ="(0.0147)" -> (0.0147)
A9: ="Number of observations (industries)" -> Number of observations (industries) | B9: ="300" -> 300
A10: Adjusted R2 | B10: ="0.707" -> 0.707 | C10: ="0.614" -> 0.614 | D10: ="0.672" -> 0.672 | E10: ="0.929" -> 0.929 | F10: ="0.924" -> 0.924 | G10: ="0.954" -> 0.954
A11: SD of Dependent Variable | B11: ="0.271" -> 0.271 | C11: ="0.254" -> 0.254 | D11: ="0.240" -> 0.240 | E11: ="0.0788" -> 0.0788 | F11: ="0.0787" -> 0.0787 | G11: ="0.0824" -> 0.0824
A12: SD of regressor (psi_j) | B12: ="0.122" -> 0.122

Sheet disclosed1-9a
A1: ="Output 9a - Bivariate Regressions, Top59 100%" -> Output 9a - Bivariate Regressions, Top59 100%
A2: ="" | B2: ="(1)" -> (1) | C2: ="(2)" -> (2) | D2: ="(3)" -> (3) | E2: ="(4)" -> (4) | F2: ="(5)" -> (5) | G2: ="(6)" -> (6) | H2: ="(7)" -> (7) | I2: ="(8)" -> (8) | J2: ="(9)" -> (9) | K2: ="(10)" -> (10)
A3: ="" | B3: Mean/SD | C3: Dependent Variable: "b_pjc_pj" | F3: Dependent Variable: "b_ajc_pj" | I3: Dependent Variable: "b_ajc_aj"
A5: ="alpha_c" -> alpha_c | B5: ="9.456" -> 9.456 | C5: ="-.0782" -> -.0782 | D5: =".2601" -> .2601 | E5: =".199" -> .199 | F5: =".8869***" -> .8869*** | G5: =".7457***" -> .7457*** | H5: =".7971***" -> .7971*** | I5: =".649***" -> .649*** | J5: =".6358***" -> .6358*** | K5: =".662***" -> .662***
A6: ="" | B6: =".1319" -> .1319 | C6: ="(.1004)" -> (.1004) | D6: ="(.2211)" -> (.2211) | E6: ="(.2203)" -> (.2203) | F6: ="(.106)" -> (.106) | G6: ="(.1694)" -> (.1694) | H6: ="(.1414)" -> (.1414) | I6: ="(.04955)" -> (.04955) | J6: ="(.05925)" -> (.05925) | K6: ="(.07046)" -> (.07046)
C7: ="-.001383" -> -.001383 | D7: =".09885" -> .09885 | E7: =".1101" -> .1101 | F7: =".7564" -> .7564 | G7: =".7659" -> .7659 | H7: =".771" -> .771 | I7: =".7742" -> .7742 | J7: =".8202" -> .8202 | K7: =".8177" -> .8177
C8: =".08189" -> .08189 | D8: =".07768" -> .07768 | E8: =".0772" -> .0772 | F8: =".06619" -> .06619 | G8: =".06489" -> .06489 | H8: =".06418" -> .06418 | I8: =".04611" -> .04611 | J8: =".04114" -> .04114 | K8: =".04142" -> .04142
A9: ="alt_cz_eff" -> alt_cz_eff | B9: ="-7.94e-11" -> -7.94e-11 | C9: =".9378***" -> .9378*** | D9: ="1.66***" -> 1.66*** | E9: ="2.039***" -> 2.039*** | F9: ="1.664***" -> 1.664*** | G9: =".9506***" -> .9506*** | H9: ="1.272***" -> 1.272*** | I9: ="1.126***" -> 1.126*** | J9: =".7613***" -> .7613*** | K9: =".8838**" -> .8838**
A10: ="" | B10: =".04096" -> .04096 | C10: ="(.2566)" -> (.2566) | D10: ="(.1729)" -> (.1729) | E10: ="(.2573)" -> (.2573) | F10: ="(.3782)" -> (.3782) | G10: ="(.2937)" -> (.2937) | H10: ="(.4239)" -> (.4239) | I10: ="(.2802)" -> (.2802) | J10: ="(.2439)" -> (.2439) | K10: ="(.4125)" -> (.4125)
C11: =".2067" -> .2067 | D11: =".5996" -> .5996 | E11: =".6674" -> .6674 | F11: =".2451" -> .2451 | G11: =".5735" -> .5735 | H11: =".577" -> .577 | I11: =".2124" -> .2124 | J11: =".5412" -> .5412 | K11: =".5276" -> .5276
C12: =".07289" -> .07289 | D12: =".05178" -> .05178 | E12: =".0472" -> .0472 | F12: =".1165" -> .1165 | G12: =".08759" -> .08759 | H12: =".08722" -> .08722 | I12: =".08611" -> .08611 | J12: =".06572" -> .06572 | K12: =".06668" -> .06668
A13: ="s_alpha_q1q5" -> s_alpha_q1q5 | B13: =".3994" -> .3994 | C13: =".1587" -> .1587 | D13: =".7098" -> .7098 | E13: =".5773" -> .5773 | F13: ="2.774***" -> 2.774*** | G13: ="1.897***" -> 1.897*** | H13: ="1.988***" -> 1.988*** | I13: ="2.376***" -> 2.376*** | J13: ="1.874***" -> 1.874*** | K13: ="1.967***" -> 1.967***
A14: ="" | B14: =".03059" -> .03059 | C14: ="(.4786)" -> (.4786) | D14: ="(.6329)" -> (.6329) | E14: ="(.6396)" -> (.6396) | F14: ="(.3319)" -> (.3319) | G14: ="(.397)" -> (.397) | H14: ="(.3943)" -> (.3943) | I14: ="(.1995)" -> (.1995) | J14: ="(.1852)" -> (.1852) | K14: ="(.2481)" -> (.2481)
C15: ="-.01396" -> -.01396 | D15: =".06943" -> .06943 | E15: =".09661" -> .09661 | F15: =".3898" -> .3898 | G15: =".6532" -> .6532 | H15: =".638" -> .638 | I15: =".5536" -> .5536 | J15: =".7354" -> .7354 | K15: =".7245" -> .7245
C16: =".0824" -> .0824 | D16: =".07894" -> .07894 | E16: =".07778" -> .07778 | F16: =".1048" -> .1048 | G16: =".07898" -> .07898 | H16: =".08069" -> .08069 | I16: =".06482" -> .06482 | J16: =".04991" -> .04991 | K16: =".05092" -> .05092
A17: ="psi_c" -> psi_c | B17: =".2356" -> .2356 | C17: ="1.004***" -> 1.004*** | D17: ="1.647***" -> 1.647*** | E17: ="1.861***" -> 1.861*** | F17: ="1.742***" -> 1.742*** | G17: ="1.113***" -> 1.113*** | H17: ="1.401***" -> 1.401*** | I17: ="1.141***" -> 1.141*** | J17: =".7909***" -> .7909*** | K17: =".8843**" -> .8843**
A18: ="" | B18: =".04349" -> .04349 | C18: ="(.2477)" -> (.2477) | D18: ="(.1554)" -> (.1554) | E18: ="(.2175)" -> (.2175) | F18: ="(.3313)" -> (.3313) | G18: ="(.2672)" -> (.2672) | H18: ="(.3538)" -> (.3538) | I18: ="(.2354)" -> (.2354) | J18: ="(.2199)" -> (.2199) | K18: ="(.355)" -> (.355)
C19: =".2721" -> .2721 | D19: =".6969" -> .6969 | E19: =".7407" -> .7407 | F19: =".3072" -> .3072 | G19: =".6181" -> .6181 | H19: =".6326" -> .6326 | I19: =".2485" -> .2485 | J19: =".5656" -> .5656 | K19: =".5558" -> .5558
C20: =".06982" -> .06982 | D20: =".04506" -> .04506 | E20: =".04167" -> .04167 | F20: =".1116" -> .1116 | G20: =".08287" -> .08287 | H20: =".08129" -> .08129 | I20: =".08411" -> .08411 | J20: =".06395" -> .06395 | K20: =".06467" -> .06467
A21: ="Ealpha_c" -> Ealpha_c | B21: ="9.456" -> 9.456 | C21: ="-.26" -> -.26 | D21: ="1.304**" -> 1.304** | E21: ="1.354***" -> 1.354*** | F21: ="3.864***" -> 3.864*** | G21: ="3.348***" -> 3.348*** | H21: ="3.393***" -> 3.393*** | I21: ="2.675***" -> 2.675*** | J21: ="2.342***" -> 2.342*** | K21: ="2.36***" -> 2.36***
A22: ="" | B22: =".03052" -> .03052 | C22: ="(.3726)" -> (.3726) | D22: ="(.5451)" -> (.5451) | E22: ="(.4808)" -> (.4808) | F22: ="(.3076)" -> (.3076) | G22: ="(.4844)" -> (.4844) | H22: ="(.4288)" -> (.4288) | I22: ="(.2472)" -> (.2472) | J22: ="(.4473)" -> (.4473) | K22: ="(.385)" -> (.385)
C23: ="-.007974" -> -.007974 | D23: =".1265" -> .1265 | E23: =".1886" -> .1886 | F23: =".7695" -> .7695 | G23: =".7815" -> .7815 | H23: =".7832" -> .7832 | I23: =".7031" -> .7031 | J23: =".7149" -> .7149 | K23: =".7184" -> .7184
C24: =".08216" -> .08216 | D24: =".07648" -> .07648 | E24: =".07371" -> .07371 | F24: =".06439" -> .06439 | G24: =".06269" -> .06269 | H24: =".06244" -> .06244 | I24: =".05287" -> .05287 | J24: =".05181" -> .05181 | K24: =".05149" -> .05149
A25: ="Es_alpha_q1q5" -> Es_alpha_q1q5 | B25: =".3872" -> .3872 | C25: ="-1.443" -> -1.443 | D25: ="2.585" -> 2.585 | E25: ="1.957" -> 1.957 | F25: ="11.08***" -> 11.08*** | G25: ="8.587***" -> 8.587*** | H25: ="8.593***" -> 8.593*** | I25: ="8.329***" -> 8.329*** | J25: ="7.138***" -> 7.138*** | K25: ="7.019***" -> 7.019***
A26: ="" | B26: =".009524" -> .009524 | C26: ="(1.28)" -> (1.28) | D26: ="(1.846)" -> (1.846) | E26: ="(2.127)" -> (2.127) | F26: ="(1.168)" -> (1.168) | G26: ="(2.806)" -> (2.806) | H26: ="(2.749)" -> (2.749) | I26: ="(.8395)" -> (.8395) | J26: ="(1.603)" -> (1.603) | K26: ="(1.658)" -> (1.658)
C27: =".01114" -> .01114 | D27: =".05402" -> .05402 | E27: =".08608" -> .08608 | F27: =".6123" -> .6123 | G27: =".6722" -> .6722 | H27: =".6553" -> .6553 | I27: =".6626" -> .6626 | J27: =".6783" -> .6783 | K27: =".6582" -> .6582
C28: =".08138" -> .08138 | D28: =".07959" -> .07959 | E28: =".07823" -> .07823 | F28: =".0835" -> .0835 | G28: =".07678" -> .07678 | H28: =".07873" -> .07873 | I28: =".05636" -> .05636 | J28: =".05503" -> .05503 | K28: =".05672" -> .05672
A29: ="Epsi_c" -> Epsi_c | B29: =".2356" -> .2356 | C29: ="2.64***" -> 2.64*** | D29: ="3.707***" -> 3.707*** | E29: ="3.975***" -> 3.975*** | F29: ="4.091**" -> 4.091** | G29: ="4.691***" -> 4.691*** | H29: ="5.241***" -> 5.241*** | I29: ="2.18*" -> 2.18* | J29: ="2.238**" -> 2.238** | K29: ="2.615***" -> 2.615***
A30: ="" | B30: =".0111" -> .0111 | C30: ="(.9478)" -> (.9478) | D30: ="(1.093)" -> (1.093) | E30: ="(1.015)" -> (1.015) | F30: ="(1.788)" -> (1.788) | G30: ="(1.153)" -> (1.153) | H30: ="(1.057)" -> (1.057) | I30: ="(1.299)" -> (1.299) | J30: ="(1.021)" -> (1.021) | K30: ="(.8646)" -> (.8646)
C31: =".1131" -> .1131 | D31: =".2419" -> .2419 | E31: =".3325" -> .3325 | F31: =".09919" -> .09919 | G31: =".6385" -> .6385 | H31: =".664" -> .664 | I31: =".04578" -> .04578 | J31: =".5128" -> .5128 | K31: =".5299" -> .5299
C32: =".07707" -> .07707 | D32: =".07125" -> .07125 | E32: =".06686" -> .06686 | F32: =".1273" -> .1273 | G32: =".08063" -> .08063 | H32: =".07774" -> .07774 | I32: =".09478" -> .09478 | J32: =".06772" -> .06772 | K32: =".06653" -> .06653
A33: ="s_psi_q1q5" -> s_psi_q1q5 | B33: =".3006" -> .3006 | C33: =".4677***" -> .4677*** | D33: =".7459***" -> .7459*** | E33: =".8656***" -> .8656*** | F33: =".9237***" -> .9237*** | G33: =".599***" -> .599*** | H33: =".7861***" -> .7861*** | I33: =".6593***" -> .6593*** | J33: =".4784***" -> .4784*** | K33: =".5768***" -> .5768***
A34: ="" | B34: =".09014" -> .09014 | C34: ="(.1353)" -> (.1353) | D34: ="(.08926)" -> (.08926) | E34: ="(.1145)" -> (.1145) | F34: ="(.1456)" -> (.1456) | G34: ="(.1234)" -> (.1234) | H34: ="(.1539)" -> (.1539) | I34: ="(.114)" -> (.114) | J34: ="(.1069)" -> (.1069) | K34: ="(.1095)" -> (.1095)
C35: =".2525" -> .2525 | D35: =".6489" -> .6489 | E35: =".6955" -> .6955 | F35: =".3746" -> .3746 | G35: =".6546" -> .6546 | H35: =".6838" -> .6838 | I35: =".3642" -> .3642 | J35: =".6395" -> .6395 | K35: =".6467" -> .6467
C36: =".07075" -> .07075 | D36: =".04849" -> .04849 | E36: =".04515" -> .04515 | F36: =".1061" -> .1061 | G36: =".07882" -> .07882 | H36: =".07542" -> .07542 | I36: =".07737" -> .07737 | J36: =".05826" -> .05826 | K36: =".05767" -> .05767
A37: ="membership" -> membership | B37: =".1178" -> .1178 | C37: =".3291" -> .3291 | D37: =".6368" -> .6368 | E37: =".5403" -> .5403 | F37: =".2339" -> .2339 | G37: =".1561" -> .1561 | H37: =".256" -> .256 | I37: =".1826" -> .1826 | J37: =".4047" -> .4047 | K37: =".7034*" -> .7034*
A38: ="" | B38: =".05989" -> .05989 | C38: ="(.2479)" -> (.2479) | D38: ="(.4074)" -> (.4074) | E38: ="(.5216)" -> (.5216) | F38: ="(.4062)" -> (.4062) | G38: ="(.3036)" -> (.3036) | H38: ="(.4258)" -> (.4258) | I38: ="(.326)" -> (.326) | J38: ="(.2667)" -> (.2667) | K38: ="(.3592)" -> (.3592)
C39: =".04148" -> .04148 | D39: =".1519" -> .1519 | E39: =".09966" -> .09966 | F39: ="-.00644" -> -.00644 | G39: =".5049" -> .5049 | H39: =".4926" -> .4926 | I39: ="-.004619" -> -.004619 | J39: =".4934" -> .4934 | K39: =".4911" -> .4911
C40: =".08012" -> .08012 | D40: =".07536" -> .07536 | E40: =".07765" -> .07765 | F40: =".1345" -> .1345 | G40: =".09436" -> .09436 | H40: =".09553" -> .09553 | I40: =".09725" -> .09725 | J40: =".06906" -> .06906 | K40: =".06921" -> .06921
A41: ="coverage" -> coverage | B41: =".1303" -> .1303 | C41: =".3196" -> .3196 | D41: =".605" -> .605 | E41: =".4496" -> .4496 | F41: =".1881" -> .1881 | G41: =".1244" -> .1244 | H41: =".1463" -> .1463 | I41: =".1492" -> .1492 | J41: =".3832" -> .3832 | K41: =".6131*" -> .6131*
A42: ="" | B42: =".06013" -> .06013 | C42: ="(.2477)" -> (.2477) | D42: ="(.4098)" -> (.4098) | E42: ="(.5278)" -> (.5278) | F42: ="(.4043)" -> (.4043) | G42: ="(.3001)" -> (.3001) | H42: ="(.4202)" -> (.4202) | I42: ="(.3256)" -> (.3256) | J42: ="(.2665)" -> (.2665) | K42: ="(.3628)" -> (.3628)
C43: =".03857" -> .03857 | D43: =".1397" -> .1397 | E43: =".08972" -> .08972 | F43: ="-.01031" -> -.01031 | G43: =".5038" -> .5038 | H43: =".4906" -> .4906 | I43: ="-.008845" -> -.008845 | J43: =".4896" -> .4896 | K43: =".4823" -> .4823
C44: =".08024" -> .08024 | D44: =".0759" -> .0759 | E44: =".07808" -> .07808 | F44: =".1348" -> .1348 | G44: =".09447" -> .09447 | H44: =".09572" -> .09572 | I44: =".09746" -> .09746 | J44: =".06932" -> .06932 | K44: =".06982" -> .06982
A45: ="lnN_c" -> lnN_c | B45: ="17.91" -> 17.91 | C45: =".04598***" -> .04598*** | D45: =".04006" -> .04006 | E45: =".02925" -> .02925 | F45: ="-.04748**" -> -.04748** | G45: =".08106***" -> .08106*** | H45: =".08542***" -> .08542*** | I45: ="-.01557" -> -.01557 | J45: =".08469***" -> .08469*** | K45: =".08752***" -> .08752***
A46: ="" | B46: =".8355" -> .8355 | C46: ="(.009572)" -> (.009572) | D46: ="(.02611)" -> (.02611) | E46: ="(.02691)" -> (.02691) | F46: ="(.0219)" -> (.0219) | G46: ="(.02641)" -> (.02641) | H46: ="(.03135)" -> (.03135) | I46: ="(.01728)" -> (.01728) | J46: ="(.01662)" -> (.01662) | K46: ="(.01958)" -> (.01958)
C47: =".2067" -> .2067 | D47: =".1018" -> .1018 | E47: =".1073" -> .1073 | F47: =".07147" -> .07147 | G47: =".6379" -> .6379 | H47: =".6304" -> .6304 | I47: =".00075" -> .00075 | J47: =".737" -> .737 | K47: =".7293" -> .7293
C48: =".07289" -> .07289 | D48: =".07756" -> .07756 | E48: =".07732" -> .07732 | F48: =".1292" -> .1292 | G48: =".08071" -> .08071 | H48: =".08154" -> .08154 | I48: =".09699" -> .09699 | J48: =".04976" -> .04976 | K48: =".05048" -> .05048
A49: ="lnmw" -> lnmw | B49: ="2.089" -> 2.089 | C49: =".07224" -> .07224 | D49: =".2625**" -> .2625** | E49: =".2417*" -> .2417* | F49: =".6453***" -> .6453*** | G49: =".3435**" -> .3435** | H49: =".4666***" -> .4666*** | I49: =".4692***" -> .4692*** | J49: =".3199***" -> .3199*** | K49: =".4191***" -> .4191***
A50: ="" | B50: =".1112" -> .1112 | C50: ="(.08676)" -> (.08676) | D50: ="(.1052)" -> (.1052) | E50: ="(.1438)" -> (.1438) | F50: ="(.1369)" -> (.1369) | G50: ="(.1392)" -> (.1392) | H50: ="(.1342)" -> (.1342) | I50: ="(.103)" -> (.103) | J50: ="(.09433)" -> (.09433) | K50: ="(.09526)" -> (.09526)
C51: ="-.007744" -> -.007744 | D51: =".1274" -> .1274 | E51: =".1249" -> .1249 | F51: =".2736" -> .2736 | G51: =".5751" -> .5751 | H51: =".5755" -> .5755 | I51: =".2766" -> .2766 | J51: =".5747" -> .5747 | K51: =".5794" -> .5794
C52: =".08215" -> .08215 | D52: =".07644" -> .07644 | E52: =".07655" -> .07655 | F52: =".1143" -> .1143 | G52: =".08743" -> .08743 | H52: =".08738" -> .08738 | I52: =".08253" -> .08253 | J52: =".06328" -> .06328 | K52: =".06292" -> .06292
A53: ="Es_psi_q1q5" -> Es_psi_q1q5 | B53: =".3006" -> .3006 | C53: =".9206*" -> .9206* | D53: ="2***" -> 2*** | E53: ="2.077***" -> 2.077*** | F53: ="4.053***" -> 4.053*** | G53: ="3.159***" -> 3.159*** | H53: ="3.297***" -> 3.297*** | I53: ="2.506***" -> 2.506*** | J53: ="1.751***" -> 1.751*** | K53: ="1.851***" -> 1.851***
A54: ="" | B54: =".02114" -> .02114 | C54: ="(.5173)" -> (.5173) | D54: ="(.5438)" -> (.5438) | E54: ="(.5314)" -> (.5314) | F54: ="(.6201)" -> (.6201) | G54: ="(.5286)" -> (.5286) | H54: ="(.5127)" -> (.5127) | I54: ="(.4273)" -> (.4273) | J54: ="(.4713)" -> (.4713) | K54: ="(.4174)" -> (.4174)
C55: =".04" -> .04 | D55: =".245" -> .245 | E55: =".3229" -> .3229 | F55: =".3977" -> .3977 | G55: =".7176" -> .7176 | H55: =".7335" -> .7335 | I55: =".2858" -> .2858 | J55: =".58" -> .58 | K55: =".5938" -> .5938
C56: =".08018" -> .08018 | D56: =".07111" -> .07111 | E56: =".06734" -> .06734 | F56: =".1041" -> .1041 | G56: =".07127" -> .07127 | H56: =".06923" -> .06923 | I56: =".082" -> .082 | J56: =".06288" -> .06288 | K56: =".06184" -> .06184
A57: ="b_pjc_pj" -> b_pjc_pj | B57: ="0.880" -> 0.880 | F57: ="-.001298" -> -.001298 | G57: =".5687***" -> .5687*** | H57: =".6166***" -> .6166*** | I57: ="-.01838" -> -.01838 | J57: =".3574**" -> .3574** | K57: =".355*" -> .355*
B58: ="0.0818" -> 0.0818 | F58: ="(.2338)" -> (.2338) | G58: ="(.1679)" -> (.1679) | H58: ="(.2044)" -> (.2044) | I58: ="(.1922)" -> (.1922) | J58: ="(.1575)" -> (.1575) | K58: ="(.2067)" -> (.2067)
F59: ="-.01754" -> -.01754 | G59: =".6207" -> .6207 | H59: =".6222" -> .6222 | I59: ="-.0173" -> -.0173 | J59: =".5431" -> .5431 | K59: =".5309" -> .5309
F60: =".1353" -> .1353 | G60: =".0826" -> .0826 | H60: =".08243" -> .08243 | I60: =".09786" -> .09786 | J60: =".06559" -> .06559 | K60: =".06645" -> .06645
A61: ="b_ajc_pj" -> b_ajc_pj | B61: =".7988" -> .7988 | C61: ="-.0004831" -> -.0004831 | D61: =".4197***" -> .4197*** | E61: =".4214***" -> .4214*** | I61: =".6661***" -> .6661*** | J61: =".6546***" -> .6546*** | K61: =".6491***" -> .6491***
A62: ="" | B62: =".1341" -> .1341 | C62: ="(.08708)" -> (.08708) | D62: ="(.08975)" -> (.08975) | E62: ="(.09287)" -> (.09287) | I62: ="(.04868)" -> (.04868) | J62: ="(.06384)" -> (.06384) | K62: ="(.06223)" -> (.06223)
C63: ="-.01754" -> -.01754 | D63: =".2482" -> .2482 | E63: =".3065" -> .3065 | I63: =".845" -> .845 | J63: =".8612" -> .8612 | K63: =".8578" -> .8578
C64: =".08255" -> .08255 | D64: =".07095" -> .07095 | E64: =".06815" -> .06815 | I64: =".0382" -> .0382 | J64: =".03615" -> .03615 | K64: =".03659" -> .03659
A65: ="b_ajc_aj" -> b_ajc_aj | B65: ="0.863" -> 0.863 | C65: ="-.01307" -> -.01307 | D65: =".4592**" -> .4592** | E65: =".4279*" -> .4279* | F65: ="1.273***" -> 1.273*** | G65: ="1.14***" -> 1.14*** | H65: ="1.144***" -> 1.144***
B66: ="0.0970" -> 0.0970 | C66: ="(.1363)" -> (.1363) | D66: ="(.2108)" -> (.2108) | E66: ="(.2222)" -> (.2222) | F66: ="(.09862)" -> (.09862) | G66: ="(.1432)" -> (.1432) | H66: ="(.1355)" -> (.1355)
C67: ="-.0173" -> -.0173 | D67: =".1746" -> .1746 | E67: =".2053" -> .2053 | F67: =".845" -> .845 | G67: =".8735" -> .8735 | H67: =".8687" -> .8687
C68: =".08254" -> .08254 | D68: =".07435" -> .07435 | E68: =".07295" -> .07295 | F68: =".0528" -> .0528 | G68: =".0477" -> .0477 | H68: =".04859" -> .04859
A70: ="Division-CZ dummies" -> Division-CZ dummies | C70: ="No" -> No | D70: ="Yes" -> Yes | E70: ="Yes" -> Yes | F70: ="No" -> No | G70: ="Yes" -> Yes | H70: ="Yes" -> Yes | I70: ="No" -> No | J70: ="Yes" -> Yes | K70: ="Yes" -> Yes
A71: ="Region dummies" -> Region dummies | C71: ="No" -> No | D71: ="No" -> No | E71: ="Yes" -> Yes | F71: ="No" -> No | G71: ="No" -> No | H71: ="Yes" -> Yes | I71: ="No" -> No | J71: ="No" -> No | K71: ="Yes" -> Yes
A72: ="N" -> N | B72: 60 | C72: ="60" -> 60 | F72: ="60" -> 60 | I72: ="60" -> 60

Sheet disclosed1-9b
A1: ="Output 9b - Multivariate Regressions, Top59 100%" -> Output 9b - Multivariate Regressions, Top59 100%
B2: ="(1)" -> (1) | C2: ="(2)" -> (2) | D2: ="(3)" -> (3) | E2: ="(4)" -> (4) | F2: ="(5)" -> (5) | G2: ="(6)" -> (6) | H2: ="(7)" -> (7) | I2: ="(8)" -> (8) | J2: ="(9)" -> (9) | K2: ="(10)" -> (10) | L2: ="(11)" -> (11) | M2: ="(12)" -> (12) | N2: ="(13)" -> (13) | O2: ="(14)" -> (14) | P2: ="(15)" -> (15) | Q2: ="(16)" -> (16) | R2: ="(17)" -> (17) | S2: ="(18)" -> (18) | T2: ="(19)" -> (19) | U2: ="(20)" -> (20) | V2: ="(21)" -> (21) | W2: ="(22)" -> (22) | X2: ="(23)" -> (23) | Y2: ="(24)" -> (24) | Z2: ="(25)" -> (25) | AA2: ="(26)" -> (26) | AB2: ="(27)" -> (27) | AC2: ="(28)" -> (28) | AD2: ="(29)" -> (29) | AE2: ="(30)" -> (30) | AF2: ="(31)" -> (31) | AG2: ="(32)" -> (32) | AH2: ="(33)" -> (33) | AI2: ="(34)" -> (34) | AJ2: ="(35)" -> (35) | AK2: ="(36)" -> (36) | AL2: ="(37)" -> (37) | AM2: ="(38)" -> (38) | AN2: ="(39)" -> (39)
A3: ="" | B3: Dependent Variable: "b_pjc_pj"
A5: ="alpha_c" -> alpha_c | B5: ="-.1234" -> -.1234 | C5: =".05898" -> .05898 | D5: ="-.2305" -> -.2305 | E5: ="" | F5: ="" | G5: ="" | H5: ="" | I5: ="" | J5: ="" | K5: ="" | L5: ="" | M5: ="" | N5: ="-.3841***" -> -.3841*** | O5: ="-.09456" -> -.09456 | P5: ="-.08004" -> -.08004 | Q5: ="-.19**" -> -.19** | R5: =".2242" -> .2242 | S5: =".158" -> .158 | T5: ="" | U5: ="" | V5: ="" | W5: ="-.4822***" -> -.4822*** | X5: ="-.03453" -> -.03453 | Y5: ="-.04833" -> -.04833 | Z5: ="" | AA5: ="" | AB5: ="" | AC5: ="" | AD5: ="" | AE5: ="" | AF5: ="" | AG5: ="" | ... AN5: =""
A6: ="" | B6: ="(.1936)" -> (.1936) | C6: ="(.3495)" -> (.3495) | D6: ="(.3905)" -> (.3905) | E6: ="" | F6: ="" | G6: ="" | H6: ="" | I6: ="" | J6: ="" | K6: ="" | L6: ="" | M6: ="" | N6: ="(.0659)" -> (.0659) | O6: ="(.1369)" -> (.1369) | P6: ="(.08615)" -> (.08615) | Q6: ="(.09468)" -> (.09468) | R6: ="(.2216)" -> (.2216) | S6: ="(.2194)" -> (.2194) | T6: ="" | U6: ="" | V6: ="" | W6: ="(.1016)" -> (.1016) | X6: ="(.1171)" -> (.1171) | Y6: ="(.08327)" -> (.08327) | Z6: ="" | AA6: ="" | AB6: ="" | AC6: ="" | AD6: ="" | AE6: ="" | AF6: ="" | AG6: ="" | ... AN6: =""
A7: ="Ealpha_c" -> Ealpha_c | B7: =".218" -> .218 | C7: ="1.099" -> 1.099 | D7: ="2.153*" -> 2.153* | E7: ="" | F7: ="" | G7: ="" | H7: ="" | I7: ="" | J7: ="" | K7: ="" | L7: ="" | ... Y7: ="" | Z7: ="-.8325**" -> -.8325** | AA7: =".1168" -> .1168 | AB7: ="-.2297" -> -.2297 | AC7: =".4706" -> .4706 | AD7: ="1.536*" -> 1.536* | AE7: ="2.005**" -> 2.005** | AF7: ="-1.504**" -> -1.504** | AG7: ="-.7078" -> -.7078 | AH7: ="-.7836" -> -.7836 | AI7: ="" | AJ7: ="" | AK7: ="" | AL7: ="-1.292" -> -1.292 | AM7: ="-.7773" -> -.7773 | AN7: ="-1.725" -> -1.725
A8: ="" | B8: ="(.6482)" -> (.6482) | C8: ="(1.038)" -> (1.038) | D8: ="(1.295)" -> (1.295) | E8: ="" | F8: ="" | G8: ="" | H8: ="" | I8: ="" | J8: ="" | K8: ="" | L8: ="" | ... Y8: ="" | Z8: ="(.3309)" -> (.3309) | AA8: ="(.6627)" -> (.6627) | AB8: ="(.9926)" -> (.9926) | AC8: ="(.6317)" -> (.6317) | AD8: ="(.9079)" -> (.9079) | AE8: ="(.9943)" -> (.9943) | AF8: ="(.7179)" -> (.7179) | AG8: ="(1.122)" -> (1.122) | AH8: ="(1.803)" -> (1.803) | AI8: ="" | AJ8: ="" | AK8: ="" | AL8: ="(.8587)" -> (.8587) | AM8: ="(1.52)" -> (1.52) | AN8: ="(1.826)" -> (1.826)
A9: ="s_alpha_q1q5" -> s_alpha_q1q5 | B9: ="" | C9: ="" | D9: ="" | E9: =".7757" -> .7757 | F9: =".5418" -> .5418 | G9: =".4509" -> .4509 | H9: ="" | I9: ="" | J9: ="" | K9: ="" | L9: ="" | M9: ="" | N9: ="" | O9: ="" | P9: ="" | Q9: =".7125*" -> .7125* | R9: =".1682" -> .1682 | S9: =".2059" -> .2059 | T9: ="" | U9: ="" | V9: ="" | W9: ="-.2371" -> -.2371 | X9: ="-.9945***" -> -.9945*** | Y9: ="-.9559***" -> -.9559*** | Z9: ="" | AA9: ="" | AB9: ="" | AC9: ="" | AD9: ="" | AE9: ="" | AF9: ="" | AG9: ="" | ... AN9: =""
A10: ="" | B10: ="" | C10: ="" | D10: ="" | E10: ="(.5934)" -> (.5934) | F10: ="(.8106)" -> (.8106) | G10: ="(.8431)" -> (.8431) | H10: ="" | I10: ="" | J10: ="" | K10: ="" | L10: ="" | M10: ="" | N10: ="" | O10: ="" | P10: ="" | Q10: ="(.4316)" -> (.4316) | R10: ="(.6091)" -> (.6091) | S10: ="(.5625)" -> (.5625) | T10: ="" | U10: ="" | V10: ="" | W10: ="(.4783)" -> (.4783) | X10: ="(.3754)" -> (.3754) | Y10: ="(.3667)" -> (.3667) | Z10: ="" | AA10: ="" | AB10: ="" | AC10: ="" | AD10: ="" | AE10: ="" | AF10: ="" | AG10: ="" | ... AN10: =""
A11: ="Es_alpha_q1q5" -> Es_alpha_q1q5 | B11: ="" | C11: ="" | D11: ="" | E11: ="-3.057***" -> -3.057*** | F11: ="1.173" -> 1.173 | G11: =".917" -> .917 | H11: ="" | I11: ="" | J11: ="" | K11: ="" | L11: ="" | M11: ="" | N11: ="" | O11: ="" | ... AB11: ="" | AC11: ="-2.734" -> -2.734 | AD11: ="-1.057" -> -1.057 | AE11: ="-2.992" -> -2.992 | AF11: ="2.055" -> 2.055 | AG11: ="1.913" -> 1.913 | AH11: =".02269" -> .02269 | AI11: ="" | AJ11: ="" | AK11: ="" | AL11: ="1.948" -> 1.948 | AM11: ="1.043" -> 1.043 | AN11: ="1.552" -> 1.552
A12: ="" | B12: ="" | C12: ="" | D12: ="" | E12: ="(1.141)" -> (1.141) | F12: ="(2.367)" -> (2.367) | G12: ="(2.808)" -> (2.808) | H12: ="" | I12: ="" | J12: ="" | K12: ="" | L12: ="" | M12: ="" | N12: ="" | O12: ="" | ... AB12: ="" | AC12: ="(2.206)" -> (2.206) | AD12: ="(2.749)" -> (2.749) | AE12: ="(3.238)" -> (3.238) | AF12: ="(1.729)" -> (1.729) | AG12: ="(2.332)" -> (2.332) | AH12: ="(2.834)" -> (2.834) | AI12: ="" | AJ12: ="" | AK12: ="" | AL12: ="(2.004)" -> (2.004) | AM12: ="(2.584)" -> (2.584) | AN12: ="(2.509)" -> (2.509)
A13: ="psi_c" -> psi_c | B13: ="" | C13: ="" | D13: ="" | E13: ="" | F13: ="" | G13: ="" | H13: =".8751***" -> .8751*** | I13: ="1.518***" -> 1.518*** | J13: ="1.783***" -> 1.783*** | K13: ="" | L13: ="" | M13: ="" | N13: ="1.656***" -> 1.656*** | O13: ="1.744***" -> 1.744*** | P13: ="1.932***" -> 1.932*** | Q13: ="" | R13: ="" | S13: ="" | T13: =".8691" -> .8691 | U13: ="1.409" -> 1.409 | V13: ="1.404*" -> 1.404* | W13: ="-.2294" -> -.2294 | X13: =".7585" -> .7585 | Y13: =".7812" -> .7812 | Z13: ="" | AA13: ="" | AB13: ="" | AC13: ="" | AD13: ="" | AE13: ="" | AF13: ="" | AG13: ="" | ... AN13: =""
A14: ="" | B14: ="" | C14: ="" | D14: ="" | E14: ="" | F14: ="" | G14: ="" | H14: ="(.2514)" -> (.2514) | I14: ="(.1606)" -> (.1606) | J14: ="(.2366)" -> (.2366) | K14: ="" | L14: ="" | M14: ="" | N14: ="(.1747)" -> (.1747) | O14: ="(.2077)" -> (.2077) | P14: ="(.2112)" -> (.2112) | Q14: ="" | R14: ="" | S14: ="" | T14: ="(1.203)" -> (1.203) | U14: ="(1.119)" -> (1.119) | V14: ="(.7881)" -> (.7881) | W14: ="(.5786)" -> (.5786) | X14: ="(.8186)" -> (.8186) | Y14: ="(.5794)" -> (.5794) | Z14: ="" | AA14: ="" | AB14: ="" | AC14: ="" | AD14: ="" | AE14: ="" | AF14: ="" | AG14: ="" | ... AN14: =""
A15: ="Epsi_c" -> Epsi_c | B15: ="" | C15: ="" | D15: ="" | E15: ="" | F15: ="" | G15: ="" | H15: ="1.443" -> 1.443 | I15: ="1.162" -> 1.162 | J15: =".4513" -> .4513 | K15: ="" | L15: ="" | M15: ="" | N15: ="" | O15: ="" | P15: ="" | Q15: ="" | R15: ="" | ... Y15: ="" | Z15: ="3.632***" -> 3.632*** | AA15: ="3.551**" -> 3.551** | AB15: ="4.314**" -> 4.314** | AC15: ="" | AD15: ="" | AE15: ="" | AF15: ="4.026" -> 4.026 | AG15: ="2.603" -> 2.603 | AH15: ="1.44" -> 1.44 | AI15: ="" | AJ15: ="" | AK15: ="" | AL15: ="9.111***" -> 9.111*** | AM15: ="5.694" -> 5.694 | AN15: ="6.734" -> 6.734
A16: ="" | B16: ="" | C16: ="" | D16: ="" | E16: ="" | F16: ="" | G16: ="" | H16: ="(.9505)" -> (.9505) | I16: ="(1.014)" -> (1.014) | J16: ="(1.006)" -> (1.006) | K16: ="" | L16: ="" | M16: ="" | N16: ="" | O16: ="" | P16: ="" | Q16: ="" | R16: ="" | ... Y16: ="" | Z16: ="(.8723)" -> (.8723) | AA16: ="(1.397)" -> (1.397) | AB16: ="(1.873)" -> (1.873) | AC16: ="" | AD16: ="" | AE16: ="" | AF16: ="(2.992)" -> (2.992) | AG16: ="(3.822)" -> (3.822) | AH16: ="(5.068)" -> (5.068) | AI16: ="" | AJ16: ="" | AK16: ="" | AL16: ="(3.146)" -> (3.146) | AM16: ="(4.656)" -> (4.656) | AN16: ="(5.039)" -> (5.039)
A17: ="s_psi_q1q5" -> s_psi_q1q5 | B17: ="" | C17: ="" | D17: ="" | E17: ="" | F17: ="" | G17: ="" | H17: ="" | I17: ="" | J17: ="" | K17: =".4639***" -> .4639*** | L17: =".6736***" -> .6736*** | M17: =".8061***" -> .8061*** | N17: ="" | O17: ="" | P17: ="" | Q17: ="" | R17: ="" | S17: ="" | T17: =".06823" -> .06823 | U17: =".1177" -> .1177 | V17: =".2365" -> .2365 | W17: ="1.084***" -> 1.084*** | X17: =".6221" -> .6221 | Y17: =".7311**" -> .7311** | Z17: ="" | AA17: ="" | AB17: ="" | AC17: ="" | AD17: ="" | AE17: ="" | AF17: ="" | AG17: ="" | ... AN17: =""
A18: ="" | B18: ="" | C18: ="" | D18: ="" | E18: ="" | F18: ="" | G18: ="" | H18: ="" | ... J18: ="" | K18: ="(.1507)" -> (.1507) | L18: ="(.1155)" -> (.1155) | M18: ="(.1235)" -> (.1235) | N18: ="" | O18: ="" | P18: ="" | Q18: ="" | R18: ="" | S18: ="" | T18: ="(.6052)" -> (.6052) | U18: ="(.5371)" -> (.5371) | V18: ="(.3614)" -> (.3614) | W18: ="(.3009)" -> (.3009) | X18: ="(.3889)" -> (.3889) | Y18: ="(.3566)" -> (.3566) | Z18: ="" | AA18: ="" | AB18: ="" | AC18: ="" | AD18: ="" | AE18: ="" | AF18: ="" | AG18: ="" | ... AN18: =""
A19: ="Es_psi_q1q5" -> Es_psi_q1q5 | B19: ="" | C19: ="" | D19: ="" | E19: ="" | F19: ="" | G19: ="" | H19: ="" | I19: ="" | J19: ="" | K19: =".03638" -> .03638 | L19: =".7969" -> .7969 | M19: =".4017" -> .4017 | N19: ="" | O19: ="" | P19: ="" | Q19: ="" | R19: ="" | S19: ="" | T19: ="" | U19: ="" | ... AE19: ="" | AF19: =".1239" -> .1239 | AG19: =".996" -> .996 | AH19: ="2.037" -> 2.037 | AI19: ="" | AJ19: ="" | AK19: ="" | AL19: ="-2.658" -> -2.658 | AM19: ="-.39" -> -.39 | AN19: ="-.165" -> -.165
A20: ="" | B20: ="" | C20: ="" | D20: ="" | E20: ="" | F20: ="" | G20: ="" | H20: ="" | ... J20: ="" | K20: ="(.5385)" -> (.5385) | L20: ="(.5686)" -> (.5686) | M20: ="(.4592)" -> (.4592) | N20: ="" | O20: ="" | P20: ="" | Q20: ="" | R20: ="" | S20: ="" | T20: ="" | U20: ="" | ... AE20: ="" | AF20: ="(1.93)" -> (1.93) | AG20: ="(2.353)" -> (2.353) | AH20: ="(3.112)" -> (3.112) | AI20: ="" | AJ20: ="" | AK20: ="" | AL20: ="(2.071)" -> (2.071) | AM20: ="(2.491)" -> (2.491) | AN20: ="(2.893)" -> (2.893)
A21: ="lnmw" -> lnmw | B21: ="" | C21: ="" | D21: ="" | E21: ="" | F21: ="" | G21: ="" | H21: ="" | I21: ="" | ... AH21: ="" | AI21: ="-.03009" -> -.03009 | AJ21: =".1561" -> .1561 | AK21: =".2191" -> .2191 | AL21: =".2209" -> .2209 | AM21: =".1272" -> .1272 | AN21: =".2197" -> .2197
A22: ="" | B22: ="" | C22: ="" | D22: ="" | E22: ="" | F22: ="" | G22: ="" | H22: ="" | ... AH22: ="" | AI22: ="(.09904)" -> (.09904) | AJ22: ="(.1508)" -> (.1508) | AK22: ="(.154)" -> (.154) | AL22: ="(.1533)" -> (.1533) | AM22: ="(.2086)" -> (.2086) | AN22: ="(.2465)" -> (.2465)
A23: ="coverage" -> coverage | B23: ="" | C23: ="" | D23: ="" | E23: ="" | F23: ="" | G23: ="" | H23: ="" | I23: ="" | ... AH23: ="" | AI23: =".3497" -> .3497 | AJ23: =".4112" -> .4112 | AK23: =".1205" -> .1205 | AL23: =".3196" -> .3196 | AM23: =".6121" -> .6121 | AN23: =".6059" -> .6059
A24: ="" | B24: ="" | C24: ="" | D24: ="" | E24: ="" | F24: ="" | G24: ="" | H24: ="" | ... AH24: ="" | AI24: ="(.27)" -> (.27) | AJ24: ="(.512)" -> (.512) | AK24: ="(.5851)" -> (.5851) | AL24: ="(.2849)" -> (.2849) | AM24: ="(.4304)" -> (.4304) | AN24: ="(.4863)" -> (.4863)
A26: ="Division-CZ dummies" -> Division-CZ dummies | B26: ="No" -> No | C26: ="Yes" -> Yes | D26: ="Yes" -> Yes | E26: ="No" -> No | F26: ="Yes" -> Yes | G26: ="Yes" -> Yes | H26: ="No" -> No | I26: ="Yes" -> Yes | J26: ="Yes" -> Yes | K26: ="No" -> No | L26: ="Yes" -> Yes | M26: ="Yes" -> Yes | N26: ="No" -> No | O26: ="Yes" -> Yes | P26: ="Yes" -> Yes | Q26: ="No" -> No | R26: ="Yes" -> Yes | S26: ="Yes" -> Yes | T26: ="No" -> No | U26: ="Yes" -> Yes | V26: ="Yes" -> Yes | W26: ="No" -> No | X26: ="Yes" -> Yes | Y26: ="Yes" -> Yes | Z26: ="No" -> No | AA26: ="Yes" -> Yes | AB26: ="Yes" -> Yes | AC26: ="No" -> No | AD26: ="Yes" -> Yes | AE26: ="Yes" -> Yes | AF26: ="No" -> No | AG26: ="Yes" -> Yes | AH26: ="Yes" -> Yes | AI26: ="No" -> No | AJ26: ="Yes" -> Yes | AK26: ="Yes" -> Yes | AL26: ="No" -> No | AM26: ="Yes" -> Yes | AN26: ="Yes" -> Yes
A27: ="Region dummies" -> Region dummies | B27: ="No" -> No | C27: ="No" -> No | D27: ="Yes" -> Yes | E27: ="No" -> No | F27: ="No" -> No | G27: ="Yes" -> Yes | H27: ="No" -> No | I27: ="No" -> No | J27: ="Yes" -> Yes | K27: ="No" -> No | L27: ="No" -> No | M27: ="Yes" -> Yes | N27: ="No" -> No | O27: ="No" -> No | P27: ="Yes" -> Yes | Q27: ="No" -> No | R27: ="No" -> No | S27: ="Yes" -> Yes | T27: ="No" -> No | U27: ="No" -> No | V27: ="Yes" -> Yes | W27: ="No" -> No | X27: ="No" -> No | Y27: ="Yes" -> Yes | Z27: ="No" -> No | AA27: ="No" -> No | AB27: ="Yes" -> Yes | AC27: ="No" -> No | AD27: ="No" -> No | AE27: ="Yes" -> Yes | AF27: ="No" -> No | AG27: ="No" -> No | AH27: ="Yes" -> Yes | AI27: ="No" -> No | AJ27: ="No" -> No | AK27: ="Yes" -> Yes | AL27: ="No" -> No | AM27: ="No" -> No | AN27: ="Yes" -> Yes
A28: ="N" -> N | B28: ="60" -> 60
A29: ="r2_a" -> r2_a | B29: ="-.01792" -> -.01792 | C29: =".1096" -> .1096 | D29: =".1902" -> .1902 | E29: =".04398" -> .04398 | F29: =".0551" -> .0551 | G29: =".07961" -> .07961 | H29: =".2939" -> .2939 | I29: =".7092" -> .7092 | J29: =".7372" -> .7372 | K29: =".2392" -> .2392 | L29: =".673" -> .673 | M29: =".6955" -> .6955 | N29: =".5314" -> .5314 | O29: =".6996" -> .6996 | P29: =".7416" -> .7416 | Q29: =".02061" -> .02061 | R29: =".08126" -> .08126 | S29: =".09221" -> .09221 | T29: =".2596" -> .2596 | U29: =".692" -> .692 | V29: =".7413" -> .7413 | W29: =".616" -> .616 | X29: =".7518" -> .7518 | Y29: =".8013" -> .8013 | Z29: =".1783" -> .1783 | AA29: =".2263" -> .2263 | AB29: =".3191" -> .3191 | AC29: =".00199" -> .00199 | AD29: =".1114" -> .1114 | AE29: =".1958" -> .1958 | AF29: =".1596" -> .1596 | AG29: =".2087" -> .2087 | AH29: =".2962" -> .2962 | AI29: =".02262" -> .02262 | AJ29: =".1496" -> .1496 | AK29: =".1064" -> .1064 | AL29: =".3005" -> .3005 | AM29: =".389" -> .389 | AN29: =".3807" -> .3807
A30: ="rmse" -> rmse | B30: =".08256" -> .08256 | C30: =".07722" -> .07722 | D30: =".07364" -> .07364 | E30: =".08001" -> .08001 | F30: =".07955" -> .07955 | G30: =".07851" -> .07851 | H30: =".06876" -> .06876 | I30: =".04413" -> .04413 | J30: =".04195" -> .04195 | K30: =".07138" -> .07138 | L30: =".04679" -> .04679 | M30: =".04516" -> .04516 | N30: =".05602" -> .05602 | O30: =".04485" -> .04485 | P30: =".0416" -> .0416 | Q30: =".08099" -> .08099 | R30: =".07844" -> .07844 | S30: =".07797" -> .07797 | T30: =".07041" -> .07041 | U30: =".04541" -> .04541 | V30: =".04162" -> .04162 | W30: =".05071" -> .05071 | X30: =".04077" -> .04077 | Y30: =".03648" -> .03648 | Z30: =".07418" -> .07418 | AA30: =".07198" -> .07198 | AB30: =".06753" -> .06753 | AC30: =".08175" -> .08175 | AD30: =".07714" -> .07714 | AE30: =".07339" -> .07339 | AF30: =".07502" -> .07502 | AG30: =".0728" -> .0728 | AH30: =".06865" -> .06865 | AI30: =".0809" -> .0809 | AJ30: =".07546" -> .07546 | AK30: =".07736" -> .07736 | AL30: =".06844" -> .06844 | AM30: =".06397" -> .06397 | AN30: =".0644" -> .0644
A34: ="Output 9b - Multivariate Regressions, Top59 100%" -> Output 9b - Multivariate Regressions, Top59 100%
A36: ="" | B36: Dependent Variable: "b_ajc_pj"
A38: ="alpha_c" -> alpha_c | B38: =".4336**" -> .4336** | C38: =".3668*" -> .3668* | D38: =".389*" -> .389* | E38: ="" | F38: ="" | G38: ="" | H38: ="" | I38: ="" | J38: ="" | K38: ="" | L38: ="" | M38: ="" | N38: =".8235***" -> .8235*** | O38: =".6567***" -> .6567*** | P38: =".6811***" -> .6811*** | Q38: =".8325***" -> .8325*** | R38: =".7034***" -> .7034*** | S38: =".7543***" -> .7543*** | T38: ="" | U38: ="" | V38: ="" | W38: =".8233***" -> .8233*** | X38: =".6916***" -> .6916*** | Y38: =".7088***" -> .7088*** | Z38: ="" | AA38: ="" | AB38: ="" | AC38: ="" | AD38: ="" | AE38: ="" | AF38: ="" | AG38: ="" | ... AN38: =""
A39: ="" | B39: ="(.1782)" -> (.1782) | C39: ="(.2229)" -> (.2229) | D39: ="(.2155)" -> (.2155) | E39: ="" | F39: ="" | G39: ="" | H39: ="" | I39: ="" | J39: ="" | K39: ="" | L39: ="" | M39: ="" | N39: ="(.1309)" -> (.1309) | O39: ="(.1821)" -> (.1821) | P39: ="(.1082)" -> (.1082) | Q39: ="(.09353)" -> (.09353) | R39: ="(.1778)" -> (.1778) | S39: ="(.1759)" -> (.1759) | T39: ="" | U39: ="" | V39: ="" | W39: ="(.09969)" -> (.09969) | X39: ="(.1733)" -> (.1733) | Y39: ="(.1612)" -> (.1612) | Z39: ="" | AA39: ="" | AB39: ="" | AC39: ="" | AD39: ="" | AE39: ="" | AF39: ="" | AG39: ="" | ... AN39: =""
A40: ="Ealpha_c" -> Ealpha_c | B40: ="2.185***" -> 2.185*** | C40: ="2.07***" -> 2.07*** | D40: ="2.046***" -> 2.046*** | E40: ="" | F40: ="" | G40: ="" | H40: ="" | I40: ="" | J40: ="" | K40: ="" | L40: ="" | ... Y40: ="" | Z40: ="3.964***" -> 3.964*** | AA40: ="3.23***" -> 3.23*** | AB40: ="3.203***" -> 3.203*** | AC40: ="3.39***" -> 3.39*** | AD40: ="3.05***" -> 3.05*** | AE40: ="3.292***" -> 3.292*** | AF40: ="2.456***" -> 2.456*** | AG40: ="2.085***" -> 2.085*** | AH40: ="1.993**" -> 1.993** | AI40: ="" | AJ40: ="" | AK40: ="" | AL40: ="2.401***" -> 2.401*** | AM40: ="2.07**" -> 2.07** | AN40: ="1.862*" -> 1.862*
A41: ="" | B41: ="(.6607)" -> (.6607) | C41: ="(.7799)" -> (.7799) | D41: ="(.7581)" -> (.7581) | E41: ="" | F41: ="" | G41: ="" | H41: ="" | I41: ="" | J41: ="" | K41: ="" | L41: ="" | ... Y41: ="" | Z41: ="(.3172)" -> (.3172) | AA41: ="(.6649)" -> (.6649) | AB41: ="(.9278)" -> (.9278) | AC41: ="(.9854)" -> (.9854) | AD41: ="(1.175)" -> (1.175) | AE41: ="(1.143)" -> (1.143) | AF41: ="(.6794)" -> (.6794) | AG41: ="(.7957)" -> (.7957) | AH41: ="(1.016)" -> (1.016) | AI41: ="" | AJ41: ="" | AK41: ="" | AL41: ="(.6649)" -> (.6649) | AM41: ="(.8356)" -> (.8356) | AN41: ="(1.082)" -> (1.082)
A42: ="s_alpha_q1q5" -> s_alpha_q1q5 | B42: ="" | C42: ="" | D42: ="" | E42: =".9279" -> .9279 | F42: ="1.065" -> 1.065 | G42: ="1.178" -> 1.178 | H42: ="" | I42: ="" | J42: ="" | K42: ="" | L42: ="" | M42: ="" | N42: ="" | O42: ="" | P42: ="" | Q42: =".3469" -> .3469 | R42: =".1976" -> .1976 | S42: =".2146" -> .2146 | T42: ="" | U42: ="" | V42: ="" | W42: =".3509" -> .3509 | X42: =".01169" -> .01169 | Y42: ="-.1841" -> -.1841 | Z42: ="" | AA42: ="" | AB42: ="" | AC42: ="" | AD42: ="" | AE42: ="" | AF42: ="" | AG42: ="" | ... AN42: =""
A43: ="" | B43: ="" | C43: ="" | D43: ="" | E43: ="(.5729)" -> (.5729) | F43: ="(.7059)" -> (.7059) | G43: ="(.7429)" -> (.7429) | H43: ="" | I43: ="" | J43: ="" | K43: ="" | L43: ="" | M43: ="" | N43: ="" | O43: ="" | P43: ="" | Q43: ="(.4358)" -> (.4358) | R43: ="(.4874)" -> (.4874) | S43: ="(.5135)" -> (.5135) | T43: ="" | U43: ="" | V43: ="" | W43: ="(.4377)" -> (.4377) | X43: ="(.542)" -> (.542) | Y43: ="(.5453)" -> (.5453) | Z43: ="" | AA43: ="" | AB43: ="" | AC43: ="" | AD43: ="" | AE43: ="" | AF43: ="" | AG43: ="" | ... AN43: =""
A44: ="Es_alpha_q1q5" -> Es_alpha_q1q5 | B44: ="" | C44: ="" | D44: ="" | E44: ="9.147***" -> 9.147*** | F44: ="5.812" -> 5.812 | G44: ="5.875" -> 5.875 | H44: ="" | I44: ="" | J44: ="" | K44: ="" | L44: ="" | M44: ="" | N44: ="" | O44: ="" | ... AB44: ="" | AC44: ="1.775" -> 1.775 | AD44: ="1.356" -> 1.356 | AE44: =".4646" -> .4646 | AF44: ="-.6438" -> -.6438 | AG44: =".02166" -> .02166 | AH44: ="-.1308" -> -.1308 | AI44: ="" | AJ44: ="" | AK44: ="" | AL44: ="-.5424" -> -.5424 | AM44: ="-.08314" -> -.08314 | AN44: =".1789" -> .1789
A45: ="" | B45: ="" | C45: ="" | D45: ="" | E45: ="(1.884)" -> (1.884) | F45: ="(4.102)" -> (4.102) | G45: ="(3.957)" -> (3.957) | H45: ="" | I45: ="" | J45: ="" | K45: ="" | L45: ="" | M45: ="" | N45: ="" | O45: ="" | ... AB45: ="" | AC45: ="(2.98)" -> (2.98) | AD45: ="(4.188)" -> (4.188) | AE45: ="(4.171)" -> (4.171) | AF45: ="(2.477)" -> (2.477) | AG45: ="(3.284)" -> (3.284) | AH45: ="(2.91)" -> (2.91) | AI45: ="" | AJ45: ="" | AK45: ="" | AL45: ="(2.439)" -> (2.439) | AM45: ="(3.316)" -> (3.316) | AN45: ="(3.015)" -> (3.015)
A46: ="psi_c" -> psi_c | B46: ="" | C46: ="" | D46: ="" | E46: ="" | F46: ="" | G46: ="" | H46: ="1.568***" -> 1.568*** | I46: =".7281***" -> .7281*** | J46: =".7555*" -> .7555* | K46: ="" | L46: ="" | M46: ="" | N46: =".3434" -> .3434 | O46: =".4376*" -> .4376* | P46: =".8029***" -> .8029*** | Q46: ="" | R46: ="" | S46: ="" | T46: ="-.8787" -> -.8787 | U46: ="-.9902" -> -.9902 | V46: ="-.8882" -> -.8882 | W46: =".969" -> .969 | X46: =".7763" -> .7763 | Y46: =".783" -> .783 | Z46: ="" | AA46: ="" | AB46: ="" | AC46: ="" | AD46: ="" | AE46: ="" | AF46: ="" | AG46: ="" | ... AN46: =""
A47: ="" | B47: ="" | C47: ="" | D47: ="" | E47: ="" | F47: ="" | G47: ="" | H47: ="(.3725)" -> (.3725) | I47: ="(.2412)" -> (.2412) | J47: ="(.3991)" -> (.3991) | K47: ="" | L47: ="" | M47: ="" | N47: ="(.262)" -> (.262) | O47: ="(.2589)" -> (.2589) | P47: ="(.2789)" -> (.2789) | Q47: ="" | R47: ="" | S47: ="" | T47: ="(.988)" -> (.988) | U47: ="(.7093)" -> (.7093) | V47: ="(.7129)" -> (.7129) | W47: ="(.8506)" -> (.8506) | X47: ="(.9304)" -> (.9304) | Y47: ="(.6374)" -> (.6374) | Z47: ="" | AA47: ="" | AB47: ="" | AC47: ="" | AD47: ="" | AE47: ="" | AF47: ="" | AG47: ="" | ... AN47: =""
A48: ="Epsi_c" -> Epsi_c | B48: ="" | C48: ="" | D48: ="" | E48: ="" | F48: ="" | G48: ="" | H48: ="1.945" -> 1.945 | I48: ="3.47***" -> 3.47*** | J48: ="3.749***" -> 3.749*** | K48: ="" | L48: ="" | M48: ="" | N48: ="" | O48: ="" | P48: ="" | Q48: ="" | R48: ="" | ... Y48: ="" | Z48: ="-.6307" -> -.6307 | AA48: =".352" -> .352 | AB48: =".5179" -> .5179 | AC48: ="" | AD48: ="" | AE48: ="" | AF48: ="-9.904***" -> -9.904*** | AG48: ="-6.657**" -> -6.657** | AH48: ="-6.123*" -> -6.123* | AI48: ="" | AJ48: ="" | AK48: ="" | AL48: ="-10.32***" -> -10.32*** | AM48: ="-6.411" -> -6.411 | AN48: ="-5.482" -> -5.482
A49: ="" | B49: ="" | C49: ="" | D49: ="" | E49: ="" | F49: ="" | G49: ="" | H49: ="(1.796)" -> (1.796) | I49: ="(1.274)" -> (1.274) | J49: ="(1.345)" -> (1.345) | K49: ="" | L49: ="" | M49: ="" | N49: ="" | O49: ="" | P49: ="" | Q49: ="" | R49: ="" | ... Y49: ="" | Z49: ="(1.257)" -> (1.257) | AA49: ="(1.892)" -> (1.892) | AB49: ="(2.507)" -> (2.507) | AC49: ="" | AD49: ="" | AE49: ="" | AF49: ="(2.987)" -> (2.987) | AG49: ="(3.37)" -> (3.37) | AH49: ="(3.435)" -> (3.435) | AI49: ="" | AJ49: ="" | AK49: ="" | AL49: ="(3.947)" -> (3.947) | AM49: ="(4.24)" -> (4.24) | AN49: ="(3.701)" -> (3.701)
A50: ="s_psi_q1q5" -> s_psi_q1q5 | B50: ="" | C50: ="" | D50: ="" | E50: ="" | F50: ="" | G50: ="" | H50: ="" | I50: ="" | J50: ="" | K50: =".6233***" -> .6233*** | L50: =".3728***" -> .3728*** | M50: =".4292***" -> .4292*** | N50: ="" | O50: ="" | P50: ="" | Q50: ="" | R50: ="" | S50: ="" | T50: ="1.328***" -> 1.328*** | U50: ="1.04***" -> 1.04*** | V50: ="1.184***" -> 1.184*** | W50: ="-.3819" -> -.3819 | X50: ="-.1872" -> -.1872 | Y50: =".0267" -> .0267 | Z50: ="" | AA50: ="" | AB50: ="" | AC50: ="" | AD50: ="" | AE50: ="" | AF50: ="" | AG50: ="" | ... AN50: =""
A51: ="" | B51: ="" | C51: ="" | D51: ="" | E51: ="" | F51: ="" | G51: ="" | H51: ="" | ... J51: ="" | K51: ="(.1508)" -> (.1508) | L51: ="(.1035)" -> (.1035) | M51: ="(.1594)" -> (.1594) | N51: ="" | O51: ="" | P51: ="" | Q51: ="" | R51: ="" | S51: ="" | T51: ="(.451)" -> (.451) | U51: ="(.3353)" -> (.3353) | V51: ="(.3592)" -> (.3592) | W51: ="(.4016)" -> (.4016) | X51: ="(.4428)" -> (.4428) | Y51: ="(.3617)" -> (.3617) | Z51: ="" | AA51: ="" | AB51: ="" | AC51: ="" | AD51: ="" | AE51: ="" | AF51: ="" | AG51: ="" | ... AN51: =""
A52: ="Es_psi_q1q5" -> Es_psi_q1q5 | B52: ="" | C52: ="" | D52: ="" | E52: ="" | F52: ="" | G52: ="" | H52: ="" | I52: ="" | J52: ="" | K52: ="2.865***" -> 2.865*** | L52: ="2.493***" -> 2.493*** | M52: ="2.405***" -> 2.405*** | N52: ="" | O52: ="" | P52: ="" | Q52: ="" | R52: ="" | S52: ="" | T52: ="" | U52: ="" | ... AE52: ="" | AF52: ="6.413***" -> 6.413*** | AG52: ="4.811**" -> 4.811** | AH52: ="4.67*" -> 4.67* | AI52: ="" | AJ52: ="" | AK52: ="" | AL52: ="6.788***" -> 6.788*** | AM52: ="4.728*" -> 4.728* | AN52: ="4.435" -> 4.435
A53: ="" | B53: ="" | C53: ="" | D53: ="" | E53: ="" | F53: ="" | G53: ="" | H53: ="" | ... J53: ="" | K53: ="(.7099)" -> (.7099) | L53: ="(.5641)" -> (.5641) | M53: ="(.6118)" -> (.6118) | N53: ="" | O53: ="" | P53: ="" | Q53: ="" | R53: ="" | S53: ="" | T53: ="" | U53: ="" | ... AE53: ="" | AF53: ="(1.964)" -> (1.964) | AG53: ="(2.24)" -> (2.24) | AH53: ="(2.611)" -> (2.611) | AI53: ="" | AJ53: ="" | AK53: ="" | AL53: ="(2.568)" -> (2.568) | AM53: ="(2.857)" -> (2.857) | AN53: ="(2.757)" -> (2.757)
A54: ="lnmw" -> lnmw | B54: ="" | C54: ="" | D54: ="" | E54: ="" | F54: ="" | G54: ="" | H54: ="" | I54: ="" | ... AH54: ="" | AI54: =".8345***" -> .8345*** | AJ54: =".4586***" -> .4586*** | AK54: =".6111***" -> .6111*** | AL54: ="-.05337" -> -.05337 | AM54: =".00732" -> .00732 | AN54: =".007664" -> .007664
A55: ="" | B55: ="" | C55: ="" | D55: ="" | E55: ="" | F55: ="" | G55: ="" | H55: ="" | ... AH55: ="" | AI55: ="(.1298)" -> (.1298) | AJ55: ="(.1415)" -> (.1415) | AK55: ="(.1527)" -> (.1527) | AL55: ="(.1442)" -> (.1442) | AM55: ="(.1488)" -> (.1488) | AN55: ="(.1986)" -> (.1986)
A57: ="Division-CZ dummies" -> Division-CZ dummies | B57: ="No" -> No | C57: ="Yes" -> Yes | D57: ="Yes" -> Yes | E57: ="No" -> No | F57: ="Yes" -> Yes | G57: ="Yes" -> Yes | H57: ="No" -> No | I57: ="Yes" -> Yes | J57: ="Yes" -> Yes | K57: ="No" -> No | L57: ="Yes" -> Yes | M57: ="Yes" -> Yes | N57: ="No" -> No | O57: ="Yes" -> Yes | P57: ="Yes" -> Yes | Q57: ="No" -> No | R57: ="Yes" -> Yes | S57: ="Yes" -> Yes | T57: ="No" -> No | U57: ="Yes" -> Yes | V57: ="Yes" -> Yes | W57: ="No" -> No | X57: ="Yes" -> Yes | Y57: ="Yes" -> Yes | Z57: ="No" -> No | AA57: ="Yes" -> Yes | AB57: ="Yes" -> Yes | AC57: ="No" -> No | AD57: ="Yes" -> Yes | AE57: ="Yes" -> Yes | AF57: ="No" -> No | AG57: ="Yes" -> Yes | AH57: ="Yes" -> Yes | AI57: ="No" -> No | AJ57: ="Yes" -> Yes | AK57: ="Yes" -> Yes | AL57: ="No" -> No | AM57: ="Yes" -> Yes | AN57: ="Yes" -> Yes
A58: ="Region dummies" -> Region dummies | B58: ="No" -> No | C58: ="No" -> No | D58: ="Yes" -> Yes | E58: ="No" -> No | F58: ="No" -> No | G58: ="Yes" -> Yes | H58: ="No" -> No | I58: ="No" -> No | J58: ="Yes" -> Yes | K58: ="No" -> No | L58: ="No" -> No | M58: ="Yes" -> Yes | N58: ="No" -> No | O58: ="No" -> No | P58: ="Yes" -> Yes | Q58: ="No" -> No | R58: ="No" -> No | S58: ="Yes" -> Yes | T58: ="No" -> No | U58: ="No" -> No | V58: ="Yes" -> Yes | W58: ="No" -> No | X58: ="No" -> No | Y58: ="Yes" -> Yes | Z58: ="No" -> No | AA58: ="No" -> No | AB58: ="Yes" -> Yes | AC58: ="No" -> No | AD58: ="No" -> No | AE58: ="Yes" -> Yes | AF58: ="No" -> No | AG58: ="No" -> No | AH58: ="Yes" -> Yes | AI58: ="No" -> No | AJ58: ="No" -> No | AK58: ="Yes" -> Yes | AL58: ="No" -> No | AM58: ="No" -> No | AN58: ="Yes" -> Yes
A59: ="N" -> N | B59: ="60" -> 60
A60: ="r2_a" -> r2_a | B60: =".8024" -> .8024 | C60: =".8005" -> .8005 | D60: =".7995" -> .7995 | E60: =".6323" -> .6323 | F60: =".6957" -> .6957 | G60: =".6839" -> .6839 | H60: =".3184" -> .3184 | I60: =".6722" -> .6722 | J60: =".6844" -> .6844 | K60: =".5324" -> .5324 | L60: =".7623" -> .7623 | M60: =".7684" -> .7684 | N60: =".7609" -> .7609 | O60: =".7755" -> .7755 | P60: =".8077" -> .8077 | Q60: =".7556" -> .7556 | R60: =".7618" -> .7618 | S60: =".7667" -> .7667 | T60: =".3712" -> .3712 | U60: =".6566" -> .6566 | V60: =".6844" -> .6844 | W60: =".7582" -> .7582 | X60: =".7665" -> .7665 | Y60: =".7992" -> .7992 | Z60: =".7677" -> .7677 | AA60: =".7773" -> .7773 | AB60: =".7791" -> .7791 | AC60: =".7698" -> .7698 | AD60: =".7789" -> .7789 | AE60: =".7785" -> .7785 | AF60: =".8106" -> .8106 | AG60: =".7984" -> .7984 | AH60: =".7869" -> .7869 | AI60: =".3222" -> .3222 | AJ60: =".5838" -> .5838 | AK60: =".5874" -> .5874 | AL60: =".8069" -> .8069 | AM60: =".7904" -> .7904 | AN60: =".7775" -> .7775
A61: ="rmse" -> rmse | B61: =".05962" -> .05962 | C61: =".05991" -> .05991 | D61: =".06005" -> .06005 | E61: =".08132" -> .08132 | F61: =".07398" -> .07398 | G61: =".07541" -> .07541 | H61: =".1107" -> .1107 | I61: =".07678" -> .07678 | J61: =".07534" -> .07534 | K61: =".09171" -> .09171 | L61: =".06539" -> .06539 | M61: =".06454" -> .06454 | N61: =".06558" -> .06558 | O61: =".06355" -> .06355 | P61: =".05881" -> .05881 | Q61: =".0663" -> .0663 | R61: =".06546" -> .06546 | S61: =".06477" -> .06477 | T61: =".1063" -> .1063 | U61: =".0786" -> .0786 | V61: =".07534" -> .07534 | W61: =".06594" -> .06594 | X61: =".06481" -> .06481 | Y61: =".0601" -> .0601 | Z61: =".06464" -> .06464 | AA61: =".06329" -> .06329 | AB61: =".06303" -> .06303 | AC61: =".06435" -> .06435 | AD61: =".06306" -> .06306 | AE61: =".06311" -> .06311 | AF61: =".05837" -> .05837 | AG61: =".06021" -> .06021 | AH61: =".0619" -> .0619 | AI61: =".1104" -> .1104 | AJ61: =".08653" -> .08653 | AK61: =".08614" -> .08614 | AL61: =".05894" -> .05894 | AM61: =".0614" -> .0614 | AN61: =".06326" -> .06326
A65: ="Output 9b - Multivariate Regressions, Top59 100%" -> Output 9b - Multivariate Regressions, Top59 100%
A66: =""
A67: ="" | B67: Dependent Variable: "b_ajc_aj"
A69: ="alpha_c" -> alpha_c | B69: =".4782***" -> .4782*** | C69: =".5718***" -> .5718*** | D69: =".6189***" -> .6189*** | E69: ="" | F69: ="" | G69: ="" | H69: ="" | I69: ="" | J69: ="" | K69: ="" | L69: ="" | M69: ="" | N69: =".6386***" -> .6386*** | O69: =".6006***" -> .6006*** | P69: =".6119***" -> .6119*** | Q69: =".5089***" -> .5089*** | R69: =".4864***" -> .4864*** | S69: =".5079***" -> .5079*** | T69: ="" | U69: ="" | V69: ="" | W69: =".5113***" -> .5113*** | X69: =".4478***" -> .4478*** | Y69: =".4495***" -> .4495*** | Z69: ="" | AA69: ="" | AB69: ="" | AC69: ="" | AD69: ="" | AE69: ="" | AF69: ="" | AG69: ="" | ... AN69: =""
A70: ="" | B70: ="(.0932)" -> (.0932) | C70: ="(.09706)" -> (.09706) | D70: ="(.1088)" -> (.1088) | E70: ="" | F70: ="" | G70: ="" | H70: ="" | I70: ="" | J70: ="" | K70: ="" | L70: ="" | M70: ="" | N70: ="(.05771)" -> (.05771) | O70: ="(.06573)" -> (.06573) | P70: ="(.07746)" -> (.07746) | Q70: ="(.05193)" -> (.05193) | R70: ="(.105)" -> (.105) | S70: ="(.1089)" -> (.1089) | T70: ="" | U70: ="" | V70: ="" | W70: ="(.06423)" -> (.06423) | X70: ="(.1249)" -> (.1249) | Y70: ="(.1253)" -> (.1253) | Z70: ="" | AA70: ="" | AB70: ="" | AC70: ="" | AD70: ="" | AE70: ="" | AF70: ="" | AG70: ="" | ... AN70: =""
A71: ="Ealpha_c" -> Ealpha_c | B71: =".8232**" -> .8232** | C71: =".3498" -> .3498 | D71: =".2161" -> .2161 | E71: ="" | F71: ="" | G71: ="" | H71: ="" | I71: ="" | J71: ="" | K71: ="" | L71: ="" | ... Y71: ="" | Z71: ="2.87***" -> 2.87*** | AA71: ="2.894***" -> 2.894*** | AB71: ="3.053***" -> 3.053*** | AC71: ="1.686***" -> 1.686*** | AD71: ="1.617**" -> 1.617** | AE71: ="1.802***" -> 1.802*** | AF71: ="1.381**" -> 1.381** | AG71: ="1.857**" -> 1.857** | AH71: ="2.215**" -> 2.215** | AI71: ="" | AJ71: ="" | AK71: ="" | AL71: ="1.405**" -> 1.405** | AM71: ="1.794***" -> 1.794*** | AN71: ="1.871**" -> 1.871**
A72: ="" | B72: ="(.4021)" -> (.4021) | C72: ="(.4339)" -> (.4339) | D72: ="(.3515)" -> (.3515) | E72: ="" | F72: ="" | G72: ="" | H72: ="" | I72: ="" | J72: ="" | K72: ="" | L72: ="" | ... Y72: ="" | Z72: ="(.2823)" -> (.2823) | AA72: ="(.5211)" -> (.5211) | AB72: ="(.6747)" -> (.6747) | AC72: ="(.4943)" -> (.4943) | AD72: ="(.6336)" -> (.6336) | AE72: ="(.6079)" -> (.6079) | AF72: ="(.6885)" -> (.6885) | AG72: ="(.9019)" -> (.9019) | AH72: ="(.9144)" -> (.9144) | AI72: ="" | AJ72: ="" | AK72: ="" | AL72: ="(.6596)" -> (.6596) | AM72: ="(.6773)" -> (.6773) | AN72: ="(.8474)" -> (.8474)
A73: ="s_alpha_q1q5" -> s_alpha_q1q5 | B73: ="" | C73: ="" | D73: ="" | E73: ="1.2***" -> 1.2*** | F73: ="1.359***" -> 1.359*** | G73: ="1.465***" -> 1.465*** | H73: ="" | I73: ="" | J73: ="" | K73: ="" | L73: ="" | M73: ="" | N73: ="" | O73: ="" | P73: ="" | Q73: =".8927***" -> .8927*** | R73: =".6986**" -> .6986** | S73: =".7727**" -> .7727** | T73: ="" | U73: ="" | V73: ="" | W73: =".8918***" -> .8918*** | X73: =".5997**" -> .5997** | Y73: =".5677*" -> .5677* | Z73: ="" | AA73: ="" | AB73: ="" | AC73: ="" | AD73: ="" | AE73: ="" | AF73: ="" | AG73: ="" | ... AN73: =""
A74: ="" | B74: ="" | C74: ="" | D74: ="" | E74: ="(.2844)" -> (.2844) | F74: ="(.3481)" -> (.3481) | G74: ="(.3986)" -> (.3986) | H74: ="" | I74: ="" | J74: ="" | K74: ="" | L74: ="" | M74: ="" | N74: ="" | O74: ="" | P74: ="" | Q74: ="(.2036)" -> (.2036) | R74: ="(.3128)" -> (.3128) | S74: ="(.3358)" -> (.3358) | T74: ="" | U74: ="" | V74: ="" | W74: ="(.218)" -> (.218) | X74: ="(.3023)" -> (.3023) | Y74: ="(.3103)" -> (.3103) | Z74: ="" | AA74: ="" | AB74: ="" | AC74: ="" | AD74: ="" | AE74: ="" | AF74: ="" | AG74: ="" | ... AN74: =""
A75: ="Es_alpha_q1q5" -> Es_alpha_q1q5 | B75: ="" | C75: ="" | D75: ="" | E75: ="5.831***" -> 5.831*** | F75: ="3.596*" -> 3.596* | G75: ="3.639*" -> 3.639* | H75: ="" | I75: ="" | J75: ="" | K75: ="" | L75: ="" | M75: ="" | N75: ="" | O75: ="" | ... AB75: ="" | AC75: ="3.701**" -> 3.701** | AD75: ="3.306" -> 3.306 | AE75: ="2.571" -> 2.571 | AF75: ="2.382" -> 2.382 | AG75: ="1.393" -> 1.393 | AH75: =".7927" -> .7927 | AI75: ="" | AJ75: ="" | AK75: ="" | AL75: ="2.376" -> 2.376 | AM75: ="1.1" -> 1.1 | AN75: ="1.979" -> 1.979
A76: ="" | B76: ="" | C76: ="" | D76: ="" | E76: ="(.9426)" -> (.9426) | F76: ="(1.9)" -> (1.9) | G76: ="(1.986)" -> (1.986) | H76: ="" | I76: ="" | J76: ="" | K76: ="" | L76: ="" | M76: ="" | N76: ="" | O76: ="" | ... AB76: ="" | AC76: ="(1.492)" -> (1.492) | AD76: ="(2.029)" -> (2.029) | AE76: ="(2.144)" -> (2.144) | AF76: ="(1.546)" -> (1.546) | AG76: ="(2.18)" -> (2.18) | AH76: ="(2.374)" -> (2.374) | AI76: ="" | AJ76: ="" | AK76: ="" | AL76: ="(1.58)" -> (1.58) | AM76: ="(2.213)" -> (2.213) | AN76: ="(2.028)" -> (2.028)
A77: ="psi_c" -> psi_c | B77: ="" | C77: ="" | D77: ="" | E77: ="" | F77: ="" | G77: ="" | H77: ="1.078***" -> 1.078*** | I77: =".6666***" -> .6666*** | J77: =".6578" -> .6578 | K77: ="" | L77: ="" | M77: ="" | N77: =".05622" -> .05622 | O77: =".1733" -> .1733 | P77: =".3468**" -> .3468** | Q77: ="" | R77: ="" | S77: ="" | T77: ="-1.736**" -> -1.736** | U77: ="-1.781***" -> -1.781*** | V77: ="-1.729**" -> -1.729** | W77: ="-.2438" -> -.2438 | X77: ="-.3019" -> -.3019 | Y77: ="-.3102" -> -.3102 | Z77: ="" | AA77: ="" | AB77: ="" | AC77: ="" | AD77: ="" | AE77: ="" | AF77: ="" | AG77: ="" | ... AN77: =""
A78: ="" | B78: ="" | C78: ="" | D78: ="" | E78: ="" | F78: ="" | G78: ="" | H78: ="(.2874)" -> (.2874) | I78: ="(.2324)" -> (.2324) | J78: ="(.4173)" -> (.4173) | K78: ="" | L78: ="" | M78: ="" | N78: ="(.1606)" -> (.1606) | O78: ="(.1565)" -> (.1565) | P78: ="(.1629)" -> (.1629) | Q78: ="" | R78: ="" | S78: ="" | T78: ="(.8474)" -> (.8474) | U78: ="(.5587)" -> (.5587) | V78: ="(.8061)" -> (.8061) | W78: ="(.5133)" -> (.5133) | X78: ="(.5493)" -> (.5493) | Y78: ="(.4656)" -> (.4656) | Z78: ="" | AA78: ="" | AB78: ="" | AC78: ="" | AD78: ="" | AE78: ="" | AF78: ="" | AG78: ="" | ... AN78: =""
A79: ="Epsi_c" -> Epsi_c | B79: ="" | C79: ="" | D79: ="" | E79: ="" | F79: ="" | G79: ="" | H79: =".7053" -> .7053 | I79: ="1.12" -> 1.12 | J79: ="1.315" -> 1.315 | K79: ="" | L79: ="" | M79: ="" | N79: ="" | O79: ="" | P79: ="" | Q79: ="" | R79: ="" | ... Y79: ="" | Z79: ="-1.24" -> -1.24 | AA79: ="-1.649" -> -1.649 | AB79: ="-1.887" -> -1.887 | AC79: ="" | AD79: ="" | AE79: ="" | AF79: ="-4.569*" -> -4.569* | AG79: ="-5.026" -> -5.026 | AH79: ="-4.734" -> -4.734 | AI79: ="" | AJ79: ="" | AK79: ="" | AL79: ="-3.918" -> -3.918 | AM79: ="-4.713" -> -4.713 | AN79: ="-3.415" -> -3.415
A80: ="" | B80: ="" | C80: ="" | D80: ="" | E80: ="" | F80: ="" | G80: ="" | H80: ="(1.354)" -> (1.354) | I80: ="(1.072)" -> (1.072) | J80: ="(.9565)" -> (.9565) | K80: ="" | L80: ="" | M80: ="" | N80: ="" | O80: ="" | P80: ="" | Q80: ="" | R80: ="" | ... Y80: ="" | Z80: ="(.7953)" -> (.7953) | AA80: ="(1.13)" -> (1.13) | AB80: ="(1.63)" -> (1.63) | AC80: ="" | AD80: ="" | AE80: ="" | AF80: ="(2.639)" -> (2.639) | AG80: ="(3.193)" -> (3.193) | AH80: ="(3.148)" -> (3.148) | AI80: ="" | AJ80: ="" | AK80: ="" | AL80: ="(3.132)" -> (3.132) | AM80: ="(3.748)" -> (3.748) | AN80: ="(3.128)" -> (3.128)
A81: ="s_psi_q1q5" -> s_psi_q1q5 | B81: ="" | C81: ="" | D81: ="" | E81: ="" | F81: ="" | G81: ="" | H81: ="" | I81: ="" | J81: ="" | K81: =".4956***" -> .4956*** | L81: =".3813***" -> .3813*** | M81: =".4369***" -> .4369*** | N81: ="" | O81: ="" | P81: ="" | Q81: ="" | R81: ="" | S81: ="" | T81: ="1.457***" -> 1.457*** | U81: ="1.272***" -> 1.272*** | V81: ="1.352***" -> 1.352*** | W81: =".09601" -> .09601 | X81: =".2133" -> .2133 | Y81: =".3242" -> .3242 | Z81: ="" | AA81: ="" | AB81: ="" | AC81: ="" | AD81: ="" | AE81: ="" | AF81: ="" | AG81: ="" | ... AN81: =""
A82: ="" | B82: ="" | C82: ="" | D82: ="" | E82: ="" | F82: ="" | G82: ="" | H82: ="" | ... J82: ="" | K82: ="(.1451)" -> (.1451) | L82: ="(.1217)" -> (.1217) | M82: ="(.1311)" -> (.1311) | N82: ="" | O82: ="" | P82: ="" | Q82: ="" | R82: ="" | S82: ="" | T82: ="(.4049)" -> (.4049) | U82: ="(.255)" -> (.255) | V82: ="(.3658)" -> (.3658) | W82: ="(.2685)" -> (.2685) | X82: ="(.3014)" -> (.3014) | Y82: ="(.2818)" -> (.2818) | Z82: ="" | AA82: ="" | AB82: ="" | AC82: ="" | AD82: ="" | AE82: ="" | AF82: ="" | AG82: ="" | ... AN82: =""
A83: ="Es_psi_q1q5" -> Es_psi_q1q5 | B83: ="" | C83: ="" | D83: ="" | E83: ="" | F83: ="" | G83: ="" | H83: ="" | I83: ="" | J83: ="" | K83: ="1.561***" -> 1.561*** | L83: ="1.069**" -> 1.069** | M83: =".9435**" -> .9435** | N83: ="" | O83: ="" | P83: ="" | Q83: ="" | R83: ="" | S83: ="" | T83: ="" | U83: ="" | ... AE83: ="" | AF83: ="2.813*" -> 2.813* | AG83: ="2.568" -> 2.568 | AH83: ="2.172" -> 2.172 | AI83: ="" | AJ83: ="" | AK83: ="" | AL83: ="2.468" -> 2.468 | AM83: ="2.587" -> 2.587 | AN83: ="1.828" -> 1.828
A84: ="" | B84: ="" | C84: ="" | D84: ="" | E84: ="" | F84: ="" | G84: ="" | H84: ="" | ... J84: ="" | K84: ="(.5751)" -> (.5751) | L84: ="(.5257)" -> (.5257) | M84: ="(.4655)" -> (.4655) | N84: ="" | O84: ="" | P84: ="" | Q84: ="" | R84: ="" | S84: ="" | T84: ="" | U84: ="" | ... AE84: ="" | AF84: ="(1.675)" -> (1.675) | AG84: ="(1.954)" -> (1.954) | AH84: ="(2.035)" -> (2.035) | AI84: ="" | AJ84: ="" | AK84: ="" | AL84: ="(1.96)" -> (1.96) | AM84: ="(2.404)" -> (2.404) | AN84: ="(2.093)" -> (2.093)
A85: ="lnmw" -> lnmw | B85: ="" | C85: ="" | D85: ="" | E85: ="" | F85: ="" | G85: ="" | H85: ="" | I85: ="" | ... AH85: ="" | AI85: =".6017***" -> .6017*** | AJ85: =".3251***" -> .3251*** | AK85: =".4234***" -> .4234*** | AL85: =".02554" -> .02554 | AM85: ="-.003035" -> -.003035 | AN85: ="-.06759" -> -.06759
A86: ="" | B86: ="" | C86: ="" | D86: ="" | E86: ="" | F86: ="" | G86: ="" | H86: ="" | ... AH86: ="" | AI86: ="(.1026)" -> (.1026) | AJ86: ="(.1075)" -> (.1075) | AK86: ="(.1057)" -> (.1057) | AL86: ="(.1131)" -> (.1131) | AM86: ="(.1263)" -> (.1263) | AN86: ="(.1589)" -> (.1589)
A87: ="coverage" -> coverage | B87: ="" | C87: ="" | D87: ="" | E87: ="" | F87: ="" | G87: ="" | H87: ="" | I87: ="" | ... AH87: ="" | AI87: ="-.4526" -> -.4526 | AJ87: ="-.02032" -> -.02032 | AK87: ="-.02297" -> -.02297 | AL87: =".05567" -> .05567 | AM87: =".306" -> .306 | AN87: =".6509***" -> .6509***
A88: ="" | B88: ="" | C88: ="" | D88: ="" | E88: ="" | F88: ="" | G88: ="" | H88: ="" | ... AH88: ="" | AI88: ="(.3024)" -> (.3024) | AJ88: ="(.3608)" -> (.3608) | AK88: ="(.3519)" -> (.3519) | AL88: ="(.1537)" -> (.1537) | AM88: ="(.1901)" -> (.1901) | AN88: ="(.2457)" -> (.2457)
A90: ="Division-CZ dummies" -> Division-CZ dummies | B90: ="No" -> No | C90: ="Yes" -> Yes | D90: ="Yes" -> Yes | E90: ="No" -> No | F90: ="Yes" -> Yes | G90: ="Yes" -> Yes | H90: ="No" -> No | I90: ="Yes" -> Yes | J90: ="Yes" -> Yes | K90: ="No" -> No | L90: ="Yes" -> Yes | M90: ="Yes" -> Yes | N90: ="No" -> No | O90: ="Yes" -> Yes | P90: ="Yes" -> Yes | Q90: ="No" -> No | R90: ="Yes" -> Yes | S90: ="Yes" -> Yes | T90: ="No" -> No | U90: ="Yes" -> Yes | V90: ="Yes" -> Yes | W90: ="No" -> No | X90: ="Yes" -> Yes | Y90: ="Yes" -> Yes | Z90: ="No" -> No | AA90: ="Yes" -> Yes | AB90: ="Yes" -> Yes | AC90: ="No" -> No | AD90: ="Yes" -> Yes | AE90: ="Yes" -> Yes | AF90: ="No" -> No | AG90: ="Yes" -> Yes | AH90: ="Yes" -> Yes | AI90: ="No" -> No | AJ90: ="Yes" -> Yes | AK90: ="Yes" -> Yes | AL90: ="No" -> No | AM90: ="Yes" -> Yes | AN90: ="Yes" -> Yes
A91: ="Region dummies" -> Region dummies | B91: ="No" -> No | C91: ="No" -> No | D91: ="Yes" -> Yes | E91: ="No" -> No | F91: ="No" -> No | G91: ="Yes" -> Yes | H91: ="No" -> No | I91: ="No" -> No | J91: ="Yes" -> Yes | K91: ="No" -> No | L91: ="No" -> No | M91: ="Yes" -> Yes | N91: ="No" -> No | O91: ="No" -> No | P91: ="Yes" -> Yes | Q91: ="No" -> No | R91: ="No" -> No | S91: ="Yes" -> Yes | T91: ="No" -> No | U91: ="No" -> No | V91: ="Yes" -> Yes | W91: ="No" -> No | X91: ="No" -> No | Y91: ="Yes" -> Yes | Z91: ="No" -> No | AA91: ="No" -> No | AB91: ="Yes" -> Yes | AC91: ="No" -> No | AD91: ="No" -> No | AE91: ="Yes" -> Yes | AF91: ="No" -> No | AG91: ="No" -> No | AH91: ="Yes" -> Yes | AI91: ="No" -> No | AJ91: ="No" -> No | AK91: ="Yes" -> Yes | AL91: ="No" -> No | AM91: ="No" -> No | AN91: ="Yes" -> Yes
A92: ="N" -> N | B92: ="60" -> 60
A93: ="r2_a" -> r2_a | B93: =".7838" -> .7838 | C93: =".8185" -> .8185 | D93: =".8143" -> .8143 | E93: =".7425" -> .7425 | F93: =".7663" -> .7663 | G93: =".7579" -> .7579 | H93: =".241" -> .241 | I93: =".5687" -> .5687 | J93: =".5598" -> .5598 | K93: =".4488" -> .4488 | L93: =".6723" -> .6723 | M93: =".6657" -> .6657 | N93: =".7706" -> .7706 | O93: =".8207" -> .8207 | P93: =".8286" -> .8286 | Q93: =".8147" -> .8147 | R93: =".8357" -> .8357 | S93: =".8369" -> .8369 | T93: =".4109" -> .4109 | U93: =".6893" -> .6893 | V93: =".6955" -> .6955 | W93: =".8092" -> .8092 | X93: =".8317" -> .8317 | Y93: =".8424" -> .8424 | Z93: =".7147" -> .7147 | AA93: =".727" -> .727 | AB93: =".7322" -> .7322 | AC93: =".7343" -> .7343 | AD93: =".7325" -> .7325 | AE93: =".7254" -> .7254 | AF93: =".7433" -> .7433 | AG93: =".7406" -> .7406 | AH93: =".7297" -> .7297 | AI93: =".3213" -> .3213 | AJ93: =".5657" -> .5657 | AK93: =".5699" -> .5699 | AL93: =".736" -> .736 | AM93: =".7524" -> .7524 | AN93: =".7463" -> .7463
A94: ="rmse" -> rmse | B94: =".04512" -> .04512 | C94: =".04133" -> .04133 | D94: =".04181" -> .04181 | E94: =".04924" -> .04924 | F94: =".0469" -> .0469 | G94: =".04774" -> .04774 | H94: =".08453" -> .08453 | I94: =".06372" -> .06372 | J94: =".06437" -> .06437 | K94: =".07204" -> .07204 | L94: =".05555" -> .05555 | M94: =".0561" -> .0561 | N94: =".04647" -> .04647 | O94: =".04108" -> .04108 | P94: =".04018" -> .04018 | Q94: =".04177" -> .04177 | R94: =".03933" -> .03933 | S94: =".03919" -> .03919 | T94: =".07447" -> .07447 | U94: =".05408" -> .05408 | V94: =".05354" -> .05354 | W94: =".04238" -> .04238 | X94: =".03981" -> .03981 | Y94: =".03852" -> .03852 | Z94: =".05182" -> .05182 | AA94: =".0507" -> .0507 | AB94: =".05021" -> .05021 | AC94: =".05002" -> .05002 | AD94: =".05019" -> .05019 | AE94: =".05084" -> .05084 | AF94: =".04916" -> .04916 | AG94: =".04941" -> .04941 | AH94: =".05044" -> .05044 | AI94: =".07994" -> .07994 | AJ94: =".06394" -> .06394 | AK94: =".06363" -> .06363 | AL94: =".04985" -> .04985 | AM94: =".04828" -> .04828 | AN94: =".04887" -> .04887

Sheet disclosed1-12
A1: Output 12: Regression coefficients of (psi_f-psi_j) on industry experience
B3: Young subgroup | D3: Old subgroup
A4: ="" | B4: ="(1)" -> (1) | C4: ="(2)" -> (2) | D4: ="(3)" -> (3) | E4: ="(4)" -> (4)
A6: indexp | B6: 0.00119*** | C6: 0.00101*** | D6: 0.000702*** | E6: 0.000587***
B7: (0.000191) | C7: (0.0000884) | D7: (0.000118) | E7: (0.0000579)
A9: indexp^2 | B9: -0.0000328*** | C9: -0.0000293*** | D9: -0.0000161*** | E9: -0.0000160***
B10: (0.00000568) | C10: (0.00000265) | D10: (0.00000294) | E10: (0.00000162)
A12: Adjusted R2 | B12: 0.000368 | C12: 0.734 | D12: 0.000173 | E12: 0.837
A13: Mean of Dependent Variable | B13: ="-0.00216" -> -0.00216 | D13: ="0.000574" -> 0.000574
A14: SD of Dependent Variable | B14: ="0.168" -> 0.168 | D14: ="0.175" -> 0.175
A15: Mean of regressor (indexp) | B15: ="8.683" -> 8.683 | D15: ="11.92" -> 11.92
A16: SD of regressor (indexp) | B16: ="7.180" -> 7.180 | D16: ="8.759" -> 8.759
A18: ="Number of person-quarter observations" -> Number of person-quarter observations | B18: =89760000 -> 89760000 | D18: 421800000

Sheet disclosed2-1
A1: Various Estimates
B3: ="(1)" -> (1) | C3: ="(2)" -> (2)
A4: ="" | B4: ="Sample 1" -> Sample 1
A6: ="" | B6: Estimate | C6: SE
A8: meansqSE_pjc_pj | B8: ="0.0008717" -> 0.0008717
A9: meansqSE_ajc_aj | B9: ="0.0005352" -> 0.0005352
A10: meansqSE_ajc_pj | B10: ="0.00479" -> 0.00479
A11: r2_pf_ind | B11: 0.3254
A12: r2_alpha_ind | B12: 0.117
A13: sd_match | B13: 0.08904
A14: r2_alpha_firm | B14: 0.326
A15: n_f_stayers | B15: 1066000000
A16: b_af_firm | B16: 0.3856 | C16: 0.0004585
A17: b_af_h | B17: 0.1372 | C17: 0.0005794
A19: ="Person-quarter observations" -> Person-quarter observations | B19: 2505000000

Sheet disclosed2-4
A1: Variance decomposition of observed earnings and AKM components (sample 1)
B3: variance or component | C3: mean | D3: sd | F3: variance share
B4: var(y)= | C4: 0.406 | D4: 0.07771
B5: var(pe)= | C5: 0.274 | D5: 0.04263 | F5: =C5/$C$4 -> 0.67487685
B6: var(fe)= | C6: 0.04398 | D6: 0.007618 | F6: =C6/$C$4 -> 0.10832512
B7: var(xb)= | C7: 0.01874 | D7: 0.004274 | F7: =C7/$C$4 -> 0.046157635
B8: var(r)= | C8: 0.04916 | D8: 0.009355 | F8: =C8/$C$4 -> 0.12108374 | H8: reg pe on fe: | J8: cov(pe,fe) | K8: correl(pe,fe)
B9: 2cov(pe,fe)= | C9: 0.02888 | D9: 0.01908 | F9: =C9/$C$4 -> 0.071133005 | H9: =C9/(2*C6) -> 0.32833106 | J9: =+C9/2 -> 0.01444 | K9: =+J9/SQRT(C5*C6) -> 0.13154196
B10: 2cov(pe,xb)= | C10: -0.01006 | D10: 0.001818 | F10: =C10/$C$4 -> -0.024778325
B11: 2cov(pe,r)= | C11: 0 | D11: 0 | F11: =C11/$C$4 -> 0
B12: 2cov(fe,xb)= | C12: 0.001313 | D12: 0.001513 | F12: =C12/$C$4 -> 0.0032339901
B13: 2cov(fe,r)= | C13: 0 | D13: 0 | F13: =C13/$C$4 -> 0
B14: 2cov(xb,r)= | C14: 0 | D14: 0 | F14: =C14/$C$4 -> 0
B15: var(mif)= | C15: 0.007929 | D15: 0.001662
F16: =+SUM(F5:F14) -> 1.000032
C17: =C15^0.5 -> 0.089044932

Sheet L3disclosure7-2
A1: Output 2: Main decomposition AKM
B3: Sample 8
B4: Person-quarter | C4: CZ
B6: SD & Var% | C6: SD & Var%
A7: y (sd) | B7: 0.6526 | C7: 0.1467
A8: pe - variance share | B8: 0.6444 | C8: 0.3033
A9: fe - variance share | B9: 0.1166 | C9: 0.2926
A10: xb - variance share | B10: 0.04259 | C10: 0.001528
A11: r - variance share | B11: 0.1265
A12: cov(pe,fe) - variance share | B12: 0.1 | C12: 0.3824
A13: cov(pe,xb) - variance share | B13: -0.0331 | C13: 0.009799
A14: cov(pe,r) - variance share | B14: 0
A15: cov(fe,xb) - variance share | B15: 0.002885 | C15: 0.01037
A16: cov(fe,r) - variance share | B16: 0
A17: cov(xb,r) - variance share | B17: 0.000186
A18: ="Number of Person-quarter observations" -> Number of Person-quarter observations | B18: 2523000000
A23: sum of variance shares | B23: =+B8+B9+B10+B11 -> 0.93009
A24: sum of covariance shares | B24: =+SUM(B12:B17) -> 0.069971
A26: cov(pe,fe)/var(fe) | B26: =+B12/(2*B9) -> 0.42881647
A28: correl (pe,fe) | B28: =+B12/(2*SQRT(B8*B9)) -> 0.18240761

Sheet t2
A1: naics2 | B1: title | C1: size | D1: share | E1: ybar | F1: skill | G1: psi | H1: logwage | I1: educ | J1: female | K1: ind_effects_adj | L1: skill_adj | M1: wc
A2: 11 | B2: Agriculture, Forestry, Fishing and Hunting | C2: 14521500 | D2: 0.0057974318 | E2: 9.119638 | F2: -0.23639491 | G2: 0.16001994 | H2: 2.4767909 | I2: 10.751294 | J2: 0.25015509 | K2: 0.087610438 | L2: -0.19985279 | M2: 14362906
A3: 21 | B3: Mining, Quarrying, and Oil and Gas Extraction | C3: 17357000 | D3: 0.0069294511 | E3: 9.9076929 | F3: 0.078292206 | G3: 0.62160186 | H3: 3.1919909 | I3: 12.97792 | J3: 0.13971388 | K3: 0.6229651 | L3: -0.020007471 | M3: 7220964
A4: 22 | B4: Utilities | C4: 22397000 | D4: 0.008941575 | E4: 9.8835471 | F4: 0.1957944 | G4: 0.48822169 | H4: 3.3027666 | I4: 13.703637 | J4: 0.22356102 | K4: 0.60447341 | L4: 0.1092599 | M4: 10880466
A5: 23 | B5: Construction | C5: 128355000 | D5: 0.051243287 | E5: 9.4804554 | F5: 0.018735725 | G5: 0.25197944 | H5: 2.8842602 | I5: 11.975319 | J5: 0.097480118 | K5: 0.35374469 | L5: -0.058517601 | M5: 76508740
A6: 31 | B6: Manufacturing | C6: 301714000 | D6: 0.12045356 | E6: 9.4966835 | F6: -0.054122381 | G6: 0.35077908 | H6: 2.9783087 | I6: 13.042388 | J6: 0.2923328 | K6: 0.37315267 | L6: 0.016122887 | M6: 134717657
A7: 42 | B7: Wholesale Trade | C7: 130636000 | D7: 0.05215393 | E7: 9.5765202 | F7: 0.080336347 | G7: 0.29539186 | H7: 2.9691465 | I7: 13.229444 | J7: 0.30545518 | K7: 0.34781817 | L7: 0.032295261 | M7: 33440145
A8: 44 | B8: Retail Trade | C8: 217762000 | D8: 0.086937323 | E8: 9.1359558 | F8: -0.15786937 | G8: 0.10734527 | H8: 2.5829251 | I8: 12.921857 | J8: 0.49625352 | K8: 0.13417928 | L8: -0.14028744 | M8: 142576468
A9: 48 | B9: Transportation and Warehousing | C9: 100640500 | D9: 0.040178798 | E9: 9.4009981 | F9: -0.045566775 | G9: 0.24470794 | H9: 2.881074 | I9: 12.773271 | J9: 0.25708759 | K9: 0.30663061 | L9: -0.014589984 | M9: 52427096
A10: 51 | B10: Information | C10: 65171000 | D10: 0.026018279 | E10: 9.7745929 | F10: 0.1897753 | G10: 0.38970665 | H10: 3.140033 | I10: 14.506565 | J10: 0.41156489 | K10: 0.43130851 | L10: 0.11969135 | M10: 26356316
A11: 52 | B11: Finance and Insurance | C11: 142134000 | D11: 0.056744289 | E11: 9.6926854 | F11: 0.17488569 | G11: 0.31782429 | H11: 3.2271664 | I11: 14.660404 | J11: 0.58864439 | K11: 0.5190739 | L11: 0.11905921 | M11: 58418174
A12: 53 | B12: Real Estate and Rental and Leasing | C12: 38044000 | D12: 0.015188341 | E12: 9.3916469 | F12: -0.027557533 | G12: 0.22311722 | H12: 2.9364994 | I12: 13.649796 | J12: 0.46116078 | K12: 0.29658061 | L12: 0.050885566 | M12: 20490365
A13: 54 | B13: Professional, Scientific, and Technical Services | C13: 188490000 | D13: 0.075251035 | E13: 9.7950068 | F13: 0.27015549 | G13: 0.32803653 | H13: 3.3243246 | I13: 15.553283 | J13: 0.44785538 | K13: 0.47749209 | L13: 0.2577993 | M13: 79387834
... A21: 92 | B21: Public Administration | C21: 141833000 | D21: 0.056624118 | E21: 9.4710006 | F21: -0.010014789 | G21: 0.2789326 | H21: 3.1409857 | I21: 14.45152 | J21: 0.43962136 | K21: 0.42675492 | L21: 0.12519775 | M21: 61287032
B22: SD | E22: 0.22078065 | F22: 0.13721281 | G22: 0.10443362 | H22: 0.26453525 | I22: 1.2213697 | J22: 0.19657275 | K22: 0.14892778 | L22: 0.13770522

Sheet t3
A1: naics3 | B1: title | C1: size | D1: share | E1: ybar | F1: skill | G1: psi | H1: logwage | I1: educ | J1: female | K1: ind_effects_adj | L1: skill_adj | M1: wc
A2: 311 | B2: Food Manufacturing | C2: 38226000 | D2: 0.12669614 | E2: 9.2838179 | F2: -0.24407361 | G2: 0.32482625 | H2: 2.7335424 | I2: 12.086887 | J2: 0.37319934 | K2: 0.27415311 | L2: -0.12964387 | M2: 17295004
A3: 313 | B3: Textile Mills | C3: 5195000 | D3: 0.017218294 | E3: 9.1369249 | F3: -0.29171222 | G3: 0.22304441 | H3: 2.6816657 | I3: 11.989532 | J3: 0.43350798 | K3: 0.22885813 | L3: -0.1362257 | M3: 2277409
A4: 315 | B4: Apparel Manufacturing | C4: 2967000 | D4: 0.0098338164 | E4: 9.0988959 | F4: -0.22897443 | G4: 0.1466246 | H4: 2.6062412 | I4: 11.578188 | J4: 0.61511457 | K4: 0.14716405 | L4: -0.12995601 | M4: 2601504
A5: 321 | B5: Wood Product Manufacturing | C5: 7963000 | D5: 0.026392544 | E5: 9.2031955 | F5: -0.22424467 | G5: 0.2177352 | H5: 2.6943402 | I5: 11.928318 | J5: 0.16122204 | K5: 0.21257707 | L5: -0.10726997 | M5: 3622780
A6: 322 | B6: Paper Manufacturing | C6: 10152000 | D6: 0.033647761 | E6: 9.5325463 | F6: -0.095454685 | G6: 0.42831864 | H6: 3.0220149 | I6: 12.846048 | J6: 0.24867505 | K6: 0.43684211 | L6: -0.0038604476 | M6: 3497460
A7: 323 | B7: Printing and Related Support Activities | C7: 10570000 | D7: 0.035033178 | E7: 9.282 | F7: -0.12726025 | G7: 0.2163 | H7: 2.8477404 | I7: 12.888768 | J7: 0.35081956 | K7: 0.26059794 | L7: -0.0018905663 | M7: 4806987
A8: 324 | B8: Petroleum and Coal Products Manufacturing | C8: 3269000 | D8: 0.010834764 | E8: 10.05 | F8: 0.21973975 | G8: 0.6214 | H8: 3.3867798 | I8: 13.691823 | J8: 0.18387558 | K8: 0.69355416 | L8: 0.10419235 | M8: 1826719
A9: 325 | B9: Chemical Manufacturing | C9: 21503000 | D9: 0.071269482 | E9: 9.7771006 | F9: 0.10552467 | G9: 0.46533688 | H9: 3.2505882 | I9: 14.196547 | J9: 0.35436809 | K9: 0.51985294 | L9: 0.14170207 | M9: 11593645
A10: 326 | B10: Plastics and Rubber Products Manufacturing | C10: 16766000 | D10: 0.055569183 | E10: 9.3204719 | F10: -0.19119857 | G10: 0.30308083 | H10: 2.832309 | I10: 12.53906 | J10: 0.29301789 | K10: 0.30486643 | L10: -0.06159072 | M10: 4854441
A11: 327 | B11: Nonmetallic Mineral Product Manufacturing | C11: 9493000 | D11: 0.031463571 | E11: 9.4204772 | F11: -0.12425814 | G11: 0.33743568 | H11: 2.8930769 | I11: 12.439256 | J11: 0.19521177 | K11: 0.33702356 | L11: -0.032979824 | M11: 3661429
A12: 331 | B12: Primary Metal Manufacturing | C12: 10323000 | D12: 0.034214523 | E12: 9.565383 | F12: -0.11686336 | G12: 0.48025375 | H12: 2.9863079 | I12: 12.579591 | J12: 0.14414538 | K12: 0.42135847 | L12: -0.024083862 | M12: 4589318
A13: 332 | B13: Fabricated Metal Product Manufacturing | C13: 33973000 | D13: 0.11260001 | E13: 9.3863793 | F13: -0.0951076 | G13: 0.2831072 | H13: 2.8808997 | I13: 12.459981 | J13: 0.18958171 | K13: 0.32188016 | L13: -0.030013798 | M13: 10481987
... A19: 339 | B19: Miscellaneous Manufacturing | C19: 14025000 | D19: 0.046484418 | E19: 9.4247356 | F19: -0.054513298 | G19: 0.28289634 | H19: 2.9238293 | I19: 13.095994 | J19: 0.36675581 | K19: 0.31435332 | L19: 0.020442761 | M19: 14619962
B20: SD | E20: 0.21787692 | F20: 0.15339325 | G20: 0.087248246 | H20: 0.20961528 | I20: 0.8339653 | J20: 0.089679688 | K20: 0.10914908 | L20: 0.10943842

Sheet t4
A2: ="" | B2: ="(1)" -> (1) | C2: ="(2)" -> (2) | D2: ="(3)" -> (3) | E2: ="(4)" -> (4) | F2: ="(5)" -> (5) | G2: ="(6)" -> (6) | H2: ="(7)" -> (7) | I2: ="(8)" -> (8)
A3: ="" | B3: ="alpha_j" -> alpha_j | C3: ="psi_j" -> psi_j | D3: ="alpha_j" -> alpha_j | E3: ="alpha" -> alpha | F3: ="alpha" -> alpha | G3: ="alpha" -> alpha | H3: ="alphahat" -> alphahat | I3: ="alphar" -> alphar
A5: ="y_j" -> y_j | B5: ="0.6185" -> 0.6185 | C5: ="0.3722" -> 0.3722 | D5: ="" | E5: ="" | F5: ="" | G5: ="" | H5: ="" | I5: =""
A6: ="" | B6: ="(0.0194)" -> (0.0194) | C6: ="(0.0183)" -> (0.0183) | D6: ="" | E6: ="" | F6: ="" | G6: ="" | H6: ="" | I6: =""
A8: ="psi_j" -> psi_j | B8: ="" | C8: ="" | D8: ="0.9012" -> 0.9012 | E8: ="0.9005" -> 0.9005 | F8: ="" | G8: ="0.3299" -> 0.3299 | H8: ="0.6587" -> 0.6587 | I8: ="0.2418" -> 0.2418
A9: ="" | B9: ="" | C9: ="" | D9: ="(0.1226)" -> (0.1226) | E9: ="(0.1227)" -> (0.1227) | F9: ="" | G9: ="(0.0997)" -> (0.0997) | H9: ="(0.1538)" -> (0.1538) | I9: ="(0.0827)" -> (0.0827)
A11: ="skill_m3" -> skill_m3 | B11: ="" | C11: ="" | D11: ="" | E11: ="" | F11: ="1.0410" -> 1.0410 | G11: ="0.9017" -> 0.9017 | H11: ="" | I11: =""
A12: ="" | B12: ="" | C12: ="" | D12: ="" | E12: ="" | F12: ="(0.0698)" -> (0.0698) | G12: ="(0.0838)" -> (0.0838) | H12: ="" | I12: =""
A14: ="_cons" -> _cons | B14: ="3.6212" -> 3.6212 | C14: ="-3.2754" -> -3.2754 | D14: ="9.2440" -> 9.2440 | E14: ="9.2441" -> 9.2441 | F14: ="6.4394" -> 6.4394 | G14: ="6.7653" -> 6.7653 | H14: ="9.3010" -> 9.3010 | I14: ="-0.0569" -> -0.0569
A15: ="" | B15: ="(0.1828)" -> (0.1828) | C15: ="(0.1726)" -> (0.1726) | D15: ="(0.0357)" -> (0.0357) | E15: ="(0.0357)" -> (0.0357) | F15: ="(0.1957)" -> (0.1957) | G15: ="(0.2234)" -> (0.2234) | H15: ="(0.0501)" -> (0.0501) | I15: ="(0.0256)" -> (0.0256)
A17: ="N" -> N | B17: ="311" -> 311 | C17: ="311" -> 311 | D17: ="311" -> 311 | E17: ="310" -> 310 | F17: ="310" -> 310 | G17: ="310" -> 310 | H17: ="310" -> 310 | I17: ="310" -> 310
A18: ="R-sq" -> R-sq | B18: ="0.867" -> 0.867 | C18: ="0.717" -> 0.717 | D18: ="0.356" -> 0.356 | E18: ="0.355" -> 0.355 | F18: ="0.712" -> 0.712 | G18: ="0.747" -> 0.747 | H18: ="0.267" -> 0.267 | I18: ="0.089" -> 0.089
A20: ="Standard errors in parentheses" -> Standard errors in parentheses

Sheet t6
A2: ="" | B2: ="(1)" -> (1) | C2: ="(2)" -> (2) | D2: ="(3)" -> (3) | E2: ="(4)" -> (4) | F2: ="(5)" -> (5) | G2: ="(6)" -> (6)
A3: ="" | B3: ="ind_effects_m1" -> ind_effects_m1 | C3: ="ind_effects_m2" -> ind_effects_m2 | D3: ="ind_effects_m3" -> ind_effects_m3 | E3: ="ind_effects_m1" -> ind_effects_m1 | F3: ="ind_effects_m2" -> ind_effects_m2 | G3: ="ind_effects_m3" -> ind_effects_m3
A5: ="psi_j" -> psi_j | B5: ="1.2390" -> 1.2390 | C5: ="1.1686" -> 1.1686 | D5: ="1.1659" -> 1.1659 | E5: ="1.2390" -> 1.2390 | F5: ="1.1686" -> 1.1686 | G5: ="1.1659" -> 1.1659
A6: ="" | B6: ="(0.0728)" -> (0.0728) | C6: ="(0.0639)" -> (0.0639) | D6: ="(0.0571)" -> (0.0571) | E6: ="(0.0523)" -> (0.0523) | F6: ="(0.0460)" -> (0.0460) | G6: ="(0.0424)" -> (0.0424)
A8: ="_cons" -> _cons | B8: ="-0.2524" -> -0.2524 | C8: ="-0.2395" -> -0.2395 | D8: ="-0.2391" -> -0.2391 | E8: ="-0.2524" -> -0.2524 | F8: ="-0.2395" -> -0.2395 | G8: ="-0.2391" -> -0.2391
A9: ="" | B9: ="(0.0173)" -> (0.0173) | C9: ="(0.0163)" -> (0.0163) | D9: ="(0.0156)" -> (0.0156) | E9: ="(0.0139)" -> (0.0139) | F9: ="(0.0122)" -> (0.0122) | G9: ="(0.0113)" -> (0.0113)
A11: ="N" -> N | B11: ="310" -> 310 | C11: ="310" -> 310 | D11: ="310" -> 310 | E11: ="310" -> 310 | F11: ="310" -> 310 | G11: ="310" -> 310
A12: ="R-sq" -> R-sq | B12: ="0.645" -> 0.645 | C12: ="0.677" -> 0.677 | D12: ="0.710" -> 0.710 | E12: ="0.645" -> 0.645 | F12: ="0.677" -> 0.677 | G12: ="0.710" -> 0.710
A13: ="adj. R-sq" -> adj. R-sq | B13: ="0.644" -> 0.644 | C13: ="0.676" -> 0.676 | D13: ="0.709" -> 0.709 | E13: ="0.644" -> 0.644 | F13: ="0.676" -> 0.676 | G13: ="0.709" -> 0.709
A14: ="sdy" -> sdy | B14: ="0.1887" -> 0.1887 | C14: ="0.1737" -> 0.1737 | D14: ="0.1692" -> 0.1692 | E14: ="0.1887" -> 0.1887 | F14: ="0.1737" -> 0.1737 | G14: ="0.1692" -> 0.1692
A15: ="sdpsi" -> sdpsi | B15: ="0.1223" -> 0.1223 | C15: ="0.1223" -> 0.1223 | D15: ="0.1223" -> 0.1223 | E15: ="0.1223" -> 0.1223 | F15: ="0.1223" -> 0.1223 | G15: ="0.1223" -> 0.1223
A17: ="Standard errors in parentheses" -> Standard errors in parentheses

Sheet apptab2
A1: ybar | B1: alpha_adj | C1: psi | D1: title | E1: naics | F1: share
A2: 9.4336428 | B2: 9.4562602 | C2: 0.23558897 | D2: Mean
A3: 0.27829195 | B3: 0.18484385 | C3: 0.12233035 | D3: SD
A4: 9.216 | B4: -0.14526024 | C4: 0.1524 | D4: Oilseed and Grain Farming | E4: 1111 | F4: 0.00030141935
A5: 9.12 | B5: -0.21326025 | C5: 0.1545 | D5: Vegetable and Melon Farming | E5: 1112 | F5: 0.0004247817
A6: 9.013 | B6: -0.27026024 | C6: 0.1043 | D6: Fruit and Tree Nut Farming | E6: 1113 | F6: 0.00060882716
A7: 9.032 | B7: -0.26326025 | C7: 0.1021 | D7: Greenhouse, Nursery, and Floriculture Production | E7: 1114 | F7: 0.00080964033
A8: 9.113 | B8: -0.21526025 | C8: 0.1306 | D8: Other Crop Farming | E8: 1119 | F8: 0.00033735012
A9: 9.108 | B9: -0.27126026 | C9: 0.1771 | D9: Cattle Ranching and Farming | E9: 1121 | F9: 0.00079646567
A10: 9.159 | B10: -0.32026026 | C10: 0.2593 | D10: Hog and Pig Farming | E10: 1122 | F10: 0.00022516624
A11: 9.143 | B11: -0.30726025 | C11: 0.2355 | D11: Poultry and Egg Production | E11: 1123 | F11: 0.00029423318
A12: 9.019 | B12: -0.25426024 | C12: 0.08397 | D12: Sheep and Goat Farming | E12: 1124 | F12: 6.9865409e-06
A13: 9.185 | B13: -0.15226024 | C13: 0.1408 | D13: Aquaculture | E13: 1125 | F13: 4.3116939e-05
A14: 9.15 | B14: -0.22926025 | C14: 0.1739 | D14: Other Animal Production | E14: 1129 | F14: 0.0001161762
A15: 9.555 | B15: 0.075739756 | C15: 0.2839 | D15: Timber Tract Operations | E15: 1131 | F15: 2.9343473e-05
... A163: 9.01 | B163: -0.20826025 | C163: 0.04634 | D163: Book Stores and News Dealers | E163: 4512 | F163: 0.00036050551
A164: 8.979 | B164: -0.25426024 | C164: 0.06735 | E164: 4521 | F164: 0.0065433946
A165: 8.947 | B165: -0.30126023 | C165: 0.05153 | E165: 4529 | F165: 0.010902996
A166: 8.9 | B166: -0.22126025 | C166: -0.06354 | D166: Florists | E166: 4531 | F166: 0.0002311547
A167: 9.154 | B167: -0.13526024 | C167: 0.1105 | D167: Office Supplies, Stationery, and Gift Stores | E167: 4532 | F167: 0.0012795351
A168: 8.892 | B168: -0.32526025 | C168: 0.02459 | D168: Used Merchandise Stores | E168: 4533 | F168: 0.00064595562
A169: 9.117 | B169: -0.15526025 | C169: 0.08517 | D169: Other Miscellaneous Store Retailers | E169: 4539 | F169: 0.0015226668
A170: 9.454 | B170: 0.015739754 | C170: 0.2424 | D170: Electronic Shopping and Mail-Order Houses | E170: 4541 | F170: 0.002565857
A171: 9.096 | B171: -0.23826024 | C171: 0.1349 | D171: Vending Machine Operators | E171: 4542 | F171: 0.00027427165
A172: 9.359 | B172: -0.067260243 | C172: 0.2292 | D172: Direct Selling Establishments | E172: 4543 | F172: 0.0010871058
A173: 9.627 | B173: 0.24973975 | C173: 0.1883 | D173: Scheduled Air Transportation | E173: 4811 | F173: 0.0042438246
A174: 9.745 | B174: 0.24673976 | C174: 0.2926 | D174: Nonscheduled Air Transportation | E174: 4812 | F174: 0.00037288168
A175: 9.485 | B175: -0.010260247 | C175: 0.3382 | D175: Rail Transportation | E175: 4821 | F175: 1.0779235e-05
A176: 9.746 | B176: 0.18173975 | C176: 0.3775 | D176: Deep Sea, Coastal, and Great Lakes Water Transportation | E176: 4831 | F176: 0.00040362246
A177: 9.706 | B177: 0.073739752 | C177: 0.4288 | D177: Inland Water Transportation | E177: 4832 | F177: 0.00025670548
... A207: 9.766 | B207: 0.17073976 | C207: 0.4109 | D207: Cable and Other Subscription Programming | E207: 5152 | F207: 0.00070104952
A208: 9.746 | B208: 0.052739754 | C208: 0.489 | E208: 5171 | F208: 0.0063517638
A209: 9.661 | B209: 0.015739754 | C209: 0.4575 | E209: 5172 | F209: 0.0014559951
A210: 9.873 | B210: 0.25973976 | C210: 0.4285 | D210: Satellite Telecommunications | E210: 5174 | F210: 0.00010100543
A211: 9.765 | B211: 0.15673976 | C211: 0.4207 | D211: Other Telecommunications | E211: 5179 | F211: 0.0009038588
A212: 9.806 | B212: 0.24573976 | C212: 0.3514 | D212: Data Processing, Hosting, and Related Services | E212: 5182 | F212: 0.002800605
A213: 9.875 | B213: 0.28973976 | C213: 0.3913 | D213: Other Information Services | E213: 5191 | F213: 0.0029028081
A214: 10.03 | B214: 0.42573977 | C214: 0.4103 | D214: Monetary Authorities-Central Bank | E214: 5211 | F214: 0.00021478624
A215: 9.493 | B215: 0.044739753 | C215: 0.2557 | D215: Depository Credit Intermediation | E215: 5221 | F215: 0.017111037
A216: 9.663 | B216: 0.12073975 | C216: 0.3315 | D216: Nondepository Credit Intermediation | E216: 5222 | F216: 0.0057369485
A217: 9.602 | B217: 0.089739755 | C217: 0.3061 | D217: Activities Related to Credit Intermediation | E217: 5223 | F217: 0.0026664634
A218: 10.27 | B218: 0.66373974 | C218: 0.4219 | D218: Securities and Commodity Contracts Intermediation and Brokerage | E218: 5231 | F218: 0.0047668172
A219: 10.34 | B219: 0.64373976 | C219: 0.5108 | D219: Securities and Commodity Exchanges | E219: 5232 | F219: 7.2260795e-05
A220: 10.15 | B220: 0.52173978 | C220: 0.4254 | D220: Other Financial Investment Activities | E220: 5239 | F220: 0.0040681632
A221: 9.718 | B221: 0.14373976 | C221: 0.3685 | D221: Insurance Carriers | E221: 5241 | F221: 0.01275942
... A314: 9.267 | B314: -0.12626025 | C314: 0.1927 | D314: National Security and International Affairs | E314: 9281 | F314: 0.00016168853
